Workbook

Sheet Painel
L1: aux
B2: PAINEL DE QUANTIDADES E VALORES POR TRECHO – PR-990 | L2: x | M2: =MIN(MAX(E7+F7/20,0),Estacas!$B$650) -> 0 | N2: =MIN(MAX(E8+F8/20,0),Estacas!$B$650) -> 642.79085
B3: Rodovia PR-990 · entre a PR-364 e Rebouças · km 0+000 a 12+883,96 · Est. 0+0,00 a 642+15,817 · quantidades das memórias do projeto e valores da planilha contratual (R$ 87.300.000,00) | L3: linha | M3: =MIN(MATCH(M2,Estacas!$B$1:$B$650,1),649) -> 2 | N3: =MIN(MATCH(N2,Estacas!$B$1:$B$650,1),649) -> 649
L4: t | M4: =MIN(1,MAX(0,(M2-INDEX(Estacas!$B$1:$B$650,M3))/(INDEX(Estacas!$B$1:$B$650,M3+1)-INDEX(Estacas!$B$1:$B$650,M3)))) -> 0 | N4: =MIN(1,MAX(0,(N2-INDEX(Estacas!$B$1:$B$650,N3))/(INDEX(Estacas!$B$1:$B$650,N3+1)-INDEX(Estacas!$B$1:$B$650,N3)))) -> 1
B5: SELECIONE O TRECHO | H5: PREMISSAS (editáveis) | L5: L | M5: =INDEX('Volumes por intervalo'!$C$1:$C$650,M3) -> 20 | N5: =INDEX('Volumes por intervalo'!$C$1:$C$650,N3) -> 5.817
E6: Estaca | F6: + metros | G6: Notação | H6: 0.048 | I6: Teor de CAP executado no CBUQ (contrato 5,7%) – ajusta o item 589000 | L6: erro | N6: =IF(E8+F8/20<=E7+F7/20,"A estaca final deve ser maior que a inicial",IF(E8+F8/20>Estacas!B650+0.00001,"Estaca final além do fim do trecho (642+15,817)",""))
B7: Estaca inicial | E7: 0 | F7: 0 | G7: =E7&"+"&FIXED(F7,2) -> 0+0.00 | H7: 1.2 | I7: Taxa de EAI na imprimação (kg/m²) | L7: ext. sel. | N7: =IF($N$6<>"",0,(N2-M2)*20) -> 12855.817
B8: Estaca final | E8: 642 | F8: 15.817 | G8: =E8&"+"&FIXED(F8,2) -> 642+15.82 | H8: 0.5 | I8: Taxa de RR-1C na pintura de ligação (kg/m²) | L8: ext. total | N8: =Estacas!$B$650*20 -> 12855.817
B9: Digite só nas células amarelas. Ex.: 100 a 108 → 100 / 0 e 108 / 0 · estaca 100+10 → 100 / 10 · trecho inteiro → 0 / 0 e 642 / 15,817 | H9: =Parâmetros!$C$14 -> 2.4 | I9: Densidade do CBUQ (t/m³) – vem de Parâmetros | L9: fração | N9: =IF(N8=0,0,N7/N8) -> 1
B10: =IF($N$6="","","⚠ "&$N$6) | L10: CAP contrato | N10: 0.057
B12: RESUMO DO TRECHO | L12: full | M12: =0 -> 0 | N12: =Estacas!$B$650 -> 642.79085
B13: EXTENSÃO | E13: CBUQ | G13: CORTE (1ª+2ª+3ª) | I13: CONSUMO REAL (PROJETO) | M13: =MIN(MATCH(M12,Estacas!$B$1:$B$650,1),649) -> 2 | N13: =MIN(MATCH(N12,Estacas!$B$1:$B$650,1),649) -> 649 | P13: AJUSTADO AO CONTRATO
B14: =$N$7 -> 12855.817 | E14: =G102 -> 17868.573 | G14: =G49+G63+G68 -> 307366.46 | I14: =J478 -> 85313984 | M14: =MIN(1,MAX(0,(M12-INDEX(Estacas!$B$1:$B$650,M13))/(INDEX(Estacas!$B$1:$B$650,M13+1)-INDEX(Estacas!$B$1:$B$650,M13)))) -> 0 | N14: =MIN(1,MAX(0,(N12-INDEX(Estacas!$B$1:$B$650,N13))/(INDEX(Estacas!$B$1:$B$650,N13+1)-INDEX(Estacas!$B$1:$B$650,N13)))) -> 1 | P14: =P478 -> 87300000
B15: =G7&" → "&G8 -> 0+0.00 → 642+15.82 | E15: =FIXED(G101,0)&" m³ compactados" -> 7,445 m³ compactados | G15: volume geométrico | I15: quantidades encontradas × preço do contrato | M15: =INDEX('Volumes por intervalo'!$C$1:$C$650,M13) -> 20 | N15: =INDEX('Volumes por intervalo'!$C$1:$C$650,N13) -> 5.817 | P15: ="real − ajustado: R$ "&FIXED(J478-P478,2)&" ("&FIXED(IF(P478=0,0,(J478/P478-1)*100),1)&"%)" -> real − ajustado: R$ -1,986,016.05 (-2.3%)
B17: DADOS DO TRECHO
B18: Estaca inicial / final | E18: =G7&" → "&G8 -> 0+0.00 → 642+15.82 | G18: Seção tipo (início / fim) | I18: =INDEX(Estacas!$E$1:$E$650,M3)&" / "&INDEX(Estacas!$E$1:$E$650,N3) -> T01 / T09*
B19: Extensão | E19: =$N$7 -> 12855.817 | G19: Segmento (início / fim) | I19: =INDEX(Estacas!$D$1:$D$650,M3)&" / "&INDEX(Estacas!$D$1:$D$650,N3) -> S01 / S13
B20: Largura média do CBUQ acabado | E20: =IF(OR($N$6<>"",$N$7=0),0,((INDEX(Estacas!$S$1:$S$650,N3)+N5*N4*(2*INDEX(Estacas!$F$1:$F$650,N3)+(INDEX(Estacas!$F$1:$F$650,N3+1)-INDEX(Estacas!$F$1:$F$650,N3))*N4)/2*1)-(INDEX(Estacas!$S$1:$S$650,M3)+M5*M4*(2*INDEX(Estacas!$F$1:$F$650,M3)+(INDEX(Estacas!$F$1:$F$650,M3+1)-INDEX(Estacas!$F$1:$F$650,M3))*M4)/2*1))/$N$7) -> 11.532677 | G20: Cota de projeto (início / fim) | I20: =IF($N$6<>"","",FIXED(G483,2)&" / "&FIXED(G484,2)&" m") -> 846.29 / 796.61 m
B21: Área de CBUQ acabado | E21: =IF($N$6<>"",0,(INDEX(Estacas!$S$1:$S$650,N3)+N5*N4*(2*INDEX(Estacas!$F$1:$F$650,N3)+(INDEX(Estacas!$F$1:$F$650,N3+1)-INDEX(Estacas!$F$1:$F$650,N3))*N4)/2*1)-(INDEX(Estacas!$S$1:$S$650,M3)+M5*M4*(2*INDEX(Estacas!$F$1:$F$650,M3)+(INDEX(Estacas!$F$1:$F$650,M3+1)-INDEX(Estacas!$F$1:$F$650,M3))*M4)/2*1)) -> 148261.99 | G21: Rampa média | I21: =IF($N$6<>"","",G486/100) -> -0.0038640144
B23: RESUMO POR DISCIPLINA
B24: # | C24: Disciplina (clique para ir ao detalhe) | E24: Itens | F24: % do saldo | G24: Ajustado ao contrato (R$) | I24: Consumo real (R$) | K24: Real − ajustado
B25: 1 | C25: =HYPERLINK("#'Painel'!B42","Terraplenagem") -> Terraplenagem | E25: =COUNTIF(J43:J89,">0")&"/"&COUNT(J43:J89) -> 39/39 | F25: =IF($I$37=0,0,I25/$I$37) -> 0.20316531 | G25: =O90 -> 17469094 | I25: =J90 -> 17332842 | K25: =I25-G25 -> -136251.38
B26: 2 | C26: =HYPERLINK("#'Painel'!B92","Pavimentação") -> Pavimentação | E26: =COUNTIF(J93:J108,">0")&"/"&COUNT(J93:J108) -> 11/11 | F26: =IF($I$37=0,0,I26/$I$37) -> 0.31594894 | G26: =O109 -> 27855986 | I26: =J109 -> 26954862 | K26: =I26-G26 -> -901123.89
B27: 3 | C27: =HYPERLINK("#'Painel'!B111","Ligantes betuminosos") -> Ligantes betuminosos | E27: =COUNTIF(J112:J114,">0")&"/"&COUNT(J112:J114) -> 3/3 | F27: =IF($I$37=0,0,I27/$I$37) -> 0.07185893 | G27: =O115 -> 7400006.8 | I27: =J115 -> 6130571.6 | K27: =I27-G27 -> -1269435.2
B28: 4 | C28: =HYPERLINK("#'Painel'!B117","Drenagem e OAC") -> Drenagem e OAC | E28: =COUNTIF(J118:J261,">0")&"/"&COUNT(J118:J261) -> 68/68 | F28: =IF($I$37=0,0,I28/$I$37) -> 0.17733818 | G28: =O262 -> 16405945 | I28: =J262 -> 15129427 | K28: =I28-G28 -> -1276518.1
B29: 5 | C29: =HYPERLINK("#'Painel'!B264","Galerias e passa-fauna") -> Galerias e passa-fauna | E29: =COUNTIF(J265:J299,">0")&"/"&COUNT(J265:J299) -> 21/21 | F29: =IF($I$37=0,0,I29/$I$37) -> 0.03053132 | G29: =O300 -> 2796171.7 | I29: =J300 -> 2604748.6 | K29: =I29-G29 -> -191423.16
B30: 6 | C30: =HYPERLINK("#'Painel'!B302","OAE – ponte") -> OAE – ponte | E30: =COUNTIF(J303:J333,">0")&"/"&COUNT(J303:J333) -> 28/28 | F30: =IF($I$37=0,0,I30/$I$37) -> 0.026777918 | G30: =O334 -> 2284530.8 | I30: =J334 -> 2284530.8 | K30: =I30-G30 -> 0.0669
B31: 7 | C31: =HYPERLINK("#'Painel'!B336","Contenções") -> Contenções | E31: =COUNTIF(J337:J345,">0")&"/"&COUNT(J337:J345) -> 7/7 | F31: =IF($I$37=0,0,I31/$I$37) -> 0.0080443863 | G31: =O346 -> 687970.09 | I31: =J346 -> 686298.65 | K31: =I31-G31 -> -1671.445
B32: 8 | C32: =HYPERLINK("#'Painel'!B348","Sinalização") -> Sinalização | E32: =COUNTIF(J349:J374,">0")&"/"&COUNT(J349:J374) -> 19/19 | F32: =IF($I$37=0,0,I32/$I$37) -> 0.050910435 | G32: =O375 -> 4392206.5 | I32: =J375 -> 4343372.1 | K32: =I32-G32 -> -48834.425
B33: 9 | C33: =HYPERLINK("#'Painel'!B377","Iluminação") -> Iluminação | E33: =COUNTIF(J378:J401,">0")&"/"&COUNT(J378:J401) -> 21/21 | F33: =IF($I$37=0,0,I33/$I$37) -> 0.0031632706 | G33: =O402 -> 269878.86 | I33: =J402 -> 269871.22 | K33: =I33-G33 -> -7.644
B34: 10 | C34: =HYPERLINK("#'Painel'!B404","Paisagismo") -> Paisagismo | E34: =COUNTIF(J405:J411,">0")&"/"&COUNT(J405:J411) -> 3/3 | F34: =IF($I$37=0,0,I34/$I$37) -> 0.02557292 | G34: =O412 -> 2503353.6 | I34: =J412 -> 2181727.7 | K34: =I34-G34 -> -321625.9
B35: 11 | C35: =HYPERLINK("#'Painel'!B414","Obras complementares") -> Obras complementares | E35: =COUNTIF(J415:J442,">0")&"/"&COUNT(J415:J442) -> 25/25 | F35: =IF($I$37=0,0,I35/$I$37) -> 0.029406624 | G35: =O443 -> 2013395.8 | I35: =J443 -> 2508796.3 | K35: =I35-G35 -> 495400.46
B36: 12 | C36: =HYPERLINK("#'Painel'!B445","Serviços gerais e interferências") -> Serviços gerais e interferências | E36: =COUNTIF(J446:J475,">0")&"/"&COUNT(J446:J475) -> 24/24 | F36: =IF($I$37=0,0,I36/$I$37) -> 0.057281764 | G36: =O476 -> 3221460.9 | I36: =J476 -> 4886935.5 | K36: =I36-G36 -> 1665474.6
C37: Total | F37: =SUM(F25:F36) -> 1 | G37: =SUM(G25:G36) -> 87300000 | I37: =SUM(I25:I36) -> 85313984 | K37: =I37-G37 -> -1986016
B39: DETALHAMENTO POR SERVIÇO | E39: LE / LD / Projeto = quantidades das memórias do projeto · Contrato = quantidade contratual distribuída pelo critério da última coluna
E40: QUANTIDADES DO PROJETO | H40: CONSUMO REAL ENCONTRADO NO PROJETO | K40: AJUSTADO AO CONTRATO | Q40: DIFERENÇA
B41: Código | C41: Serviço | D41: Un | E41: LE | F41: LD | G41: Projeto no trecho | H41: Qtd. real | I41: Preço contrato (R$) | J41: Valor real (R$) | K41: Qtd. ajustada | P41: Valor ajustado (R$) | Q41: Real − ajustado (R$) | R41: Base da quantidade · critério / fonte
B42: 1 · TERRAPLENAGEM
C43: Limpeza
B44: 400000 | C44: Desmatamento e limpeza (árvores Ø até 30 cm) | D44: m² | G44: =IF($N$6<>"",0,SUMPRODUCT('Terraplenagem por estaca'!$E$2:$E$744,((('Terraplenagem por estaca'!$D$2:$D$744<$N$2)*'Terraplenagem por estaca'!$D$2:$D$744+('Terraplenagem por estaca'!$D$2:$D$744>=$N$2)*$N$2)-(('Terraplenagem por estaca'!$C$2:$C$744>$M$2)*'Terraplenagem por estaca'!$C$2:$C$744+('Terraplenagem por estaca'!$C$2:$C$744<=$M$2)*$M$2))*('Terraplenagem por estaca'!$C$2:$C$744<$N$2)*('Terraplenagem por estaca'!$D$2:$D$744>$M$2)/('Terraplenagem por estaca'!$D$2:$D$744-'Terraplenagem por estaca'!$C$2:$C$744))+SUMPRODUCT('Terrapl. – ramos e solo mole'!$E$2:$E$14,((('Terrapl. – ramos e solo mole'!$C$2:$C$14<$N$2)*'Terrapl. – ramos e solo mole'!$C$2:$C$14+('Terrapl. – ramos e solo mole'!$C$2:$C$14>=$N$2)*$N$2)-(('Terrapl. – ramos e solo mole'!$B$2:$B$14>$M$2)*'Terrapl. – ramos e solo mole'!$B$2:$B$14+('Terrapl. – ramos e solo mole'!$B$2:$B$14<=$M$2)*$M$2))*('Terrapl. – ramos e solo mole'!$B$2:$B$14<$N$2)*('Terrapl. – ramos e solo mole'!$C$2:$C$14>$M$2)/('Terrapl. – ramos e solo mole'!$C$2:$C$14-'Terrapl. – ramos e solo mole'!$B$2:$B$14))/Parâmetros!$C$22) -> 236317.35 | H44: =IF($N$6<>"",0,$G$44) -> 236317.35 | I44: 1.25 | J44: =H44*I44 -> 295396.69 | K44: =IF($N$6<>"",0,232329.7*IF($L$44=0,$N$9,$G$44/$L$44)) -> 232329.7 | L44: =SUMPRODUCT('Terraplenagem por estaca'!$E$2:$E$744,((('Terraplenagem por estaca'!$D$2:$D$744<$N$12)*'Terraplenagem por estaca'!$D$2:$D$744+('Terraplenagem por estaca'!$D$2:$D$744>=$N$12)*$N$12)-(('Terraplenagem por estaca'!$C$2:$C$744>$M$12)*'Terraplenagem por estaca'!$C$2:$C$744+('Terraplenagem por estaca'!$C$2:$C$744<=$M$12)*$M$12))*('Terraplenagem por estaca'!$C$2:$C$744<$N$12)*('Terraplenagem por estaca'!$D$2:$D$744>$M$12)/('Terraplenagem por estaca'!$D$2:$D$744-'Terraplenagem por estaca'!$C$2:$C$744))+SUMPRODUCT('Terrapl. – ramos e solo mole'!$E$2:$E$14,((('Terrapl. – ramos e solo mole'!$C$2:$C$14<$N$12)*'Terrapl. – ramos e solo mole'!$C$2:$C$14+('Terrapl. – ramos e solo mole'!$C$2:$C$14>=$N$12)*$N$12)-(('Terrapl. – ramos e solo mole'!$B$2:$B$14>$M$12)*'Terrapl. – ramos e solo mole'!$B$2:$B$14+('Terrapl. – ramos e solo mole'!$B$2:$B$14<=$M$12)*$M$12))*('Terrapl. – ramos e solo mole'!$B$2:$B$14<$N$12)*('Terrapl. – ramos e solo mole'!$C$2:$C$14>$M$12)/('Terrapl. – ramos e solo mole'!$C$2:$C$14-'Terrapl. – ramos e solo mole'!$B$2:$B$14))/Parâmetros!$C$22 -> 236317.35 | O44: =IF($N$6<>"",0,290412.12*IF($L$44=0,$N$9,$G$44/$L$44)) -> 290412.12 | P44: =O44 -> 290412.12 | Q44: =J44-P44 -> 4984.5714 | R44: Projeto · REV04 por intervalo; ramos IN-01 na Est. 326
B45: 493647 | C45: Carga e transporte do material de limpeza para bota-fora | D45: m³ | G45: =IF($N$6<>"",0,SUMPRODUCT('Terraplenagem por estaca'!$F$2:$F$744,((('Terraplenagem por estaca'!$D$2:$D$744<$N$2)*'Terraplenagem por estaca'!$D$2:$D$744+('Terraplenagem por estaca'!$D$2:$D$744>=$N$2)*$N$2)-(('Terraplenagem por estaca'!$C$2:$C$744>$M$2)*'Terraplenagem por estaca'!$C$2:$C$744+('Terraplenagem por estaca'!$C$2:$C$744<=$M$2)*$M$2))*('Terraplenagem por estaca'!$C$2:$C$744<$N$2)*('Terraplenagem por estaca'!$D$2:$D$744>$M$2)/('Terraplenagem por estaca'!$D$2:$D$744-'Terraplenagem por estaca'!$C$2:$C$744))+SUMPRODUCT('Terrapl. – ramos e solo mole'!$E$2:$E$14,((('Terrapl. – ramos e solo mole'!$C$2:$C$14<$N$2)*'Terrapl. – ramos e solo mole'!$C$2:$C$14+('Terrapl. – ramos e solo mole'!$C$2:$C$14>=$N$2)*$N$2)-(('Terrapl. – ramos e solo mole'!$B$2:$B$14>$M$2)*'Terrapl. – ramos e solo mole'!$B$2:$B$14+('Terrapl. – ramos e solo mole'!$B$2:$B$14<=$M$2)*$M$2))*('Terrapl. – ramos e solo mole'!$B$2:$B$14<$N$2)*('Terrapl. – ramos e solo mole'!$C$2:$C$14>$M$2)/('Terrapl. – ramos e solo mole'!$C$2:$C$14-'Terrapl. – ramos e solo mole'!$B$2:$B$14))) -> 47263.471 | H45: =IF($N$6<>"",0,$G$45) -> 47263.471 | I45: 11.78 | J45: =H45*I45 -> 556763.68 | K45: =IF($N$6<>"",0,46465.94*IF($L$45=0,$N$9,$G$45/$L$45)) -> 46465.94 | L45: =SUMPRODUCT('Terraplenagem por estaca'!$F$2:$F$744,((('Terraplenagem por estaca'!$D$2:$D$744<$N$12)*'Terraplenagem por estaca'!$D$2:$D$744+('Terraplenagem por estaca'!$D$2:$D$744>=$N$12)*$N$12)-(('Terraplenagem por estaca'!$C$2:$C$744>$M$12)*'Terraplenagem por estaca'!$C$2:$C$744+('Terraplenagem por estaca'!$C$2:$C$744<=$M$12)*$M$12))*('Terraplenagem por estaca'!$C$2:$C$744<$N$12)*('Terraplenagem por estaca'!$D$2:$D$744>$M$12)/('Terraplenagem por estaca'!$D$2:$D$744-'Terraplenagem por estaca'!$C$2:$C$744))+SUMPRODUCT('Terrapl. – ramos e solo mole'!$E$2:$E$14,((('Terrapl. – ramos e solo mole'!$C$2:$C$14<$N$12)*'Terrapl. – ramos e solo mole'!$C$2:$C$14+('Terrapl. – ramos e solo mole'!$C$2:$C$14>=$N$12)*$N$12)-(('Terrapl. – ramos e solo mole'!$B$2:$B$14>$M$12)*'Terrapl. – ramos e solo mole'!$B$2:$B$14+('Terrapl. – ramos e solo mole'!$B$2:$B$14<=$M$12)*$M$12))*('Terrapl. – ramos e solo mole'!$B$2:$B$14<$N$12)*('Terrapl. – ramos e solo mole'!$C$2:$C$14>$M$12)/('Terrapl. – ramos e solo mole'!$C$2:$C$14-'Terrapl. – ramos e solo mole'!$B$2:$B$14)) -> 47263.471 | O45: =IF($N$6<>"",0,547368.77*IF($L$45=0,$N$9,$G$45/$L$45)) -> 547368.77 | P45: =O45 -> 547368.77 | Q45: =J45-P45 -> 9394.9139 | R45: Projeto · volume de limpeza (área × 0,20 m)
C46: Árvores Ø > 30 cm a remover – projeto de interferências (exóticas + nativas) | D46: un | E46: =IF($N$6<>"",0,COUNTIFS(Interferências!$C$2:$C$330,">="&$M$2,Interferências!$C$2:$C$330,"<"&($N$2+($N$2>=Estacas!$B$650-0.00001)*0.001),Interferências!$A$2:$A$330,"Árvore*",Interferências!$D$2:$D$330,"LE")) -> 154 | F46: =IF($N$6<>"",0,COUNTIFS(Interferências!$C$2:$C$330,">="&$M$2,Interferências!$C$2:$C$330,"<"&($N$2+($N$2>=Estacas!$B$650-0.00001)*0.001),Interferências!$A$2:$A$330,"Árvore*",Interferências!$D$2:$D$330,"LD")) -> 105 | G46: =E46+F46 -> 259 | L46: =COUNTIFS(Interferências!$C$2:$C$330,">="&$M$12,Interferências!$C$2:$C$330,"<"&($N$12+($N$12>=Estacas!$B$650-0.00001)*0.001),Interferências!$A$2:$A$330,"Árvore*",Interferências!$D$2:$D$330,"LE")+COUNTIFS(Interferências!$C$2:$C$330,">="&$M$12,Interferências!$C$2:$C$330,"<"&($N$12+($N$12>=Estacas!$B$650-0.00001)*0.001),Interferências!$A$2:$A$330,"Árvore*",Interferências!$D$2:$D$330,"LD") -> 259 | R46: IT-2-0001: 85 exóticas + 174 nativas, localizadas pelas coordenadas
B47: 400300 | C47: Destocamento árvores diam. > 30cm | D47: un | H47: =IF($N$6<>"",0,($G$46)*1) -> 259 | I47: 54.77 | J47: =H47*I47 -> 14185.43 | K47: =IF($N$6<>"",0,259*IF(($L$46)=0,$N$9,($G$46)/($L$46))) -> 259 | O47: =IF($N$6<>"",0,14185.43*IF(($L$46)=0,$N$9,($G$46)/($L$46))) -> 14185.43 | P47: =O47 -> 14185.43 | Q47: =J47-P47 -> 0 | R47: Projeto · árvores do projeto de interferências (IT-2-0001)
C48: Escavação, carga e transporte – volumes do projeto e faixas de DMT do contrato
C49: Corte em 1ª categoria – volume geométrico do projeto | D49: m³ | G49: =IF($N$6<>"",0,SUMPRODUCT('Terraplenagem por estaca'!$G$2:$G$744,((('Terraplenagem por estaca'!$D$2:$D$744<$N$2)*'Terraplenagem por estaca'!$D$2:$D$744+('Terraplenagem por estaca'!$D$2:$D$744>=$N$2)*$N$2)-(('Terraplenagem por estaca'!$C$2:$C$744>$M$2)*'Terraplenagem por estaca'!$C$2:$C$744+('Terraplenagem por estaca'!$C$2:$C$744<=$M$2)*$M$2))*('Terraplenagem por estaca'!$C$2:$C$744<$N$2)*('Terraplenagem por estaca'!$D$2:$D$744>$M$2)/('Terraplenagem por estaca'!$D$2:$D$744-'Terraplenagem por estaca'!$C$2:$C$744))+SUMPRODUCT('Terrapl. – ramos e solo mole'!$F$2:$F$14,((('Terrapl. – ramos e solo mole'!$C$2:$C$14<$N$2)*'Terrapl. – ramos e solo mole'!$C$2:$C$14+('Terrapl. – ramos e solo mole'!$C$2:$C$14>=$N$2)*$N$2)-(('Terrapl. – ramos e solo mole'!$B$2:$B$14>$M$2)*'Terrapl. – ramos e solo mole'!$B$2:$B$14+('Terrapl. – ramos e solo mole'!$B$2:$B$14<=$M$2)*$M$2))*('Terrapl. – ramos e solo mole'!$B$2:$B$14<$N$2)*('Terrapl. – ramos e solo mole'!$C$2:$C$14>$M$2)/('Terrapl. – ramos e solo mole'!$C$2:$C$14-'Terrapl. – ramos e solo mole'!$B$2:$B$14))) -> 258251.37 | L49: =SUMPRODUCT('Terraplenagem por estaca'!$G$2:$G$744,((('Terraplenagem por estaca'!$D$2:$D$744<$N$12)*'Terraplenagem por estaca'!$D$2:$D$744+('Terraplenagem por estaca'!$D$2:$D$744>=$N$12)*$N$12)-(('Terraplenagem por estaca'!$C$2:$C$744>$M$12)*'Terraplenagem por estaca'!$C$2:$C$744+('Terraplenagem por estaca'!$C$2:$C$744<=$M$12)*$M$12))*('Terraplenagem por estaca'!$C$2:$C$744<$N$12)*('Terraplenagem por estaca'!$D$2:$D$744>$M$12)/('Terraplenagem por estaca'!$D$2:$D$744-'Terraplenagem por estaca'!$C$2:$C$744))+SUMPRODUCT('Terrapl. – ramos e solo mole'!$F$2:$F$14,((('Terrapl. – ramos e solo mole'!$C$2:$C$14<$N$12)*'Terrapl. – ramos e solo mole'!$C$2:$C$14+('Terrapl. – ramos e solo mole'!$C$2:$C$14>=$N$12)*$N$12)-(('Terrapl. – ramos e solo mole'!$B$2:$B$14>$M$12)*'Terrapl. – ramos e solo mole'!$B$2:$B$14+('Terrapl. – ramos e solo mole'!$B$2:$B$14<=$M$12)*$M$12))*('Terrapl. – ramos e solo mole'!$B$2:$B$14<$N$12)*('Terrapl. – ramos e solo mole'!$C$2:$C$14>$M$12)/('Terrapl. – ramos e solo mole'!$C$2:$C$14-'Terrapl. – ramos e solo mole'!$B$2:$B$14)) -> 258251.37 | R49: REV04 por intervalo + ramos
B50: 410200 | C50: Esc. carga e transp. 1a. cat. 0-200m | D50: m³ | H50: =IF($N$6<>"",0,($G$49)*0.38667268) -> 99858.75 | I50: 10.47 | J50: =H50*I50 -> 1045521.1 | K50: =IF($N$6<>"",0,101294.29*IF(($L$49)=0,$N$9,($G$49)/($L$49))) -> 101294.29 | O50: =IF($N$6<>"",0,1060551.21*IF(($L$49)=0,$N$9,($G$49)/($L$49))) -> 1060551.2 | P50: =O50 -> 1060551.2 | Q50: =J50-P50 -> -15030.096 | R50: Projeto · corte 1ª cat. do projeto × participação da faixa de DMT no contrato
B51: 410400 | C51: Esc. carga e transp. 1a. cat. 200-400m | D51: m³ | H51: =IF($N$6<>"",0,($G$49)*0.05069461) -> 13091.953 | I51: 10.76 | J51: =H51*I51 -> 140869.41 | K51: =IF($N$6<>"",0,13280.16*IF(($L$49)=0,$N$9,($G$49)/($L$49))) -> 13280.16 | O51: =IF($N$6<>"",0,142894.52*IF(($L$49)=0,$N$9,($G$49)/($L$49))) -> 142894.52 | P51: =O51 -> 142894.52 | Q51: =J51-P51 -> -2025.1102 | R51: Projeto · corte 1ª cat. do projeto × participação da faixa de DMT no contrato
B52: 410800 | C52: Esc. carga e transp. 1a. cat. 600-800m | D52: m³ | H52: =IF($N$6<>"",0,($G$49)*0.01776554) -> 4587.9751 | I52: 11.55 | J52: =H52*I52 -> 52991.112 | K52: =IF($N$6<>"",0,4653.93*IF(($L$49)=0,$N$9,($G$49)/($L$49))) -> 4653.93 | O52: =IF($N$6<>"",0,53752.89*IF(($L$49)=0,$N$9,($G$49)/($L$49))) -> 53752.89 | P52: =O52 -> 53752.89 | Q52: =J52-P52 -> -761.77784 | R52: Projeto · corte 1ª cat. do projeto × participação da faixa de DMT no contrato
B53: 411000 | C53: Esc. carga e transp. 1a. cat. 800-1000m | D53: m³ | H53: =IF($N$6<>"",0,($G$49)*0.00627098) -> 1619.4892 | I53: 11.99 | J53: =H53*I53 -> 19417.675 | K53: =IF($N$6<>"",0,1642.77*IF(($L$49)=0,$N$9,($G$49)/($L$49))) -> 1642.77 | O53: =IF($N$6<>"",0,19696.81*IF(($L$49)=0,$N$9,($G$49)/($L$49))) -> 19696.81 | P53: =O53 -> 19696.81 | Q53: =J53-P53 -> -279.13463 | R53: Projeto · corte 1ª cat. do projeto × participação da faixa de DMT no contrato
B54: 411200 | C54: Esc. carga e transp. 1a. cat. 1000-1200m | D54: m³ | H54: =IF($N$6<>"",0,($G$49)*0.073287) -> 18926.468 | I54: 12.38 | J54: =H54*I54 -> 234309.68 | K54: =IF($N$6<>"",0,19198.55*IF(($L$49)=0,$N$9,($G$49)/($L$49))) -> 19198.55 | O54: =IF($N$6<>"",0,237678.04*IF(($L$49)=0,$N$9,($G$49)/($L$49))) -> 237678.04 | P54: =O54 -> 237678.04 | Q54: =J54-P54 -> -3368.3625 | R54: Projeto · corte 1ª cat. do projeto × participação da faixa de DMT no contrato
B55: 411400 | C55: Esc. carga e transp. 1a. cat. 1200-1400m | D55: m³ | H55: =IF($N$6<>"",0,($G$49)*0.02162832) -> 5585.5433 | I55: 13.71 | J55: =H55*I55 -> 76577.799 | K55: =IF($N$6<>"",0,5665.84*IF(($L$49)=0,$N$9,($G$49)/($L$49))) -> 5665.84 | O55: =IF($N$6<>"",0,77678.66*IF(($L$49)=0,$N$9,($G$49)/($L$49))) -> 77678.66 | P55: =O55 -> 77678.66 | Q55: =J55-P55 -> -1100.8612 | R55: Projeto · corte 1ª cat. do projeto × participação da faixa de DMT no contrato
B56: 411600 | C56: Esc. carga e transp. 1a. cat. 1400-1600m | D56: m³ | H56: =IF($N$6<>"",0,($G$49)*0.00229749) -> 593.32994 | I56: 14.16 | J56: =H56*I56 -> 8401.552 | K56: =IF($N$6<>"",0,601.86*IF(($L$49)=0,$N$9,($G$49)/($L$49))) -> 601.86 | O56: =IF($N$6<>"",0,8522.33*IF(($L$49)=0,$N$9,($G$49)/($L$49))) -> 8522.33 | P56: =O56 -> 8522.33 | Q56: =J56-P56 -> -120.77798 | R56: Projeto · corte 1ª cat. do projeto × participação da faixa de DMT no contrato
B57: 412000 | C57: Esc. carga e transp. 1a. cat. 1600-2000m | D57: m³ | H57: =IF($N$6<>"",0,($G$49)*0.02644093) -> 6828.4064 | I57: 14.9 | J57: =H57*I57 -> 101743.26 | K57: =IF($N$6<>"",0,6926.57*IF(($L$49)=0,$N$9,($G$49)/($L$49))) -> 6926.57 | O57: =IF($N$6<>"",0,103205.89*IF(($L$49)=0,$N$9,($G$49)/($L$49))) -> 103205.89 | P57: =O57 -> 103205.89 | Q57: =J57-P57 -> -1462.6339 | R57: Projeto · corte 1ª cat. do projeto × participação da faixa de DMT no contrato
B58: 413000 | C58: Esc. carga e transp. 1a. cat. 2000-3000m | D58: m³ | H58: =IF($N$6<>"",0,($G$49)*0.06573031) -> 16974.943 | I58: 17.21 | J58: =H58*I58 -> 292138.76 | K58: =IF($N$6<>"",0,17218.97*IF(($L$49)=0,$N$9,($G$49)/($L$49))) -> 17218.97 | O58: =IF($N$6<>"",0,296338.47*IF(($L$49)=0,$N$9,($G$49)/($L$49))) -> 296338.47 | P58: =O58 -> 296338.47 | Q58: =J58-P58 -> -4199.7055 | R58: Projeto · corte 1ª cat. do projeto × participação da faixa de DMT no contrato
B59: 414000 | C59: Esc. carga e transp. 1a. cat. 3000-4000m | D59: m³ | H59: =IF($N$6<>"",0,($G$49)*0.13110241) -> 33857.377 | I59: 19.27 | J59: =H59*I59 -> 652431.66 | K59: =IF($N$6<>"",0,34344.1*IF(($L$49)=0,$N$9,($G$49)/($L$49))) -> 34344.1 | O59: =IF($N$6<>"",0,661810.8*IF(($L$49)=0,$N$9,($G$49)/($L$49))) -> 661810.8 | P59: =O59 -> 661810.8 | Q59: =J59-P59 -> -9379.1403 | R59: Projeto · corte 1ª cat. do projeto × participação da faixa de DMT no contrato
B60: 415000 | C60: Esc. carga e transp. 1a. cat. 4000-5000m | D60: m³ | H60: =IF($N$6<>"",0,($G$49)*0.15267851) -> 39429.435 | I60: 22.25 | J60: =H60*I60 -> 877304.92 | K60: =IF($N$6<>"",0,39996.26*IF(($L$49)=0,$N$9,($G$49)/($L$49))) -> 39996.26 | O60: =IF($N$6<>"",0,889916.78*IF(($L$49)=0,$N$9,($G$49)/($L$49))) -> 889916.78 | P60: =O60 -> 889916.78 | Q60: =J60-P60 -> -12611.858 | R60: Projeto · corte 1ª cat. do projeto × participação da faixa de DMT no contrato
B61: 416010 | C61: Esc. carga e transp. 1a. cat. 5000-6000m | D61: m³ | H61: =IF($N$6<>"",0,($G$49)*0.05259446) -> 13582.591 | I61: 25.37 | J61: =H61*I61 -> 344590.35 | K61: =IF($N$6<>"",0,13777.85*IF(($L$49)=0,$N$9,($G$49)/($L$49))) -> 13777.85 | O61: =IF($N$6<>"",0,349544.05*IF(($L$49)=0,$N$9,($G$49)/($L$49))) -> 349544.05 | P61: =O61 -> 349544.05 | Q61: =J61-P61 -> -4953.7048 | R61: Projeto · corte 1ª cat. do projeto × participação da faixa de DMT no contrato
B62: 418000 | C62: Esc. carga e transp. 1a. cat. 6000-8000m | D62: m³ | H62: =IF($N$6<>"",0,($G$49)*0.01283677) -> 3315.1135 | I62: 29.3 | J62: =H62*I62 -> 97132.825 | K62: =IF($N$6<>"",0,3362.77*IF(($L$49)=0,$N$9,($G$49)/($L$49))) -> 3362.77 | O62: =IF($N$6<>"",0,98529.16*IF(($L$49)=0,$N$9,($G$49)/($L$49))) -> 98529.16 | P62: =O62 -> 98529.16 | Q62: =J62-P62 -> -1396.3355 | R62: Projeto · corte 1ª cat. do projeto × participação da faixa de DMT no contrato
C63: Corte em 2ª categoria – volume geométrico do projeto | D63: m³ | G63: =IF($N$6<>"",0,SUMPRODUCT('Terraplenagem por estaca'!$H$2:$H$744,((('Terraplenagem por estaca'!$D$2:$D$744<$N$2)*'Terraplenagem por estaca'!$D$2:$D$744+('Terraplenagem por estaca'!$D$2:$D$744>=$N$2)*$N$2)-(('Terraplenagem por estaca'!$C$2:$C$744>$M$2)*'Terraplenagem por estaca'!$C$2:$C$744+('Terraplenagem por estaca'!$C$2:$C$744<=$M$2)*$M$2))*('Terraplenagem por estaca'!$C$2:$C$744<$N$2)*('Terraplenagem por estaca'!$D$2:$D$744>$M$2)/('Terraplenagem por estaca'!$D$2:$D$744-'Terraplenagem por estaca'!$C$2:$C$744))) -> 31637.58 | L63: =SUMPRODUCT('Terraplenagem por estaca'!$H$2:$H$744,((('Terraplenagem por estaca'!$D$2:$D$744<$N$12)*'Terraplenagem por estaca'!$D$2:$D$744+('Terraplenagem por estaca'!$D$2:$D$744>=$N$12)*$N$12)-(('Terraplenagem por estaca'!$C$2:$C$744>$M$12)*'Terraplenagem por estaca'!$C$2:$C$744+('Terraplenagem por estaca'!$C$2:$C$744<=$M$12)*$M$12))*('Terraplenagem por estaca'!$C$2:$C$744<$N$12)*('Terraplenagem por estaca'!$D$2:$D$744>$M$12)/('Terraplenagem por estaca'!$D$2:$D$744-'Terraplenagem por estaca'!$C$2:$C$744)) -> 31637.58 | R63: REV04 por intervalo
B64: 420400 | C64: Esc. carga e transp. 2a. cat. 200-400m | D64: m³ | H64: =IF($N$6<>"",0,($G$63)*0.17495017) -> 5535 | I64: 14.84 | J64: =H64*I64 -> 82139.4 | K64: =IF($N$6<>"",0,5535*IF(($L$63)=0,$N$9,($G$63)/($L$63))) -> 5535 | O64: =IF($N$6<>"",0,82139.4*IF(($L$63)=0,$N$9,($G$63)/($L$63))) -> 82139.4 | P64: =O64 -> 82139.4 | Q64: =J64-P64 -> -9.0731628e-06 | R64: Projeto · corte 2ª cat. do projeto × participação da faixa de DMT no contrato
B65: 420800 | C65: Esc. carga e transp. 2a. cat. 600-800m | D65: m³ | H65: =IF($N$6<>"",0,($G$63)*0.00844312) -> 267.11988 | I65: 15.81 | J65: =H65*I65 -> 4223.1654 | K65: =IF($N$6<>"",0,267.12*IF(($L$63)=0,$N$9,($G$63)/($L$63))) -> 267.12 | O65: =IF($N$6<>"",0,4223.16*IF(($L$63)=0,$N$9,($G$63)/($L$63))) -> 4223.16 | P65: =O65 -> 4223.16 | Q65: =J65-P65 -> 0.0053731482 | R65: Projeto · corte 2ª cat. do projeto × participação da faixa de DMT no contrato
B66: 422000 | C66: Esc. carga e transp. 2a. cat. 1600-2000m | D66: m³ | H66: =IF($N$6<>"",0,($G$63)*0.26832615) -> 8489.19 | I66: 19.99 | J66: =H66*I66 -> 169698.91 | K66: =IF($N$6<>"",0,8489.19*IF(($L$63)=0,$N$9,($G$63)/($L$63))) -> 8489.19 | O66: =IF($N$6<>"",0,169698.9*IF(($L$63)=0,$N$9,($G$63)/($L$63))) -> 169698.9 | P66: =O66 -> 169698.9 | Q66: =J66-P66 -> 0.0088339728 | R66: Projeto · corte 2ª cat. do projeto × participação da faixa de DMT no contrato
B67: 423000 | C67: Esc. carga e transp. 2a. cat. 2000-3000m | D67: m³ | H67: =IF($N$6<>"",0,($G$63)*0.54828056) -> 17346.27 | I67: 21.84 | J67: =H67*I67 -> 378842.54 | K67: =IF($N$6<>"",0,17346.27*IF(($L$63)=0,$N$9,($G$63)/($L$63))) -> 17346.27 | O67: =IF($N$6<>"",0,378842.53*IF(($L$63)=0,$N$9,($G$63)/($L$63))) -> 378842.53 | P67: =O67 -> 378842.53 | Q67: =J67-P67 -> 0.0085350745 | R67: Projeto · corte 2ª cat. do projeto × participação da faixa de DMT no contrato
C68: Corte em 3ª categoria – volume geométrico do projeto | D68: m³ | G68: =IF($N$6<>"",0,SUMPRODUCT('Terraplenagem por estaca'!$I$2:$I$744,((('Terraplenagem por estaca'!$D$2:$D$744<$N$2)*'Terraplenagem por estaca'!$D$2:$D$744+('Terraplenagem por estaca'!$D$2:$D$744>=$N$2)*$N$2)-(('Terraplenagem por estaca'!$C$2:$C$744>$M$2)*'Terraplenagem por estaca'!$C$2:$C$744+('Terraplenagem por estaca'!$C$2:$C$744<=$M$2)*$M$2))*('Terraplenagem por estaca'!$C$2:$C$744<$N$2)*('Terraplenagem por estaca'!$D$2:$D$744>$M$2)/('Terraplenagem por estaca'!$D$2:$D$744-'Terraplenagem por estaca'!$C$2:$C$744))) -> 17477.512 | L68: =SUMPRODUCT('Terraplenagem por estaca'!$I$2:$I$744,((('Terraplenagem por estaca'!$D$2:$D$744<$N$12)*'Terraplenagem por estaca'!$D$2:$D$744+('Terraplenagem por estaca'!$D$2:$D$744>=$N$12)*$N$12)-(('Terraplenagem por estaca'!$C$2:$C$744>$M$12)*'Terraplenagem por estaca'!$C$2:$C$744+('Terraplenagem por estaca'!$C$2:$C$744<=$M$12)*$M$12))*('Terraplenagem por estaca'!$C$2:$C$744<$N$12)*('Terraplenagem por estaca'!$D$2:$D$744>$M$12)/('Terraplenagem por estaca'!$D$2:$D$744-'Terraplenagem por estaca'!$C$2:$C$744)) -> 17477.512 | R68: REV04 por intervalo
B69: 430410 | C69: Esc. carga e transp. 3a. cat. 200-400m | D69: m³ | H69: =IF($N$6<>"",0,($G$68)*0.15776395) -> 2757.3213 | I69: 46.71 | J69: =H69*I69 -> 128794.48 | K69: =IF($N$6<>"",0,2271.55*IF(($L$68)=0,$N$9,($G$68)/($L$68))) -> 2271.55 | O69: =IF($N$6<>"",0,106104.1*IF(($L$68)=0,$N$9,($G$68)/($L$68))) -> 106104.1 | P69: =O69 -> 106104.1 | Q69: =J69-P69 -> 22690.376 | R69: Projeto · corte 3ª cat. do projeto × participação da faixa de DMT no contrato
B70: 430610 | C70: Esc. carga e transp. 3a. cat. 400-600m | D70: m³ | H70: =IF($N$6<>"",0,($G$68)*0.09809069) -> 1714.3812 | I70: 48.32 | J70: =H70*I70 -> 82838.898 | K70: =IF($N$6<>"",0,1412.35*IF(($L$68)=0,$N$9,($G$68)/($L$68))) -> 1412.35 | O70: =IF($N$6<>"",0,68244.75*IF(($L$68)=0,$N$9,($G$68)/($L$68))) -> 68244.75 | P70: =O70 -> 68244.75 | Q70: =J70-P70 -> 14594.148 | R70: Projeto · corte 3ª cat. do projeto × participação da faixa de DMT no contrato
B71: 431410 | C71: Esc. carga e transp. 3a. cat. 1200-1400m | D71: m³ | H71: =IF($N$6<>"",0,($G$68)*0.0302207) -> 528.18263 | I71: 50.52 | J71: =H71*I71 -> 26683.787 | K71: =IF($N$6<>"",0,435.13*IF(($L$68)=0,$N$9,($G$68)/($L$68))) -> 435.13 | O71: =IF($N$6<>"",0,21982.76*IF(($L$68)=0,$N$9,($G$68)/($L$68))) -> 21982.76 | P71: =O71 -> 21982.76 | Q71: =J71-P71 -> 4701.0266 | R71: Projeto · corte 3ª cat. do projeto × participação da faixa de DMT no contrato
B72: 432010 | C72: Esc. carga e transp. 3a. cat. 1600-2000m | D72: m³ | H72: =IF($N$6<>"",0,($G$68)*0.05301071) -> 926.49529 | I72: 53.74 | J72: =H72*I72 -> 49789.857 | K72: =IF($N$6<>"",0,763.27*IF(($L$68)=0,$N$9,($G$68)/($L$68))) -> 763.27 | O72: =IF($N$6<>"",0,41018.12*IF(($L$68)=0,$N$9,($G$68)/($L$68))) -> 41018.12 | P72: =O72 -> 41018.12 | Q72: =J72-P72 -> 8771.7371 | R72: Projeto · corte 3ª cat. do projeto × participação da faixa de DMT no contrato
B73: 433010 | C73: Esc. carga e transp. 3a. cat. 2000-3000m | D73: m³ | H73: =IF($N$6<>"",0,($G$68)*0.07434015) -> 1299.2808 | I73: 57.73 | J73: =H73*I73 -> 75007.482 | K73: =IF($N$6<>"",0,1070.38*IF(($L$68)=0,$N$9,($G$68)/($L$68))) -> 1070.38 | O73: =IF($N$6<>"",0,61793.03*IF(($L$68)=0,$N$9,($G$68)/($L$68))) -> 61793.03 | P73: =O73 -> 61793.03 | Q73: =J73-P73 -> 13214.452 | R73: Projeto · corte 3ª cat. do projeto × participação da faixa de DMT no contrato
B74: 434010 | C74: Esc. carga e transp. 3a. cat. 3000-4000m | D74: m³ | H74: =IF($N$6<>"",0,($G$68)*0.5865738) -> 10251.85 | I74: 62.3 | J74: =H74*I74 -> 638690.28 | K74: =IF($N$6<>"",0,8445.73*IF(($L$68)=0,$N$9,($G$68)/($L$68))) -> 8445.73 | O74: =IF($N$6<>"",0,526168.97*IF(($L$68)=0,$N$9,($G$68)/($L$68))) -> 526168.97 | P74: =O74 -> 526168.97 | Q74: =J74-P74 -> 112521.31 | R74: Projeto · corte 3ª cat. do projeto × participação da faixa de DMT no contrato
B75: 404000 | C75: Remoção de solos moles | D75: m³ | G75: =IF($N$6<>"",0,SUMPRODUCT('Terraplenagem por estaca'!$J$2:$J$744,((('Terraplenagem por estaca'!$D$2:$D$744<$N$2)*'Terraplenagem por estaca'!$D$2:$D$744+('Terraplenagem por estaca'!$D$2:$D$744>=$N$2)*$N$2)-(('Terraplenagem por estaca'!$C$2:$C$744>$M$2)*'Terraplenagem por estaca'!$C$2:$C$744+('Terraplenagem por estaca'!$C$2:$C$744<=$M$2)*$M$2))*('Terraplenagem por estaca'!$C$2:$C$744<$N$2)*('Terraplenagem por estaca'!$D$2:$D$744>$M$2)/('Terraplenagem por estaca'!$D$2:$D$744-'Terraplenagem por estaca'!$C$2:$C$744))) -> 28621.07 | H75: =IF($N$6<>"",0,$G$75) -> 28621.07 | I75: 20.54 | J75: =H75*I75 -> 587876.78 | K75: =IF($N$6<>"",0,28621.07*IF($L$75=0,$N$9,$G$75/$L$75)) -> 28621.07 | L75: =SUMPRODUCT('Terraplenagem por estaca'!$J$2:$J$744,((('Terraplenagem por estaca'!$D$2:$D$744<$N$12)*'Terraplenagem por estaca'!$D$2:$D$744+('Terraplenagem por estaca'!$D$2:$D$744>=$N$12)*$N$12)-(('Terraplenagem por estaca'!$C$2:$C$744>$M$12)*'Terraplenagem por estaca'!$C$2:$C$744+('Terraplenagem por estaca'!$C$2:$C$744<=$M$12)*$M$12))*('Terraplenagem por estaca'!$C$2:$C$744<$N$12)*('Terraplenagem por estaca'!$D$2:$D$744>$M$12)/('Terraplenagem por estaca'!$D$2:$D$744-'Terraplenagem por estaca'!$C$2:$C$744)) -> 28621.07 | O75: =IF($N$6<>"",0,587876.77*IF($L$75=0,$N$9,$G$75/$L$75)) -> 587876.77 | P75: =O75 -> 587876.77 | Q75: =J75-P75 -> 0.0077999999 | R75: Projeto · REV04 / aba SOLO MOLE
B76: 404300 | C76: Espalhamento e conformação de bota-fora | D76: m³ | G76: =IF($N$6<>"",0,$G$45+$G$75) -> 75884.541 | H76: =IF($N$6<>"",0,$G$76) -> 75884.541 | I76: 0.87 | J76: =H76*I76 -> 66019.55 | K76: =IF($N$6<>"",0,75087.01*IF($L$76=0,$N$9,$G$76/$L$76)) -> 75087.01 | L76: =$L$45+$L$75 -> 75884.541 | O76: =IF($N$6<>"",0,65325.69*IF($L$76=0,$N$9,$G$76/$L$76)) -> 65325.69 | P76: =O76 -> 65325.69 | Q76: =J76-P76 -> 693.86034 | R76: Projeto · volume de limpeza + solo mole removido
C77: Aterros e fundações
B78: 401950 | C78: Compactação de aterros 95% PN (corpo de aterro) | D78: m³ | G78: =IF($N$6<>"",0,SUMPRODUCT('Terraplenagem por estaca'!$K$2:$K$744,((('Terraplenagem por estaca'!$D$2:$D$744<$N$2)*'Terraplenagem por estaca'!$D$2:$D$744+('Terraplenagem por estaca'!$D$2:$D$744>=$N$2)*$N$2)-(('Terraplenagem por estaca'!$C$2:$C$744>$M$2)*'Terraplenagem por estaca'!$C$2:$C$744+('Terraplenagem por estaca'!$C$2:$C$744<=$M$2)*$M$2))*('Terraplenagem por estaca'!$C$2:$C$744<$N$2)*('Terraplenagem por estaca'!$D$2:$D$744>$M$2)/('Terraplenagem por estaca'!$D$2:$D$744-'Terraplenagem por estaca'!$C$2:$C$744))+SUMPRODUCT('Terrapl. – ramos e solo mole'!$G$2:$G$14,((('Terrapl. – ramos e solo mole'!$C$2:$C$14<$N$2)*'Terrapl. – ramos e solo mole'!$C$2:$C$14+('Terrapl. – ramos e solo mole'!$C$2:$C$14>=$N$2)*$N$2)-(('Terrapl. – ramos e solo mole'!$B$2:$B$14>$M$2)*'Terrapl. – ramos e solo mole'!$B$2:$B$14+('Terrapl. – ramos e solo mole'!$B$2:$B$14<=$M$2)*$M$2))*('Terrapl. – ramos e solo mole'!$B$2:$B$14<$N$2)*('Terrapl. – ramos e solo mole'!$C$2:$C$14>$M$2)/('Terrapl. – ramos e solo mole'!$C$2:$C$14-'Terrapl. – ramos e solo mole'!$B$2:$B$14))) -> 125515.05 | H78: =IF($N$6<>"",0,$G$78) -> 125515.05 | I78: 6.18 | J78: =H78*I78 -> 775682.98 | K78: =IF($N$6<>"",0,125515.05*IF($L$78=0,$N$9,$G$78/$L$78)) -> 125515.05 | L78: =SUMPRODUCT('Terraplenagem por estaca'!$K$2:$K$744,((('Terraplenagem por estaca'!$D$2:$D$744<$N$12)*'Terraplenagem por estaca'!$D$2:$D$744+('Terraplenagem por estaca'!$D$2:$D$744>=$N$12)*$N$12)-(('Terraplenagem por estaca'!$C$2:$C$744>$M$12)*'Terraplenagem por estaca'!$C$2:$C$744+('Terraplenagem por estaca'!$C$2:$C$744<=$M$12)*$M$12))*('Terraplenagem por estaca'!$C$2:$C$744<$N$12)*('Terraplenagem por estaca'!$D$2:$D$744>$M$12)/('Terraplenagem por estaca'!$D$2:$D$744-'Terraplenagem por estaca'!$C$2:$C$744))+SUMPRODUCT('Terrapl. – ramos e solo mole'!$G$2:$G$14,((('Terrapl. – ramos e solo mole'!$C$2:$C$14<$N$12)*'Terrapl. – ramos e solo mole'!$C$2:$C$14+('Terrapl. – ramos e solo mole'!$C$2:$C$14>=$N$12)*$N$12)-(('Terrapl. – ramos e solo mole'!$B$2:$B$14>$M$12)*'Terrapl. – ramos e solo mole'!$B$2:$B$14+('Terrapl. – ramos e solo mole'!$B$2:$B$14<=$M$12)*$M$12))*('Terrapl. – ramos e solo mole'!$B$2:$B$14<$N$12)*('Terrapl. – ramos e solo mole'!$C$2:$C$14>$M$12)/('Terrapl. – ramos e solo mole'!$C$2:$C$14-'Terrapl. – ramos e solo mole'!$B$2:$B$14)) -> 125515.05 | O78: =IF($N$6<>"",0,775683*IF($L$78=0,$N$9,$G$78/$L$78)) -> 775683 | P78: =O78 -> 775683 | Q78: =J78-P78 -> -0.019067826 | R78: Projeto · REV04 por intervalo + ramos
B79: 401100 | C79: Compactação de aterros 100% PN (camada final) | D79: m³ | G79: =IF($N$6<>"",0,SUMPRODUCT('Terraplenagem por estaca'!$L$2:$L$744,((('Terraplenagem por estaca'!$D$2:$D$744<$N$2)*'Terraplenagem por estaca'!$D$2:$D$744+('Terraplenagem por estaca'!$D$2:$D$744>=$N$2)*$N$2)-(('Terraplenagem por estaca'!$C$2:$C$744>$M$2)*'Terraplenagem por estaca'!$C$2:$C$744+('Terraplenagem por estaca'!$C$2:$C$744<=$M$2)*$M$2))*('Terraplenagem por estaca'!$C$2:$C$744<$N$2)*('Terraplenagem por estaca'!$D$2:$D$744>$M$2)/('Terraplenagem por estaca'!$D$2:$D$744-'Terraplenagem por estaca'!$C$2:$C$744))+SUMPRODUCT('Terrapl. – ramos e solo mole'!$H$2:$H$14,((('Terrapl. – ramos e solo mole'!$C$2:$C$14<$N$2)*'Terrapl. – ramos e solo mole'!$C$2:$C$14+('Terrapl. – ramos e solo mole'!$C$2:$C$14>=$N$2)*$N$2)-(('Terrapl. – ramos e solo mole'!$B$2:$B$14>$M$2)*'Terrapl. – ramos e solo mole'!$B$2:$B$14+('Terrapl. – ramos e solo mole'!$B$2:$B$14<=$M$2)*$M$2))*('Terrapl. – ramos e solo mole'!$B$2:$B$14<$N$2)*('Terrapl. – ramos e solo mole'!$C$2:$C$14>$M$2)/('Terrapl. – ramos e solo mole'!$C$2:$C$14-'Terrapl. – ramos e solo mole'!$B$2:$B$14))) -> 101065.32 | H79: =IF($N$6<>"",0,$G$79) -> 101065.32 | I79: 7.44 | J79: =H79*I79 -> 751925.99 | K79: =IF($N$6<>"",0,102477.69*IF($L$79=0,$N$9,$G$79/$L$79)) -> 102477.69 | L79: =SUMPRODUCT('Terraplenagem por estaca'!$L$2:$L$744,((('Terraplenagem por estaca'!$D$2:$D$744<$N$12)*'Terraplenagem por estaca'!$D$2:$D$744+('Terraplenagem por estaca'!$D$2:$D$744>=$N$12)*$N$12)-(('Terraplenagem por estaca'!$C$2:$C$744>$M$12)*'Terraplenagem por estaca'!$C$2:$C$744+('Terraplenagem por estaca'!$C$2:$C$744<=$M$12)*$M$12))*('Terraplenagem por estaca'!$C$2:$C$744<$N$12)*('Terraplenagem por estaca'!$D$2:$D$744>$M$12)/('Terraplenagem por estaca'!$D$2:$D$744-'Terraplenagem por estaca'!$C$2:$C$744))+SUMPRODUCT('Terrapl. – ramos e solo mole'!$H$2:$H$14,((('Terrapl. – ramos e solo mole'!$C$2:$C$14<$N$12)*'Terrapl. – ramos e solo mole'!$C$2:$C$14+('Terrapl. – ramos e solo mole'!$C$2:$C$14>=$N$12)*$N$12)-(('Terrapl. – ramos e solo mole'!$B$2:$B$14>$M$12)*'Terrapl. – ramos e solo mole'!$B$2:$B$14+('Terrapl. – ramos e solo mole'!$B$2:$B$14<=$M$12)*$M$12))*('Terrapl. – ramos e solo mole'!$B$2:$B$14<$N$12)*('Terrapl. – ramos e solo mole'!$C$2:$C$14>$M$12)/('Terrapl. – ramos e solo mole'!$C$2:$C$14-'Terrapl. – ramos e solo mole'!$B$2:$B$14)) -> 101065.32 | O79: =IF($N$6<>"",0,762434.01*IF($L$79=0,$N$9,$G$79/$L$79)) -> 762434.01 | P79: =O79 -> 762434.01 | Q79: =J79-P79 -> -10508.022 | R79: Projeto · REV04 por intervalo + ramos
B80: 403000 | C80: Compactação de aterros em 3a. cat. | D80: m³ | H80: =IF($N$6<>"",0,16881.88*IF(($L$68)=0,$N$9,($G$68)/($L$68))) -> 16881.88 | I80: 8 | J80: =H80*I80 -> 135055.04 | K80: =IF($N$6<>"",0,18294.23*IF(($L$68)=0,$N$9,($G$68)/($L$68))) -> 18294.23 | O80: =IF($N$6<>"",0,146353.84*IF(($L$68)=0,$N$9,($G$68)/($L$68))) -> 146353.84 | P80: =O80 -> 146353.84 | Q80: =J80-P80 -> -11298.8 | R80: Projeto (memória, total) · quadro de terraplenagem 16.881,88 m³ – distribuído pelo corte 3ª cat.
B81: 495161 | C81: Fundação de aterro com rachão / 3ª cat. | D81: m³ | G81: =IF($N$6<>"",0,SUMPRODUCT('Terraplenagem por estaca'!$M$2:$M$744,((('Terraplenagem por estaca'!$D$2:$D$744<$N$2)*'Terraplenagem por estaca'!$D$2:$D$744+('Terraplenagem por estaca'!$D$2:$D$744>=$N$2)*$N$2)-(('Terraplenagem por estaca'!$C$2:$C$744>$M$2)*'Terraplenagem por estaca'!$C$2:$C$744+('Terraplenagem por estaca'!$C$2:$C$744<=$M$2)*$M$2))*('Terraplenagem por estaca'!$C$2:$C$744<$N$2)*('Terraplenagem por estaca'!$D$2:$D$744>$M$2)/('Terraplenagem por estaca'!$D$2:$D$744-'Terraplenagem por estaca'!$C$2:$C$744))) -> 27235.294 | H81: =IF($N$6<>"",0,$G$81) -> 27235.294 | I81: 169.76 | J81: =H81*I81 -> 4623463.5 | K81: =IF($N$6<>"",0,28703.95*IF($L$81=0,$N$9,$G$81/$L$81)) -> 28703.95 | L81: =SUMPRODUCT('Terraplenagem por estaca'!$M$2:$M$744,((('Terraplenagem por estaca'!$D$2:$D$744<$N$12)*'Terraplenagem por estaca'!$D$2:$D$744+('Terraplenagem por estaca'!$D$2:$D$744>=$N$12)*$N$12)-(('Terraplenagem por estaca'!$C$2:$C$744>$M$12)*'Terraplenagem por estaca'!$C$2:$C$744+('Terraplenagem por estaca'!$C$2:$C$744<=$M$12)*$M$12))*('Terraplenagem por estaca'!$C$2:$C$744<$N$12)*('Terraplenagem por estaca'!$D$2:$D$744>$M$12)/('Terraplenagem por estaca'!$D$2:$D$744-'Terraplenagem por estaca'!$C$2:$C$744)) -> 27235.294 | O81: =IF($N$6<>"",0,4872782.55*IF($L$81=0,$N$9,$G$81/$L$81)) -> 4872782.5 | P81: =O81 -> 4872782.5 | Q81: =J81-P81 -> -249319.04 | R81: Projeto · REV04 por intervalo
B82: 400500 | C82: Colchão drenante de areia (fundação em solo mole) | D82: m³ | G82: =IF($N$6<>"",0,SUMPRODUCT('Terrapl. – ramos e solo mole'!$J$2:$J$14,((('Terrapl. – ramos e solo mole'!$C$2:$C$14<$N$2)*'Terrapl. – ramos e solo mole'!$C$2:$C$14+('Terrapl. – ramos e solo mole'!$C$2:$C$14>=$N$2)*$N$2)-(('Terrapl. – ramos e solo mole'!$B$2:$B$14>$M$2)*'Terrapl. – ramos e solo mole'!$B$2:$B$14+('Terrapl. – ramos e solo mole'!$B$2:$B$14<=$M$2)*$M$2))*('Terrapl. – ramos e solo mole'!$B$2:$B$14<$N$2)*('Terrapl. – ramos e solo mole'!$C$2:$C$14>$M$2)/('Terrapl. – ramos e solo mole'!$C$2:$C$14-'Terrapl. – ramos e solo mole'!$B$2:$B$14))) -> 6633.825 | H82: =IF($N$6<>"",0,$G$82) -> 6633.825 | I82: 324.85 | J82: =H82*I82 -> 2154998.1 | K82: =IF($N$6<>"",0,6633.83*IF($L$82=0,$N$9,$G$82/$L$82)) -> 6633.83 | L82: =SUMPRODUCT('Terrapl. – ramos e solo mole'!$J$2:$J$14,((('Terrapl. – ramos e solo mole'!$C$2:$C$14<$N$12)*'Terrapl. – ramos e solo mole'!$C$2:$C$14+('Terrapl. – ramos e solo mole'!$C$2:$C$14>=$N$12)*$N$12)-(('Terrapl. – ramos e solo mole'!$B$2:$B$14>$M$12)*'Terrapl. – ramos e solo mole'!$B$2:$B$14+('Terrapl. – ramos e solo mole'!$B$2:$B$14<=$M$12)*$M$12))*('Terrapl. – ramos e solo mole'!$B$2:$B$14<$N$12)*('Terrapl. – ramos e solo mole'!$C$2:$C$14>$M$12)/('Terrapl. – ramos e solo mole'!$C$2:$C$14-'Terrapl. – ramos e solo mole'!$B$2:$B$14)) -> 6633.825 | O82: =IF($N$6<>"",0,2154999.67*IF($L$82=0,$N$9,$G$82/$L$82)) -> 2154999.7 | P82: =O82 -> 2154999.7 | Q82: =J82-P82 -> -1.61875 | R82: Projeto · 10 trechos de solo mole
B83: 495160 | C83: Fundação de aterro com brita – fechamento (solo mole) | D83: m³ | G83: =IF($N$6<>"",0,SUMPRODUCT('Terrapl. – ramos e solo mole'!$K$2:$K$14,((('Terrapl. – ramos e solo mole'!$C$2:$C$14<$N$2)*'Terrapl. – ramos e solo mole'!$C$2:$C$14+('Terrapl. – ramos e solo mole'!$C$2:$C$14>=$N$2)*$N$2)-(('Terrapl. – ramos e solo mole'!$B$2:$B$14>$M$2)*'Terrapl. – ramos e solo mole'!$B$2:$B$14+('Terrapl. – ramos e solo mole'!$B$2:$B$14<=$M$2)*$M$2))*('Terrapl. – ramos e solo mole'!$B$2:$B$14<$N$2)*('Terrapl. – ramos e solo mole'!$C$2:$C$14>$M$2)/('Terrapl. – ramos e solo mole'!$C$2:$C$14-'Terrapl. – ramos e solo mole'!$B$2:$B$14))) -> 1326.765 | H83: =IF($N$6<>"",0,$G$83) -> 1326.765 | I83: 164 | J83: =H83*I83 -> 217589.46 | K83: =IF($N$6<>"",0,1326.77*IF($L$83=0,$N$9,$G$83/$L$83)) -> 1326.77 | L83: =SUMPRODUCT('Terrapl. – ramos e solo mole'!$K$2:$K$14,((('Terrapl. – ramos e solo mole'!$C$2:$C$14<$N$12)*'Terrapl. – ramos e solo mole'!$C$2:$C$14+('Terrapl. – ramos e solo mole'!$C$2:$C$14>=$N$12)*$N$12)-(('Terrapl. – ramos e solo mole'!$B$2:$B$14>$M$12)*'Terrapl. – ramos e solo mole'!$B$2:$B$14+('Terrapl. – ramos e solo mole'!$B$2:$B$14<=$M$12)*$M$12))*('Terrapl. – ramos e solo mole'!$B$2:$B$14<$N$12)*('Terrapl. – ramos e solo mole'!$C$2:$C$14>$M$12)/('Terrapl. – ramos e solo mole'!$C$2:$C$14-'Terrapl. – ramos e solo mole'!$B$2:$B$14)) -> 1326.765 | O83: =IF($N$6<>"",0,217590.28*IF($L$83=0,$N$9,$G$83/$L$83)) -> 217590.28 | P83: =O83 -> 217590.28 | Q83: =J83-P83 -> -0.82 | R83: Projeto · 10 trechos de solo mole
C84: Tratamento de corte em rocha – solo grampeado (só total no projeto)
B85: 791117 | C85: Bate choco e limpeza de talude com bota fora de pedras soltas | D85: m² | H85: =IF($N$6<>"",0,3099*IF(($L$68)=0,$N$9,($G$68)/($L$68))) -> 3099 | I85: 73.18 | J85: =H85*I85 -> 226784.82 | K85: =IF($N$6<>"",0,3099*IF(($L$68)=0,$N$9,($G$68)/($L$68))) -> 3099 | O85: =IF($N$6<>"",0,226784.82*IF(($L$68)=0,$N$9,($G$68)/($L$68))) -> 226784.82 | P85: =O85 -> 226784.82 | Q85: =J85-P85 -> 0 | R85: Projeto (memória, total) · quadro de terraplenagem (tratamento de corte em rocha) – distribuído pelo corte 3ª cat.
B86: 794433 | C86: Dreno de PVC reforçado 0,30m a 0,55m Ø=75mm - barbacã | D86: un | H86: =IF($N$6<>"",0,179*IF(($L$68)=0,$N$9,($G$68)/($L$68))) -> 179 | I86: 43.19 | J86: =H86*I86 -> 7731.01 | K86: =IF($N$6<>"",0,179*IF(($L$68)=0,$N$9,($G$68)/($L$68))) -> 179 | O86: =IF($N$6<>"",0,7731.01*IF(($L$68)=0,$N$9,($G$68)/($L$68))) -> 7731.01 | P86: =O86 -> 7731.01 | Q86: =J86-P86 -> 0 | R86: Projeto (memória, total) · quadro de terraplenagem (tratamento de corte em rocha) – distribuído pelo corte 3ª cat.
B87: 792400 | C87: Fornecimento e aplicação de concreto projetado via seca Fck = 20 mPa, volume passado na máquina | D87: m³ | H87: =IF($N$6<>"",0,201.44*IF(($L$68)=0,$N$9,($G$68)/($L$68))) -> 201.44 | I87: 2549.55 | J87: =H87*I87 -> 513581.35 | K87: =IF($N$6<>"",0,201.44*IF(($L$68)=0,$N$9,($G$68)/($L$68))) -> 201.44 | O87: =IF($N$6<>"",0,513581.35*IF(($L$68)=0,$N$9,($G$68)/($L$68))) -> 513581.35 | P87: =O87 -> 513581.35 | Q87: =J87-P87 -> 0.002 | R87: Projeto (memória, total) · quadro de terraplenagem (tratamento de corte em rocha) – distribuído pelo corte 3ª cat.
B88: 792600 | C88: Fornecimento e colocação de Tela Telcon Q-138 ou equivalente, para OAE | D88: kg | H88: =IF($N$6<>"",0,2409.47*IF(($L$68)=0,$N$9,($G$68)/($L$68))) -> 2409.47 | I88: 19.53 | J88: =H88*I88 -> 47056.949 | K88: =IF($N$6<>"",0,2409.47*IF(($L$68)=0,$N$9,($G$68)/($L$68))) -> 2409.47 | O88: =IF($N$6<>"",0,47056.94*IF(($L$68)=0,$N$9,($G$68)/($L$68))) -> 47056.94 | P88: =O88 -> 47056.94 | Q88: =J88-P88 -> 0.0091 | R88: Projeto (memória, total) · quadro de terraplenagem (tratamento de corte em rocha) – distribuído pelo corte 3ª cat.
B89: 795482 | C89: Fornecimento, perfuração, instalação e protensão de tirante INCO 22 D em rocha, inclusive injeção de nata de cimento, acessórios e proteção das cabeças dos tirantes, ou equivalente | D89: m | H89: =IF($N$6<>"",0,1162.13*IF(($L$68)=0,$N$9,($G$68)/($L$68))) -> 1162.13 | I89: 669.97 | J89: =H89*I89 -> 778592.24 | K89: =IF($N$6<>"",0,1162.13*IF(($L$68)=0,$N$9,($G$68)/($L$68))) -> 1162.13 | O89: =IF($N$6<>"",0,778592.23*IF(($L$68)=0,$N$9,($G$68)/($L$68))) -> 778592.23 | P89: =O89 -> 778592.23 | Q89: =J89-P89 -> 0.0061000001 | R89: Projeto (memória, total) · quadro de terraplenagem (tratamento de corte em rocha) – distribuído pelo corte 3ª cat.
C90: Subtotal – Terraplenagem | H90: =COUNTIF(J43:J89,">0")&" de "&COUNT(J43:J89)&" itens" -> 39 de 39 itens | J90: =SUM(J43:J89) -> 17332842 | O90: =SUM(O43:O89) -> 17469094 | P90: =SUM(P43:P89) -> 17469094 | Q90: =J90-P90 -> -136251.38
B92: 2 · PAVIMENTAÇÃO
C93: Estrutura do pavimento (seções tipo PV-2)
B94: 511200 | C94: Regularização e compactação do subleito 100% PN | D94: m² | G94: =IF($N$6<>"",0,(INDEX(Estacas!$Z$1:$Z$650,N3)+N5*N4*(2*INDEX(Estacas!$P$1:$P$650,N3)+(INDEX(Estacas!$P$1:$P$650,N3+1)-INDEX(Estacas!$P$1:$P$650,N3))*N4)/2*1)-(INDEX(Estacas!$Z$1:$Z$650,M3)+M5*M4*(2*INDEX(Estacas!$P$1:$P$650,M3)+(INDEX(Estacas!$P$1:$P$650,M3+1)-INDEX(Estacas!$P$1:$P$650,M3))*M4)/2*1)) -> 172945.16 | H94: =IF($N$6<>"",0,$G$94) -> 172945.16 | I94: 5.16 | J94: =H94*I94 -> 892397 | K94: =IF($N$6<>"",0,171057*IF($L$94=0,$N$9,$G$94/$L$94)) -> 171057 | L94: =(INDEX(Estacas!$Z$1:$Z$650,N13)+N15*N14*(2*INDEX(Estacas!$P$1:$P$650,N13)+(INDEX(Estacas!$P$1:$P$650,N13+1)-INDEX(Estacas!$P$1:$P$650,N13))*N14)/2*1)-(INDEX(Estacas!$Z$1:$Z$650,M13)+M15*M14*(2*INDEX(Estacas!$P$1:$P$650,M13)+(INDEX(Estacas!$P$1:$P$650,M13+1)-INDEX(Estacas!$P$1:$P$650,M13))*M14)/2*1) -> 172945.16 | O94: =IF($N$6<>"",0,882654.12*IF($L$94=0,$N$9,$G$94/$L$94)) -> 882654.12 | P94: =O94 -> 882654.12 | Q94: =J94-P94 -> 9742.8831 | R94: Projeto · largura medida + Detalhe "A" · áreas médias
C95: Reforço do subleito – bica corrida (2 × 15 cm) – projeto | D95: m³ | G95: =IF($N$6<>"",0,(INDEX(Estacas!$W$1:$W$650,N3)+N5*N4*(2*INDEX(Estacas!$N$1:$N$650,N3)+(INDEX(Estacas!$N$1:$N$650,N3+1)-INDEX(Estacas!$N$1:$N$650,N3))*N4)/2*1)-(INDEX(Estacas!$W$1:$W$650,M3)+M5*M4*(2*INDEX(Estacas!$N$1:$N$650,M3)+(INDEX(Estacas!$N$1:$N$650,M3+1)-INDEX(Estacas!$N$1:$N$650,M3))*M4)/2*1)) -> 50726.523 | L95: =(INDEX(Estacas!$W$1:$W$650,N13)+N15*N14*(2*INDEX(Estacas!$N$1:$N$650,N13)+(INDEX(Estacas!$N$1:$N$650,N13+1)-INDEX(Estacas!$N$1:$N$650,N13))*N14)/2*1)-(INDEX(Estacas!$W$1:$W$650,M13)+M15*M14*(2*INDEX(Estacas!$N$1:$N$650,M13)+(INDEX(Estacas!$N$1:$N$650,M13+1)-INDEX(Estacas!$N$1:$N$650,M13))*M14)/2*1) -> 50726.523 | R95: espessura em Parâmetros C4
C96: Sub-base – bica corrida (20 cm) – projeto | D96: m³ | G96: =IF($N$6<>"",0,(INDEX(Estacas!$V$1:$V$650,N3)+N5*N4*(2*INDEX(Estacas!$M$1:$M$650,N3)+(INDEX(Estacas!$M$1:$M$650,N3+1)-INDEX(Estacas!$M$1:$M$650,N3))*N4)/2*1)-(INDEX(Estacas!$V$1:$V$650,M3)+M5*M4*(2*INDEX(Estacas!$M$1:$M$650,M3)+(INDEX(Estacas!$M$1:$M$650,M3+1)-INDEX(Estacas!$M$1:$M$650,M3))*M4)/2*1)) -> 32017.868 | L96: =(INDEX(Estacas!$V$1:$V$650,N13)+N15*N14*(2*INDEX(Estacas!$M$1:$M$650,N13)+(INDEX(Estacas!$M$1:$M$650,N13+1)-INDEX(Estacas!$M$1:$M$650,N13))*N14)/2*1)-(INDEX(Estacas!$V$1:$V$650,M13)+M15*M14*(2*INDEX(Estacas!$M$1:$M$650,M13)+(INDEX(Estacas!$M$1:$M$650,M13+1)-INDEX(Estacas!$M$1:$M$650,M13))*M14)/2*1) -> 32017.868 | R96: espessura em Parâmetros C3
B97: 530200 | C97: Bica corrida | D97: m³ | H97: =IF($N$6<>"",0,($G$95+$G$96)*1) -> 82744.391 | I97: 180.59 | J97: =H97*I97 -> 14942810 | K97: =IF($N$6<>"",0,84642*IF(($L$95+$L$96)=0,$N$9,($G$95+$G$96)/($L$95+$L$96))) -> 84642 | O97: =IF($N$6<>"",0,15285498.78*IF(($L$95+$L$96)=0,$N$9,($G$95+$G$96)/($L$95+$L$96))) -> 15285499 | P97: =O97 -> 15285499 | Q97: =J97-P97 -> -342689.23 | R97: Projeto · reforço + sub-base do projeto
B98: 531100 | C98: Base – brita graduada 100% PM (16 cm) | D98: m³ | G98: =IF($N$6<>"",0,(INDEX(Estacas!$U$1:$U$650,N3)+N5*N4*(2*INDEX(Estacas!$L$1:$L$650,N3)+(INDEX(Estacas!$L$1:$L$650,N3+1)-INDEX(Estacas!$L$1:$L$650,N3))*N4)/2*1)-(INDEX(Estacas!$U$1:$U$650,M3)+M5*M4*(2*INDEX(Estacas!$L$1:$L$650,M3)+(INDEX(Estacas!$L$1:$L$650,M3+1)-INDEX(Estacas!$L$1:$L$650,M3))*M4)/2*1)) -> 24462.413 | H98: =IF($N$6<>"",0,$G$98) -> 24462.413 | I98: 241.97 | J98: =H98*I98 -> 5919170.1 | K98: =IF($N$6<>"",0,25878.66*IF($L$98=0,$N$9,$G$98/$L$98)) -> 25878.66 | L98: =(INDEX(Estacas!$U$1:$U$650,N13)+N15*N14*(2*INDEX(Estacas!$L$1:$L$650,N13)+(INDEX(Estacas!$L$1:$L$650,N13+1)-INDEX(Estacas!$L$1:$L$650,N13))*N14)/2*1)-(INDEX(Estacas!$U$1:$U$650,M13)+M15*M14*(2*INDEX(Estacas!$L$1:$L$650,M13)+(INDEX(Estacas!$L$1:$L$650,M13+1)-INDEX(Estacas!$L$1:$L$650,M13))*M14)/2*1) -> 24462.413 | O98: =IF($N$6<>"",0,6261859.36*IF($L$98=0,$N$9,$G$98/$L$98)) -> 6261859.4 | P98: =O98 -> 6261859.4 | Q98: =J98-P98 -> -342689.29 | R98: Projeto · espessura em Parâmetros C2
B99: 560100 | C99: Imprimação impermeabilizante (exclusive emulsão) | D99: m² | G99: =IF($N$6<>"",0,(INDEX(Estacas!$X$1:$X$650,N3)+N5*N4*(2*INDEX(Estacas!$O$1:$O$650,N3)+(INDEX(Estacas!$O$1:$O$650,N3+1)-INDEX(Estacas!$O$1:$O$650,N3))*N4)/2*1)-(INDEX(Estacas!$X$1:$X$650,M3)+M5*M4*(2*INDEX(Estacas!$O$1:$O$650,M3)+(INDEX(Estacas!$O$1:$O$650,M3+1)-INDEX(Estacas!$O$1:$O$650,M3))*M4)/2*1)) -> 150833.15 | H99: =IF($N$6<>"",0,$G$99) -> 150833.15 | I99: 0.79 | J99: =H99*I99 -> 119158.19 | K99: =IF($N$6<>"",0,161756*IF($L$99=0,$N$9,$G$99/$L$99)) -> 161756 | L99: =(INDEX(Estacas!$X$1:$X$650,N13)+N15*N14*(2*INDEX(Estacas!$O$1:$O$650,N13)+(INDEX(Estacas!$O$1:$O$650,N13+1)-INDEX(Estacas!$O$1:$O$650,N13))*N14)/2*1)-(INDEX(Estacas!$X$1:$X$650,M13)+M15*M14*(2*INDEX(Estacas!$O$1:$O$650,M13)+(INDEX(Estacas!$O$1:$O$650,M13+1)-INDEX(Estacas!$O$1:$O$650,M13))*M14)/2*1) -> 150833.15 | O99: =IF($N$6<>"",0,127787.24*IF($L$99=0,$N$9,$G$99/$L$99)) -> 127787.24 | P99: =O99 -> 127787.24 | Q99: =J99-P99 -> -8629.0512 | R99: Projeto · topo da base
B100: 561100 | C100: Pintura de ligação (exclusive emulsão) | D100: m² | G100: =IF($N$6<>"",0,(INDEX(Estacas!$Y$1:$Y$650,N3)+N5*N4*(2*INDEX(Estacas!$O$1:$O$650,N3)+(INDEX(Estacas!$O$1:$O$650,N3+1)-INDEX(Estacas!$O$1:$O$650,N3))*N4)/2*1)-(INDEX(Estacas!$Y$1:$Y$650,M3)+M5*M4*(2*INDEX(Estacas!$O$1:$O$650,M3)+(INDEX(Estacas!$O$1:$O$650,M3+1)-INDEX(Estacas!$O$1:$O$650,M3))*M4)/2*1)) -> 150833.15 | H100: =IF($N$6<>"",0,$G$100) -> 150833.15 | I100: 0.46 | J100: =H100*I100 -> 69383.249 | K100: =IF($N$6<>"",0,161734*IF($L$100=0,$N$9,$G$100/$L$100)) -> 161734 | L100: =(INDEX(Estacas!$Y$1:$Y$650,N13)+N15*N14*(2*INDEX(Estacas!$O$1:$O$650,N13)+(INDEX(Estacas!$O$1:$O$650,N13+1)-INDEX(Estacas!$O$1:$O$650,N13))*N14)/2*1)-(INDEX(Estacas!$Y$1:$Y$650,M13)+M15*M14*(2*INDEX(Estacas!$O$1:$O$650,M13)+(INDEX(Estacas!$O$1:$O$650,M13+1)-INDEX(Estacas!$O$1:$O$650,M13))*M14)/2*1) -> 150833.15 | O100: =IF($N$6<>"",0,74397.64*IF($L$100=0,$N$9,$G$100/$L$100)) -> 74397.64 | P100: =O100 -> 74397.64 | Q100: =J100-P100 -> -5014.3908 | R100: Projeto · topo da base
C101: CBUQ Faixa C – volume compactado (5 cm) – projeto | D101: m³ | G101: =IF($N$6<>"",0,(INDEX(Estacas!$T$1:$T$650,N3)+N5*N4*(2*INDEX(Estacas!$K$1:$K$650,N3)+(INDEX(Estacas!$K$1:$K$650,N3+1)-INDEX(Estacas!$K$1:$K$650,N3))*N4)/2*1)-(INDEX(Estacas!$T$1:$T$650,M3)+M5*M4*(2*INDEX(Estacas!$K$1:$K$650,M3)+(INDEX(Estacas!$K$1:$K$650,M3+1)-INDEX(Estacas!$K$1:$K$650,M3))*M4)/2*1)) -> 7445.2389 | L101: =(INDEX(Estacas!$T$1:$T$650,N13)+N15*N14*(2*INDEX(Estacas!$K$1:$K$650,N13)+(INDEX(Estacas!$K$1:$K$650,N13+1)-INDEX(Estacas!$K$1:$K$650,N13))*N14)/2*1)-(INDEX(Estacas!$T$1:$T$650,M13)+M15*M14*(2*INDEX(Estacas!$K$1:$K$650,M13)+(INDEX(Estacas!$K$1:$K$650,M13+1)-INDEX(Estacas!$K$1:$K$650,M13))*M14)/2*1) -> 7445.2389 | R101: referência para a tonelagem
B102: 570400 | C102: CBUQ Faixa C – massa (exclusive CAP) | D102: t | G102: =IF($N$6<>"",0,$G$101*$H$9) -> 17868.573 | H102: =IF($N$6<>"",0,$G$102) -> 17868.573 | I102: 263.04 | J102: =H102*I102 -> 4700149.5 | K102: =IF($N$6<>"",0,18747.81*IF($L$102=0,$N$9,$G$102/$L$102)) -> 18747.81 | L102: =$L$101*$H$9 -> 17868.573 | O102: =IF($N$6<>"",0,4931423.94*IF($L$102=0,$N$9,$G$102/$L$102)) -> 4931423.9 | P102: =O102 -> 4931423.9 | Q102: =J102-P102 -> -231274.41 | R102: Projeto · projeto: volume × densidade (premissa)
B103: 575000 | C103: Camada de fechamento do pavimento – saia (contenção lateral solo local) | D103: m³ | G103: =IF($N$6<>"",0,SUMPRODUCT('Terraplenagem por estaca'!$O$2:$O$744,((('Terraplenagem por estaca'!$D$2:$D$744<$N$2)*'Terraplenagem por estaca'!$D$2:$D$744+('Terraplenagem por estaca'!$D$2:$D$744>=$N$2)*$N$2)-(('Terraplenagem por estaca'!$C$2:$C$744>$M$2)*'Terraplenagem por estaca'!$C$2:$C$744+('Terraplenagem por estaca'!$C$2:$C$744<=$M$2)*$M$2))*('Terraplenagem por estaca'!$C$2:$C$744<$N$2)*('Terraplenagem por estaca'!$D$2:$D$744>$M$2)/('Terraplenagem por estaca'!$D$2:$D$744-'Terraplenagem por estaca'!$C$2:$C$744))+SUMPRODUCT('Terrapl. – ramos e solo mole'!$I$2:$I$14,((('Terrapl. – ramos e solo mole'!$C$2:$C$14<$N$2)*'Terrapl. – ramos e solo mole'!$C$2:$C$14+('Terrapl. – ramos e solo mole'!$C$2:$C$14>=$N$2)*$N$2)-(('Terrapl. – ramos e solo mole'!$B$2:$B$14>$M$2)*'Terrapl. – ramos e solo mole'!$B$2:$B$14+('Terrapl. – ramos e solo mole'!$B$2:$B$14<=$M$2)*$M$2))*('Terrapl. – ramos e solo mole'!$B$2:$B$14<$N$2)*('Terrapl. – ramos e solo mole'!$C$2:$C$14>$M$2)/('Terrapl. – ramos e solo mole'!$C$2:$C$14-'Terrapl. – ramos e solo mole'!$B$2:$B$14))) -> 2514.01 | H103: =IF($N$6<>"",0,$G$103) -> 2514.01 | I103: 44.25 | J103: =H103*I103 -> 111244.94 | K103: =IF($N$6<>"",0,2514.01*IF($L$103=0,$N$9,$G$103/$L$103)) -> 2514.01 | L103: =SUMPRODUCT('Terraplenagem por estaca'!$O$2:$O$744,((('Terraplenagem por estaca'!$D$2:$D$744<$N$12)*'Terraplenagem por estaca'!$D$2:$D$744+('Terraplenagem por estaca'!$D$2:$D$744>=$N$12)*$N$12)-(('Terraplenagem por estaca'!$C$2:$C$744>$M$12)*'Terraplenagem por estaca'!$C$2:$C$744+('Terraplenagem por estaca'!$C$2:$C$744<=$M$12)*$M$12))*('Terraplenagem por estaca'!$C$2:$C$744<$N$12)*('Terraplenagem por estaca'!$D$2:$D$744>$M$12)/('Terraplenagem por estaca'!$D$2:$D$744-'Terraplenagem por estaca'!$C$2:$C$744))+SUMPRODUCT('Terrapl. – ramos e solo mole'!$I$2:$I$14,((('Terrapl. – ramos e solo mole'!$C$2:$C$14<$N$12)*'Terrapl. – ramos e solo mole'!$C$2:$C$14+('Terrapl. – ramos e solo mole'!$C$2:$C$14>=$N$12)*$N$12)-(('Terrapl. – ramos e solo mole'!$B$2:$B$14>$M$12)*'Terrapl. – ramos e solo mole'!$B$2:$B$14+('Terrapl. – ramos e solo mole'!$B$2:$B$14<=$M$12)*$M$12))*('Terrapl. – ramos e solo mole'!$B$2:$B$14<$N$12)*('Terrapl. – ramos e solo mole'!$C$2:$C$14>$M$12)/('Terrapl. – ramos e solo mole'!$C$2:$C$14-'Terrapl. – ramos e solo mole'!$B$2:$B$14)) -> 2514.01 | O103: =IF($N$6<>"",0,111244.94*IF($L$103=0,$N$9,$G$103/$L$103)) -> 111244.94 | P103: =O103 -> 111244.94 | Q103: =J103-P103 -> 0.0025 | R103: Projeto · aba COBRIM. SAIA (terraplenagem)
B104: 516300 | C104: Preenchimento de rebaixo em rocha c/ aproveitamento de corte 3ª cat. | D104: m³ | G104: =IF($N$6<>"",0,SUMPRODUCT('Terraplenagem por estaca'!$N$2:$N$744,((('Terraplenagem por estaca'!$D$2:$D$744<$N$2)*'Terraplenagem por estaca'!$D$2:$D$744+('Terraplenagem por estaca'!$D$2:$D$744>=$N$2)*$N$2)-(('Terraplenagem por estaca'!$C$2:$C$744>$M$2)*'Terraplenagem por estaca'!$C$2:$C$744+('Terraplenagem por estaca'!$C$2:$C$744<=$M$2)*$M$2))*('Terraplenagem por estaca'!$C$2:$C$744<$N$2)*('Terraplenagem por estaca'!$D$2:$D$744>$M$2)/('Terraplenagem por estaca'!$D$2:$D$744-'Terraplenagem por estaca'!$C$2:$C$744))) -> 3079.1028 | H104: =IF($N$6<>"",0,$G$104) -> 3079.1028 | I104: 26.84 | J104: =H104*I104 -> 82643.118 | K104: =IF($N$6<>"",0,3079.1*IF($L$104=0,$N$9,$G$104/$L$104)) -> 3079.1 | L104: =SUMPRODUCT('Terraplenagem por estaca'!$N$2:$N$744,((('Terraplenagem por estaca'!$D$2:$D$744<$N$12)*'Terraplenagem por estaca'!$D$2:$D$744+('Terraplenagem por estaca'!$D$2:$D$744>=$N$12)*$N$12)-(('Terraplenagem por estaca'!$C$2:$C$744>$M$12)*'Terraplenagem por estaca'!$C$2:$C$744+('Terraplenagem por estaca'!$C$2:$C$744<=$M$12)*$M$12))*('Terraplenagem por estaca'!$C$2:$C$744<$N$12)*('Terraplenagem por estaca'!$D$2:$D$744>$M$12)/('Terraplenagem por estaca'!$D$2:$D$744-'Terraplenagem por estaca'!$C$2:$C$744)) -> 3079.1028 | O104: =IF($N$6<>"",0,82643.04*IF($L$104=0,$N$9,$G$104/$L$104)) -> 82643.04 | P104: =O104 -> 82643.04 | Q104: =J104-P104 -> 0.07781 | R104: Projeto · REV04 por intervalo (terraplenagem)
C105: Pavimento existente
...

Sheet Contrato × Projeto
B2: CONTRATO × PROJETO – SERVIÇOS DA PLANILHA CONTRATUAL CONFRONTADOS COM AS QUANTIDADES E CONSUMOS DOS PROJETOS
B3: Trecho inteiro 0+000 a 642+15,817 · Contrato = medição provisória ago/2026 (R$ 87.300.000,00) · Memória = total impresso nos quadros do Vol. 3 (Tomo II) e pranchas · Consumo real = apurado por estaca no Painel (atualiza com as premissas)
B5: RESUMO
B6: VALOR DO CONTRATO | F6: CONSUMO REAL A PREÇO DO CONTRATO | I6: REAL − CONTRATO | M6: SITUAÇÃO DOS ITENS | Q6: Como ler
B7: =L359 -> 87300000 | F7: =M359 -> 85313984 | I7: =N359 -> -1986016 | M7: =COUNTIF(O12:O358,"Confere*")&" conferem" -> 140 conferem | Q7: Verde = consumo real encontrado nos projetos · laranja = quantidade do contrato · amarelo na coluna "Quadro da memória" = total impresso diferente do contrato.
B8: =COUNT(F12:F358)&" itens da planilha contratual" -> 269 itens da planilha contratual | F8: projeto onde encontrado; contrato onde não | I8: =FIXED(IF(L359=0,0,N359/L359*100),1)&"% do contrato" -> -2.3% do contrato | M8: =COUNTIF(O12:O358,"Projeto maior")&" maiores · "&COUNTIF(O12:O358,"Projeto menor")&" menores · "&COUNTIF(O12:O358,"Não encontrado")&" não encontrados · "&(COUNTIF(O12:O358,"Medição mensal")+COUNTIF(O12:O358,"Mobilização"))&" mensais/mobilização" -> 29 maiores · 41 menores · 51 não encontrados · 8 mensais/mobilização | Q8: Situação: "Confere" = diferença de até ±2%. Detalhes das divergências na aba Discrepâncias; o link da última coluna leva à linha do Painel.
F10: REFERÊNCIAS | H10: CONSUMO REAL × CONTRATO | K10: VALORES A PREÇO DO CONTRATO | O10: ANÁLISE
B11: Linha med. | C11: Código | D11: Serviço | E11: Un | F11: Qtd. contrato | G11: Quadro da memória | H11: Consumo real (projeto) | I11: Real − contrato | J11: Dif. % | K11: Preço (R$) | L11: Valor contrato (R$) | M11: Valor consumo real (R$) | N11: Real − contrato (R$) | O11: Situação | P11: Como foi apurado · fonte | Q11: Discrepância / observação | R11: Painel
B12: Terraplenagem
B13: 17 | C13: 493647 | D13: Carga e transporte de material para bota fora | E13: m³ | F13: 46465.94 | G13: 46465.94 | H13: =Painel!$L$45 -> 47263.471 | I13: =IF(H13="","",H13-F13) -> 797.53062 | J13: =IF(OR(H13="",F13=0),"",H13/F13-1) -> 0.017163768 | K13: 11.78 | L13: 547368.77 | M13: =IF(H13="",F13*K13,H13*K13) -> 556763.68 | N13: =M13-L13 -> 9394.9139 | O13: =IF(F13=0,"Sem qtd. no contrato",IF(ABS(H13/F13-1)<=0.02,"Confere (±2%)",IF(H13>F13,"Projeto maior","Projeto menor"))) -> Confere (±2%) | P13: Projeto por estaca · volume de limpeza (área × 0,20 m) · memória: Quadro de terraplenagem (NCT-001) | Q13: Quadro = contrato. Por estaca (área de limpeza × 0,20 m) dá 47.263,47 m³. | R13: =HYPERLINK("#'Painel'!B45","→ 45") -> → 45
B14: 18 | C14: 400500 | D14: Colchão drenante de areia para fundação de aterros | E14: m³ | F14: 6633.83 | G14: 6633.83 | H14: =Painel!$L$82 -> 6633.825 | I14: =IF(H14="","",H14-F14) -> -0.005 | J14: =IF(OR(H14="",F14=0),"",H14/F14-1) -> -7.5371241e-07 | K14: 324.85 | L14: 2154999.7 | M14: =IF(H14="",F14*K14,H14*K14) -> 2154998.1 | N14: =M14-L14 -> -1.61875 | O14: =IF(F14=0,"Sem qtd. no contrato",IF(ABS(H14/F14-1)<=0.02,"Confere (±2%)",IF(H14>F14,"Projeto maior","Projeto menor"))) -> Confere (±2%) | P14: Projeto por estaca · 10 trechos de solo mole · memória: Quadro de terraplenagem 1.1.35 | R14: =HYPERLINK("#'Painel'!B82","→ 82") -> → 82
B15: 19 | C15: 401950 | D15: Compactação de aterros 95% PN (B) | E15: m³ | F15: 125515.05 | G15: 125515.05 | H15: =Painel!$L$78 -> 125515.05 | I15: =IF(H15="","",H15-F15) -> -0.0045417193 | J15: =IF(OR(H15="",F15=0),"",H15/F15-1) -> -3.6184659e-08 | K15: 6.18 | L15: 775683 | M15: =IF(H15="",F15*K15,H15*K15) -> 775682.98 | N15: =M15-L15 -> -0.019067826 | O15: =IF(F15=0,"Sem qtd. no contrato",IF(ABS(H15/F15-1)<=0.02,"Confere (±2%)",IF(H15>F15,"Projeto maior","Projeto menor"))) -> Confere (±2%) | P15: Projeto por estaca · REV04 por intervalo + ramos · memória: Quadro de terraplenagem 1.1.41 | R15: =HYPERLINK("#'Painel'!B78","→ 78") -> → 78
B16: 20 | C16: 401100 | D16: Compactação de aterros 100% PN (B) | E16: m³ | F16: 102477.69 | G16: 101065.34 | H16: =Painel!$L$79 -> 101065.32 | I16: =IF(H16="","",H16-F16) -> -1412.3691 | J16: =IF(OR(H16="",F16=0),"",H16/F16-1) -> -0.01378221 | K16: 7.44 | L16: 762434.01 | M16: =IF(H16="",F16*K16,H16*K16) -> 751925.99 | N16: =M16-L16 -> -10508.022 | O16: =IF(F16=0,"Sem qtd. no contrato",IF(ABS(H16/F16-1)<=0.02,"Confere (±2%)",IF(H16>F16,"Projeto maior","Projeto menor"))) -> Confere (±2%) | P16: Projeto por estaca · REV04 por intervalo + ramos · memória: Quadro de terraplenagem 1.1.40 | Q16: Contrato = quadro (101.065,34) + 1.412,35 m³. A mesma parcela de 1.412,35 m³ (preenchimento de rebaixo com material de 3ª, quadro 1.1.33) foi somada também ao 403000 e lançada como transporte 3ª cat. 400–600 m (430610). | R16: =HYPERLINK("#'Painel'!B79","→ 79") -> → 79
B17: 21 | C17: 403000 | D17: Compactação de aterros em 3a. cat. | E17: m³ | F17: 18294.23 | G17: 16881.88 | H17: =16881.88 -> 16881.88 | I17: =IF(H17="","",H17-F17) -> -1412.35 | J17: =IF(OR(H17="",F17=0),"",H17/F17-1) -> -0.077201937 | K17: 8 | L17: 146353.84 | M17: =IF(H17="",F17*K17,H17*K17) -> 135055.04 | N17: =M17-L17 -> -11298.8 | O17: =IF(F17=0,"Sem qtd. no contrato",IF(ABS(H17/F17-1)<=0.02,"Confere (±2%)",IF(H17>F17,"Projeto maior","Projeto menor"))) -> Projeto menor | P17: Total da memória (sem localização) · quadro de terraplenagem 16.881,88 m³ – distribuído pelo corte 3ª cat. · memória: Quadro de terraplenagem 1.1.38 | Q17: Contrato = quadro (16.881,88) + 1.412,35 m³ – mesma parcela somada ao 401100 e ao 430610. | R17: =HYPERLINK("#'Painel'!B80","→ 80") -> → 80
B18: 22 | C18: 400000 | D18: Desmatamento e limpeza diam. até 30cm | E18: m² | F18: 232329.7 | G18: 232329.7 | H18: =Painel!$L$44 -> 236317.35 | I18: =IF(H18="","",H18-F18) -> 3987.6531 | J18: =IF(OR(H18="",F18=0),"",H18/F18-1) -> 0.017163768 | K18: 1.25 | L18: 290412.12 | M18: =IF(H18="",F18*K18,H18*K18) -> 295396.69 | N18: =M18-L18 -> 4984.5714 | O18: =IF(F18=0,"Sem qtd. no contrato",IF(ABS(H18/F18-1)<=0.02,"Confere (±2%)",IF(H18>F18,"Projeto maior","Projeto menor"))) -> Confere (±2%) | P18: Projeto por estaca · REV04 por intervalo; ramos IN-01 na Est. 326 · memória: Quadro de terraplenagem 1.1.1 | R18: =HYPERLINK("#'Painel'!B44","→ 44") -> → 44
B19: 23 | C19: 400300 | D19: Destocamento árvores diam. > 30cm | E19: un | F19: 259 | G19: 259 | H19: =(Painel!$L$46)*1 -> 259 | I19: =IF(H19="","",H19-F19) -> 0 | J19: =IF(OR(H19="",F19=0),"",H19/F19-1) -> 0 | K19: 54.77 | L19: 14185.43 | M19: =IF(H19="",F19*K19,H19*K19) -> 14185.43 | N19: =M19-L19 -> 0 | O19: =IF(F19=0,"Sem qtd. no contrato",IF(ABS(H19/F19-1)<=0.02,"Confere (±2%)",IF(H19>F19,"Projeto maior","Projeto menor"))) -> Confere (±2%) | P19: Projeto por estaca – grupo repartido na proporção do contrato · árvores do projeto de interferências (IT-2-0001) · memória: IT-2-0001 – resumo 3.1 | Q19: Projeto de interferências IT-2-0001: 85 exóticas + 174 nativas = 259 árvores (= contrato), localizadas por coordenada. O paisagismo PG-01 só marca 16 delas na planta. | R19: =HYPERLINK("#'Painel'!B47","→ 47") -> → 47
B20: 24 | C20: 410200 | D20: Esc. carga e transp. 1a. cat. 0-200m | E20: m³ | F20: 101294.29 | G20: 101294.29 | H20: =(Painel!$L$49)*0.38667268 -> 99858.75 | I20: =IF(H20="","",H20-F20) -> -1435.5399 | J20: =IF(OR(H20="",F20=0),"",H20/F20-1) -> -0.014171972 | K20: 10.47 | L20: 1060551.2 | M20: =IF(H20="",F20*K20,H20*K20) -> 1045521.1 | N20: =M20-L20 -> -15030.096 | O20: =IF(F20=0,"Sem qtd. no contrato",IF(ABS(H20/F20-1)<=0.02,"Confere (±2%)",IF(H20>F20,"Projeto maior","Projeto menor"))) -> Confere (±2%) | P20: Projeto por estaca – grupo repartido na proporção do contrato · corte 1ª cat. do projeto × participação da faixa de DMT no contrato · memória: Quadro de terraplenagem (mesma faixa de DMT) | Q20: Corte 1ª cat. por estaca (REV04 + ramos) repartido entre as faixas na proporção do contrato: −1,4% em todas as faixas. | R20: =HYPERLINK("#'Painel'!B50","→ 50") -> → 50
B21: 25 | C21: 410400 | D21: Esc. carga e transp. 1a. cat. 200-400m | E21: m³ | F21: 13280.16 | G21: 13280.16 | H21: =(Painel!$L$49)*0.05069461 -> 13091.953 | I21: =IF(H21="","",H21-F21) -> -188.20742 | J21: =IF(OR(H21="",F21=0),"",H21/F21-1) -> -0.014172074 | K21: 10.76 | L21: 142894.52 | M21: =IF(H21="",F21*K21,H21*K21) -> 140869.41 | N21: =M21-L21 -> -2025.1102 | O21: =IF(F21=0,"Sem qtd. no contrato",IF(ABS(H21/F21-1)<=0.02,"Confere (±2%)",IF(H21>F21,"Projeto maior","Projeto menor"))) -> Confere (±2%) | P21: Projeto por estaca – grupo repartido na proporção do contrato · corte 1ª cat. do projeto × participação da faixa de DMT no contrato · memória: Quadro de terraplenagem (mesma faixa de DMT) | Q21: Corte 1ª cat. por estaca (REV04 + ramos) repartido entre as faixas na proporção do contrato: −1,4% em todas as faixas. | R21: =HYPERLINK("#'Painel'!B51","→ 51") -> → 51
B22: 26 | C22: 410800 | D22: Esc. carga e transp. 1a. cat. 600-800m | E22: m³ | F22: 4653.93 | G22: 4653.93 | H22: =(Painel!$L$49)*0.01776554 -> 4587.9751 | I22: =IF(H22="","",H22-F22) -> -65.954921 | J22: =IF(OR(H22="",F22=0),"",H22/F22-1) -> -0.014171876 | K22: 11.55 | L22: 53752.89 | M22: =IF(H22="",F22*K22,H22*K22) -> 52991.112 | N22: =M22-L22 -> -761.77784 | O22: =IF(F22=0,"Sem qtd. no contrato",IF(ABS(H22/F22-1)<=0.02,"Confere (±2%)",IF(H22>F22,"Projeto maior","Projeto menor"))) -> Confere (±2%) | P22: Projeto por estaca – grupo repartido na proporção do contrato · corte 1ª cat. do projeto × participação da faixa de DMT no contrato · memória: Quadro de terraplenagem (mesma faixa de DMT) | Q22: Corte 1ª cat. por estaca (REV04 + ramos) repartido entre as faixas na proporção do contrato: −1,4% em todas as faixas. | R22: =HYPERLINK("#'Painel'!B52","→ 52") -> → 52
B23: 27 | C23: 411000 | D23: Esc. carga e transp. 1a. cat. 800-1000m | E23: m³ | F23: 1642.77 | G23: 1642.77 | H23: =(Painel!$L$49)*0.00627098 -> 1619.4892 | I23: =IF(H23="","",H23-F23) -> -23.280811 | J23: =IF(OR(H23="",F23=0),"",H23/F23-1) -> -0.01417168 | K23: 11.99 | L23: 19696.81 | M23: =IF(H23="",F23*K23,H23*K23) -> 19417.675 | N23: =M23-L23 -> -279.13463 | O23: =IF(F23=0,"Sem qtd. no contrato",IF(ABS(H23/F23-1)<=0.02,"Confere (±2%)",IF(H23>F23,"Projeto maior","Projeto menor"))) -> Confere (±2%) | P23: Projeto por estaca – grupo repartido na proporção do contrato · corte 1ª cat. do projeto × participação da faixa de DMT no contrato · memória: Quadro de terraplenagem (mesma faixa de DMT) | Q23: Corte 1ª cat. por estaca (REV04 + ramos) repartido entre as faixas na proporção do contrato: −1,4% em todas as faixas. | R23: =HYPERLINK("#'Painel'!B53","→ 53") -> → 53
B24: 28 | C24: 411200 | D24: Esc. carga e transp. 1a. cat. 1000-1200m | E24: m³ | F24: 19198.55 | G24: 19198.55 | H24: =(Painel!$L$49)*0.073287 -> 18926.468 | I24: =IF(H24="","",H24-F24) -> -272.0817 | J24: =IF(OR(H24="",F24=0),"",H24/F24-1) -> -0.014171992 | K24: 12.38 | L24: 237678.04 | M24: =IF(H24="",F24*K24,H24*K24) -> 234309.68 | N24: =M24-L24 -> -3368.3625 | O24: =IF(F24=0,"Sem qtd. no contrato",IF(ABS(H24/F24-1)<=0.02,"Confere (±2%)",IF(H24>F24,"Projeto maior","Projeto menor"))) -> Confere (±2%) | P24: Projeto por estaca – grupo repartido na proporção do contrato · corte 1ª cat. do projeto × participação da faixa de DMT no contrato · memória: Quadro de terraplenagem (mesma faixa de DMT) | Q24: Corte 1ª cat. por estaca (REV04 + ramos) repartido entre as faixas na proporção do contrato: −1,4% em todas as faixas. | R24: =HYPERLINK("#'Painel'!B54","→ 54") -> → 54
B25: 29 | C25: 411400 | D25: Esc. carga e transp. 1a. cat. 1200-1400m | E25: m³ | F25: 5665.84 | G25: 5665.84 | H25: =(Painel!$L$49)*0.02162832 -> 5585.5433 | I25: =IF(H25="","",H25-F25) -> -80.296686 | J25: =IF(OR(H25="",F25=0),"",H25/F25-1) -> -0.014172071 | K25: 13.71 | L25: 77678.66 | M25: =IF(H25="",F25*K25,H25*K25) -> 76577.799 | N25: =M25-L25 -> -1100.8612 | O25: =IF(F25=0,"Sem qtd. no contrato",IF(ABS(H25/F25-1)<=0.02,"Confere (±2%)",IF(H25>F25,"Projeto maior","Projeto menor"))) -> Confere (±2%) | P25: Projeto por estaca – grupo repartido na proporção do contrato · corte 1ª cat. do projeto × participação da faixa de DMT no contrato · memória: Quadro de terraplenagem (mesma faixa de DMT) | Q25: Corte 1ª cat. por estaca (REV04 + ramos) repartido entre as faixas na proporção do contrato: −1,4% em todas as faixas. | R25: =HYPERLINK("#'Painel'!B55","→ 55") -> → 55
B26: 30 | C26: 411600 | D26: Esc. carga e transp. 1a. cat. 1400-1600m | E26: m³ | F26: 601.86 | G26: 601.86 | H26: =(Painel!$L$49)*0.00229749 -> 593.32994 | I26: =IF(H26="","",H26-F26) -> -8.5300554 | J26: =IF(OR(H26="",F26=0),"",H26/F26-1) -> -0.014172823 | K26: 14.16 | L26: 8522.33 | M26: =IF(H26="",F26*K26,H26*K26) -> 8401.552 | N26: =M26-L26 -> -120.77798 | O26: =IF(F26=0,"Sem qtd. no contrato",IF(ABS(H26/F26-1)<=0.02,"Confere (±2%)",IF(H26>F26,"Projeto maior","Projeto menor"))) -> Confere (±2%) | P26: Projeto por estaca – grupo repartido na proporção do contrato · corte 1ª cat. do projeto × participação da faixa de DMT no contrato · memória: Quadro de terraplenagem (mesma faixa de DMT) | Q26: Corte 1ª cat. por estaca (REV04 + ramos) repartido entre as faixas na proporção do contrato: −1,4% em todas as faixas. | R26: =HYPERLINK("#'Painel'!B56","→ 56") -> → 56
B27: 31 | C27: 412000 | D27: Esc. carga e transp. 1a. cat. 1600-2000m | E27: m³ | F27: 6926.57 | G27: 6926.57 | H27: =(Painel!$L$49)*0.02644093 -> 6828.4064 | I27: =IF(H27="","",H27-F27) -> -98.163551 | J27: =IF(OR(H27="",F27=0),"",H27/F27-1) -> -0.014172029 | K27: 14.9 | L27: 103205.89 | M27: =IF(H27="",F27*K27,H27*K27) -> 101743.26 | N27: =M27-L27 -> -1462.6339 | O27: =IF(F27=0,"Sem qtd. no contrato",IF(ABS(H27/F27-1)<=0.02,"Confere (±2%)",IF(H27>F27,"Projeto maior","Projeto menor"))) -> Confere (±2%) | P27: Projeto por estaca – grupo repartido na proporção do contrato · corte 1ª cat. do projeto × participação da faixa de DMT no contrato · memória: Quadro de terraplenagem (mesma faixa de DMT) | Q27: Corte 1ª cat. por estaca (REV04 + ramos) repartido entre as faixas na proporção do contrato: −1,4% em todas as faixas. | R27: =HYPERLINK("#'Painel'!B57","→ 57") -> → 57
B28: 32 | C28: 413000 | D28: Esc. carga e transp. 1a. cat. 2000-3000m | E28: m³ | F28: 17218.97 | G28: 17218.97 | H28: =(Painel!$L$49)*0.06573031 -> 16974.943 | I28: =IF(H28="","",H28-F28) -> -244.02726 | J28: =IF(OR(H28="",F28=0),"",H28/F28-1) -> -0.014172001 | K28: 17.21 | L28: 296338.47 | M28: =IF(H28="",F28*K28,H28*K28) -> 292138.76 | N28: =M28-L28 -> -4199.7055 | O28: =IF(F28=0,"Sem qtd. no contrato",IF(ABS(H28/F28-1)<=0.02,"Confere (±2%)",IF(H28>F28,"Projeto maior","Projeto menor"))) -> Confere (±2%) | P28: Projeto por estaca – grupo repartido na proporção do contrato · corte 1ª cat. do projeto × participação da faixa de DMT no contrato · memória: Quadro de terraplenagem (mesma faixa de DMT) | Q28: Corte 1ª cat. por estaca (REV04 + ramos) repartido entre as faixas na proporção do contrato: −1,4% em todas as faixas. | R28: =HYPERLINK("#'Painel'!B58","→ 58") -> → 58
B29: 33 | C29: 414000 | D29: Esc. carga e transp. 1a. cat. 3000-4000m | E29: m³ | F29: 34344.1 | G29: 34344.1 | H29: =(Painel!$L$49)*0.13110241 -> 33857.377 | I29: =IF(H29="","",H29-F29) -> -486.72275 | J29: =IF(OR(H29="",F29=0),"",H29/F29-1) -> -0.014171946 | K29: 19.27 | L29: 661810.8 | M29: =IF(H29="",F29*K29,H29*K29) -> 652431.66 | N29: =M29-L29 -> -9379.1403 | O29: =IF(F29=0,"Sem qtd. no contrato",IF(ABS(H29/F29-1)<=0.02,"Confere (±2%)",IF(H29>F29,"Projeto maior","Projeto menor"))) -> Confere (±2%) | P29: Projeto por estaca – grupo repartido na proporção do contrato · corte 1ª cat. do projeto × participação da faixa de DMT no contrato · memória: Quadro de terraplenagem (mesma faixa de DMT) | Q29: Corte 1ª cat. por estaca (REV04 + ramos) repartido entre as faixas na proporção do contrato: −1,4% em todas as faixas. | R29: =HYPERLINK("#'Painel'!B59","→ 59") -> → 59
B30: 34 | C30: 415000 | D30: Esc. carga e transp. 1a. cat. 4000-5000m | E30: m³ | F30: 39996.26 | G30: 39996.26 | H30: =(Painel!$L$49)*0.15267851 -> 39429.435 | I30: =IF(H30="","",H30-F30) -> -566.82532 | J30: =IF(OR(H30="",F30=0),"",H30/F30-1) -> -0.014171958 | K30: 22.25 | L30: 889916.78 | M30: =IF(H30="",F30*K30,H30*K30) -> 877304.92 | N30: =M30-L30 -> -12611.858 | O30: =IF(F30=0,"Sem qtd. no contrato",IF(ABS(H30/F30-1)<=0.02,"Confere (±2%)",IF(H30>F30,"Projeto maior","Projeto menor"))) -> Confere (±2%) | P30: Projeto por estaca – grupo repartido na proporção do contrato · corte 1ª cat. do projeto × participação da faixa de DMT no contrato · memória: Quadro de terraplenagem (mesma faixa de DMT) | Q30: Corte 1ª cat. por estaca (REV04 + ramos) repartido entre as faixas na proporção do contrato: −1,4% em todas as faixas. | R30: =HYPERLINK("#'Painel'!B60","→ 60") -> → 60
B31: 35 | C31: 416010 | D31: Esc. carga e transp. 1a. cat. 5000-6000m | E31: m³ | F31: 13777.85 | G31: 13777.85 | H31: =(Painel!$L$49)*0.05259446 -> 13582.591 | I31: =IF(H31="","",H31-F31) -> -195.25855 | J31: =IF(OR(H31="",F31=0),"",H31/F31-1) -> -0.014171917 | K31: 25.37 | L31: 349544.05 | M31: =IF(H31="",F31*K31,H31*K31) -> 344590.35 | N31: =M31-L31 -> -4953.7048 | O31: =IF(F31=0,"Sem qtd. no contrato",IF(ABS(H31/F31-1)<=0.02,"Confere (±2%)",IF(H31>F31,"Projeto maior","Projeto menor"))) -> Confere (±2%) | P31: Projeto por estaca – grupo repartido na proporção do contrato · corte 1ª cat. do projeto × participação da faixa de DMT no contrato · memória: Quadro de terraplenagem (mesma faixa de DMT) | Q31: Corte 1ª cat. por estaca (REV04 + ramos) repartido entre as faixas na proporção do contrato: −1,4% em todas as faixas. | R31: =HYPERLINK("#'Painel'!B61","→ 61") -> → 61
B32: 36 | C32: 418000 | D32: Esc. carga e transp. 1a. cat. 6000-8000m | E32: m³ | F32: 3362.77 | G32: 3362.77 | H32: =(Painel!$L$49)*0.01283677 -> 3315.1135 | I32: =IF(H32="","",H32-F32) -> -47.656536 | J32: =IF(OR(H32="",F32=0),"",H32/F32-1) -> -0.014171809 | K32: 29.3 | L32: 98529.16 | M32: =IF(H32="",F32*K32,H32*K32) -> 97132.825 | N32: =M32-L32 -> -1396.3355 | O32: =IF(F32=0,"Sem qtd. no contrato",IF(ABS(H32/F32-1)<=0.02,"Confere (±2%)",IF(H32>F32,"Projeto maior","Projeto menor"))) -> Confere (±2%) | P32: Projeto por estaca – grupo repartido na proporção do contrato · corte 1ª cat. do projeto × participação da faixa de DMT no contrato · memória: Quadro de terraplenagem (mesma faixa de DMT) | Q32: Corte 1ª cat. por estaca (REV04 + ramos) repartido entre as faixas na proporção do contrato: −1,4% em todas as faixas. | R32: =HYPERLINK("#'Painel'!B62","→ 62") -> → 62
B33: 37 | C33: 420400 | D33: Esc. carga e transp. 2a. cat. 200-400m | E33: m³ | F33: 5535 | G33: 5535 | H33: =(Painel!$L$63)*0.17495017 -> 5535 | I33: =IF(H33="","",H33-F33) -> -6.1139963e-07 | J33: =IF(OR(H33="",F33=0),"",H33/F33-1) -> -1.1046064e-10 | K33: 14.84 | L33: 82139.4 | M33: =IF(H33="",F33*K33,H33*K33) -> 82139.4 | N33: =M33-L33 -> -9.0731628e-06 | O33: =IF(F33=0,"Sem qtd. no contrato",IF(ABS(H33/F33-1)<=0.02,"Confere (±2%)",IF(H33>F33,"Projeto maior","Projeto menor"))) -> Confere (±2%) | P33: Projeto por estaca – grupo repartido na proporção do contrato · corte 2ª cat. do projeto × participação da faixa de DMT no contrato · memória: Quadro de terraplenagem (mesma faixa de DMT) | Q33: Corte 2ª cat. por estaca = quadro = contrato (31.637,58 m³). | R33: =HYPERLINK("#'Painel'!B64","→ 64") -> → 64
B34: 38 | C34: 420800 | D34: Esc. carga e transp. 2a. cat. 600-800m | E34: m³ | F34: 267.12 | G34: 267.12 | H34: =(Painel!$L$63)*0.00844312 -> 267.11988 | I34: =IF(H34="","",H34-F34) -> -0.0001155504 | J34: =IF(OR(H34="",F34=0),"",H34/F34-1) -> -4.3257862e-07 | K34: 15.81 | L34: 4223.16 | M34: =IF(H34="",F34*K34,H34*K34) -> 4223.1654 | N34: =M34-L34 -> 0.0053731482 | O34: =IF(F34=0,"Sem qtd. no contrato",IF(ABS(H34/F34-1)<=0.02,"Confere (±2%)",IF(H34>F34,"Projeto maior","Projeto menor"))) -> Confere (±2%) | P34: Projeto por estaca – grupo repartido na proporção do contrato · corte 2ª cat. do projeto × participação da faixa de DMT no contrato · memória: Quadro de terraplenagem (mesma faixa de DMT) | Q34: Corte 2ª cat. por estaca = quadro = contrato (31.637,58 m³). | R34: =HYPERLINK("#'Painel'!B65","→ 65") -> → 65
B35: 39 | C35: 422000 | D35: Esc. carga e transp. 2a. cat. 1600-2000m | E35: m³ | F35: 8489.19 | G35: 8489.19 | H35: =(Painel!$L$63)*0.26832615 -> 8489.19 | I35: =IF(H35="","",H35-F35) -> 3.6717e-05 | J35: =IF(OR(H35="",F35=0),"",H35/F35-1) -> 4.3251476e-09 | K35: 19.99 | L35: 169698.9 | M35: =IF(H35="",F35*K35,H35*K35) -> 169698.91 | N35: =M35-L35 -> 0.0088339728 | O35: =IF(F35=0,"Sem qtd. no contrato",IF(ABS(H35/F35-1)<=0.02,"Confere (±2%)",IF(H35>F35,"Projeto maior","Projeto menor"))) -> Confere (±2%) | P35: Projeto por estaca – grupo repartido na proporção do contrato · corte 2ª cat. do projeto × participação da faixa de DMT no contrato · memória: Quadro de terraplenagem (mesma faixa de DMT) | Q35: Corte 2ª cat. por estaca = quadro = contrato (31.637,58 m³). | R35: =HYPERLINK("#'Painel'!B66","→ 66") -> → 66
B36: 40 | C36: 423000 | D36: Esc. carga e transp. 2a. cat. 2000-3000m | E36: m³ | F36: 17346.27 | G36: 17346.27 | H36: =(Painel!$L$63)*0.54828056 -> 17346.27 | I36: =IF(H36="","",H36-F36) -> 7.9444802e-05 | J36: =IF(OR(H36="",F36=0),"",H36/F36-1) -> 4.5799358e-09 | K36: 21.84 | L36: 378842.53 | M36: =IF(H36="",F36*K36,H36*K36) -> 378842.54 | N36: =M36-L36 -> 0.0085350745 | O36: =IF(F36=0,"Sem qtd. no contrato",IF(ABS(H36/F36-1)<=0.02,"Confere (±2%)",IF(H36>F36,"Projeto maior","Projeto menor"))) -> Confere (±2%) | P36: Projeto por estaca – grupo repartido na proporção do contrato · corte 2ª cat. do projeto × participação da faixa de DMT no contrato · memória: Quadro de terraplenagem (mesma faixa de DMT) | Q36: Corte 2ª cat. por estaca = quadro = contrato (31.637,58 m³). | R36: =HYPERLINK("#'Painel'!B67","→ 67") -> → 67
B37: 41 | C37: 430410 | D37: Esc. carga e transp. 3a. cat. 200-400m | E37: m³ | F37: 2271.55 | G37: 2271.55 | H37: =(Painel!$L$68)*0.15776395 -> 2757.3213 | I37: =IF(H37="","",H37-F37) -> 485.77125 | J37: =IF(OR(H37="",F37=0),"",H37/F37-1) -> 0.21385012 | K37: 46.71 | L37: 106104.1 | M37: =IF(H37="",F37*K37,H37*K37) -> 128794.48 | N37: =M37-L37 -> 22690.376 | O37: =IF(F37=0,"Sem qtd. no contrato",IF(ABS(H37/F37-1)<=0.02,"Confere (±2%)",IF(H37>F37,"Projeto maior","Projeto menor"))) -> Projeto maior | P37: Projeto por estaca – grupo repartido na proporção do contrato · corte 3ª cat. do projeto × participação da faixa de DMT no contrato · memória: Quadro de terraplenagem (mesma faixa de DMT) | Q37: Corte 3ª cat. por estaca: 17.477,51 m³ contra 14.398,41 m³ das faixas do contrato (+21,4%), repartido na proporção do contrato. Note que o quadro soma 12.986,06 m³ sem o 430610. | R37: =HYPERLINK("#'Painel'!B69","→ 69") -> → 69
B38: 42 | C38: 430610 | D38: Esc. carga e transp. 3a. cat. 400-600m | E38: m³ | F38: 1412.35 | G38: 0 | H38: =(Painel!$L$68)*0.09809069 -> 1714.3812 | I38: =IF(H38="","",H38-F38) -> 302.03116 | J38: =IF(OR(H38="",F38=0),"",H38/F38-1) -> 0.21385008 | K38: 48.32 | L38: 68244.75 | M38: =IF(H38="",F38*K38,H38*K38) -> 82838.898 | N38: =M38-L38 -> 14594.148 | O38: =IF(F38=0,"Sem qtd. no contrato",IF(ABS(H38/F38-1)<=0.02,"Confere (±2%)",IF(H38>F38,"Projeto maior","Projeto menor"))) -> Projeto maior | P38: Projeto por estaca – grupo repartido na proporção do contrato · corte 3ª cat. do projeto × participação da faixa de DMT no contrato · memória: Faixa 400–600 m inexistente no quadro de terraplenagem | Q38: Faixa de DMT que não existe no quadro de terraplenagem; os 1.412,35 m³ são o preenchimento de rebaixo com material de 3ª (quadro 1.1.33), que já está no 495161. | R38: =HYPERLINK("#'Painel'!B70","→ 70") -> → 70
B39: 43 | C39: 431410 | D39: Esc. carga e transp. 3a. cat. 1200-1400m | E39: m³ | F39: 435.13 | G39: 435.13 | H39: =(Painel!$L$68)*0.0302207 -> 528.18263 | I39: =IF(H39="","",H39-F39) -> 93.052632 | J39: =IF(OR(H39="",F39=0),"",H39/F39-1) -> 0.21385019 | K39: 50.52 | L39: 21982.76 | M39: =IF(H39="",F39*K39,H39*K39) -> 26683.787 | N39: =M39-L39 -> 4701.0266 | O39: =IF(F39=0,"Sem qtd. no contrato",IF(ABS(H39/F39-1)<=0.02,"Confere (±2%)",IF(H39>F39,"Projeto maior","Projeto menor"))) -> Projeto maior | P39: Projeto por estaca – grupo repartido na proporção do contrato · corte 3ª cat. do projeto × participação da faixa de DMT no contrato · memória: Quadro de terraplenagem (mesma faixa de DMT) | Q39: Corte 3ª cat. por estaca: 17.477,51 m³ contra 14.398,41 m³ das faixas do contrato (+21,4%), repartido na proporção do contrato. Note que o quadro soma 12.986,06 m³ sem o 430610. | R39: =HYPERLINK("#'Painel'!B71","→ 71") -> → 71
B40: 44 | C40: 432010 | D40: Esc. carga e transp. 3a. cat. 1600-2000m | E40: m³ | F40: 763.27 | G40: 763.27 | H40: =(Painel!$L$68)*0.05301071 -> 926.49529 | I40: =IF(H40="","",H40-F40) -> 163.22529 | J40: =IF(OR(H40="",F40=0),"",H40/F40-1) -> 0.21385001 | K40: 53.74 | L40: 41018.12 | M40: =IF(H40="",F40*K40,H40*K40) -> 49789.857 | N40: =M40-L40 -> 8771.7371 | O40: =IF(F40=0,"Sem qtd. no contrato",IF(ABS(H40/F40-1)<=0.02,"Confere (±2%)",IF(H40>F40,"Projeto maior","Projeto menor"))) -> Projeto maior | P40: Projeto por estaca – grupo repartido na proporção do contrato · corte 3ª cat. do projeto × participação da faixa de DMT no contrato · memória: Quadro de terraplenagem (mesma faixa de DMT) | Q40: Corte 3ª cat. por estaca: 17.477,51 m³ contra 14.398,41 m³ das faixas do contrato (+21,4%), repartido na proporção do contrato. Note que o quadro soma 12.986,06 m³ sem o 430610. | R40: =HYPERLINK("#'Painel'!B72","→ 72") -> → 72
B41: 45 | C41: 433010 | D41: Esc. carga e transp. 3a. cat. 2000-3000m | E41: m³ | F41: 1070.38 | G41: 1070.38 | H41: =(Painel!$L$68)*0.07434015 -> 1299.2808 | I41: =IF(H41="","",H41-F41) -> 228.90083 | J41: =IF(OR(H41="",F41=0),"",H41/F41-1) -> 0.21385006 | K41: 57.73 | L41: 61793.03 | M41: =IF(H41="",F41*K41,H41*K41) -> 75007.482 | N41: =M41-L41 -> 13214.452 | O41: =IF(F41=0,"Sem qtd. no contrato",IF(ABS(H41/F41-1)<=0.02,"Confere (±2%)",IF(H41>F41,"Projeto maior","Projeto menor"))) -> Projeto maior | P41: Projeto por estaca – grupo repartido na proporção do contrato · corte 3ª cat. do projeto × participação da faixa de DMT no contrato · memória: Quadro de terraplenagem (mesma faixa de DMT) | Q41: Corte 3ª cat. por estaca: 17.477,51 m³ contra 14.398,41 m³ das faixas do contrato (+21,4%), repartido na proporção do contrato. Note que o quadro soma 12.986,06 m³ sem o 430610. | R41: =HYPERLINK("#'Painel'!B73","→ 73") -> → 73
B42: 46 | C42: 434010 | D42: Esc. carga e transp. 3a. cat. 3000-4000m | E42: m³ | F42: 8445.73 | G42: 8445.73 | H42: =(Painel!$L$68)*0.5865738 -> 10251.85 | I42: =IF(H42="","",H42-F42) -> 1806.1203 | J42: =IF(OR(H42="",F42=0),"",H42/F42-1) -> 0.21385012 | K42: 62.3 | L42: 526168.97 | M42: =IF(H42="",F42*K42,H42*K42) -> 638690.28 | N42: =M42-L42 -> 112521.31 | O42: =IF(F42=0,"Sem qtd. no contrato",IF(ABS(H42/F42-1)<=0.02,"Confere (±2%)",IF(H42>F42,"Projeto maior","Projeto menor"))) -> Projeto maior | P42: Projeto por estaca – grupo repartido na proporção do contrato · corte 3ª cat. do projeto × participação da faixa de DMT no contrato · memória: Quadro de terraplenagem (mesma faixa de DMT) | Q42: Corte 3ª cat. por estaca: 17.477,51 m³ contra 14.398,41 m³ das faixas do contrato (+21,4%), repartido na proporção do contrato. Note que o quadro soma 12.986,06 m³ sem o 430610. | R42: =HYPERLINK("#'Painel'!B74","→ 74") -> → 74
B43: 47 | C43: 404300 | D43: Espalhamento e conformação de bota-fora | E43: m³ | F43: 75087.01 | G43: 75087.01 | H43: =Painel!$L$76 -> 75884.541 | I43: =IF(H43="","",H43-F43) -> 797.53062 | J43: =IF(OR(H43="",F43=0),"",H43/F43-1) -> 0.010621419 | K43: 0.87 | L43: 65325.69 | M43: =IF(H43="",F43*K43,H43*K43) -> 66019.55 | N43: =M43-L43 -> 693.86034 | O43: =IF(F43=0,"Sem qtd. no contrato",IF(ABS(H43/F43-1)<=0.02,"Confere (±2%)",IF(H43>F43,"Projeto maior","Projeto menor"))) -> Confere (±2%) | P43: Projeto por estaca · volume de limpeza + solo mole removido · memória: Quadro de terraplenagem 1.1.42 | Q43: Quadro = contrato. Por estaca (limpeza + solo mole removido) dá 75.884,54 m³ (+1,1%). | R43: =HYPERLINK("#'Painel'!B76","→ 76") -> → 76
B44: 48 | C44: 404000 | D44: Remoção de solos moles | E44: m³ | F44: 28621.07 | G44: 28621.07 | H44: =Painel!$L$75 -> 28621.07 | I44: =IF(H44="","",H44-F44) -> 0 | J44: =IF(OR(H44="",F44=0),"",H44/F44-1) -> 0 | K44: 20.54 | L44: 587876.77 | M44: =IF(H44="",F44*K44,H44*K44) -> 587876.78 | N44: =M44-L44 -> 0.0077999999 | O44: =IF(F44=0,"Sem qtd. no contrato",IF(ABS(H44/F44-1)<=0.02,"Confere (±2%)",IF(H44>F44,"Projeto maior","Projeto menor"))) -> Confere (±2%) | P44: Projeto por estaca · REV04 / aba SOLO MOLE · memória: Quadro de terraplenagem 1.1.25 a 1.1.30 | R44: =HYPERLINK("#'Painel'!B75","→ 75") -> → 75
B45: 49 | C45: 495160 | D45: Fundação de aterro com brita | E45: m³ | F45: 1326.77 | G45: 1326.77 | H45: =Painel!$L$83 -> 1326.765 | I45: =IF(H45="","",H45-F45) -> -0.005 | J45: =IF(OR(H45="",F45=0),"",H45/F45-1) -> -3.7685507e-06 | K45: 164 | L45: 217590.28 | M45: =IF(H45="",F45*K45,H45*K45) -> 217589.46 | N45: =M45-L45 -> -0.82 | O45: =IF(F45=0,"Sem qtd. no contrato",IF(ABS(H45/F45-1)<=0.02,"Confere (±2%)",IF(H45>F45,"Projeto maior","Projeto menor"))) -> Confere (±2%) | P45: Projeto por estaca · 10 trechos de solo mole · memória: Quadro de terraplenagem 1.1.36 | R45: =HYPERLINK("#'Painel'!B83","→ 83") -> → 83
B46: 50 | C46: 495161 | D46: Fundação de aterro com rachão | E46: m³ | F46: 28703.95 | G46: 27235.29 | H46: =Painel!$L$81 -> 27235.294 | I46: =IF(H46="","",H46-F46) -> -1468.656 | J46: =IF(OR(H46="",F46=0),"",H46/F46-1) -> -0.051165641 | K46: 169.76 | L46: 4872782.5 | M46: =IF(H46="",F46*K46,H46*K46) -> 4623463.5 | N46: =M46-L46 -> -249319.04 | O46: =IF(F46=0,"Sem qtd. no contrato",IF(ABS(H46/F46-1)<=0.02,"Confere (±2%)",IF(H46>F46,"Projeto maior","Projeto menor"))) -> Projeto menor | P46: Projeto por estaca · REV04 por intervalo · memória: Quadro de terraplenagem 1.1.32 + 1.1.33 | Q46: Quadro: rachão 25.822,95 + material de 3ª 1.412,35 = 27.235,29 m³ (igual ao apurado por estaca); contrato 28.703,95 (+1.468,66). | R46: =HYPERLINK("#'Painel'!B81","→ 81") -> → 81
D47: Subtotal – Terraplenagem | L47: =SUM(L13:L46) -> 15895347 | M47: =SUM(M13:M46) -> 15759096 | N47: =SUM(N13:N46) -> -136251.4
B49: Pavimentação
B50: 53 | C50: 530200 | D50: Bica corrida | E50: m³ | F50: 84642 | G50: 84642 | H50: =(Painel!$L$95+Painel!$L$96)*1 -> 82744.391 | I50: =IF(H50="","",H50-F50) -> -1897.6091 | J50: =IF(OR(H50="",F50=0),"",H50/F50-1) -> -0.022419238 | K50: 180.59 | L50: 15285499 | M50: =IF(H50="",F50*K50,H50*K50) -> 14942810 | N50: =M50-L50 -> -342689.23 | O50: =IF(F50=0,"Sem qtd. no contrato",IF(ABS(H50/F50-1)<=0.02,"Confere (±2%)",IF(H50>F50,"Projeto maior","Projeto menor"))) -> Projeto menor | P50: Projeto por estaca – grupo repartido na proporção do contrato · reforço + sub-base do projeto · memória: Tab. 71 (sub-base 33.325 + reforço 51.317) | Q50: Tab. 71 = contrato. Por estaca (larguras medidas × espessuras PV-2): 82.744,39 m³ (−2,2%). | R50: =HYPERLINK("#'Painel'!B97","→ 97") -> → 97
B51: 54 | C51: 531100 | D51: Brita graduada 100% Pm | E51: m³ | F51: 25878.66 | G51: 25877.5 | H51: =Painel!$L$98 -> 24462.413 | I51: =IF(H51="","",H51-F51) -> -1416.247 | J51: =IF(OR(H51="",F51=0),"",H51/F51-1) -> -0.054726443 | K51: 241.97 | L51: 6261859.4 | M51: =IF(H51="",F51*K51,H51*K51) -> 5919170.1 | N51: =M51-L51 -> -342689.29 | O51: =IF(F51=0,"Sem qtd. no contrato",IF(ABS(H51/F51-1)<=0.02,"Confere (±2%)",IF(H51>F51,"Projeto maior","Projeto menor"))) -> Projeto menor | P51: Projeto por estaca · espessura em Parâmetros C2 · memória: Tab. 71 item 4 | Q51: Tab. 71 = contrato. Por estaca (larguras medidas × 0,16 m): −5,5%. | R51: =HYPERLINK("#'Painel'!B98","→ 98") -> → 98
B52: 55 | C52: 570400 | D52: C.B.U.Q. excl. fornec. do CAP (acima de 10.000 t) | E52: t | F52: 18747.81 | G52: 18744.5 | H52: =Painel!$L$102 -> 17868.573 | I52: =IF(H52="","",H52-F52) -> -879.23666 | J52: =IF(OR(H52="",F52=0),"",H52/F52-1) -> -0.046898099 | K52: 263.04 | L52: 4931423.9 | M52: =IF(H52="",F52*K52,H52*K52) -> 4700149.5 | N52: =M52-L52 -> -231274.41 | O52: =IF(F52=0,"Sem qtd. no contrato",IF(ABS(H52/F52-1)<=0.02,"Confere (±2%)",IF(H52>F52,"Projeto maior","Projeto menor"))) -> Projeto menor | P52: Projeto por estaca · projeto: volume × densidade (premissa) · memória: Tab. 71 item 1 | Q52: Tab. 71 = contrato. Por estaca: volume de CBUQ × densidade = −4,7%. | R52: =HYPERLINK("#'Painel'!B102","→ 102") -> → 102
B53: 56 | C53: 575000 | D53: Contenção lateral com solo local | E53: m³ | F53: 2514.01 | G53: 2514.01 | H53: =Painel!$L$103 -> 2514.01 | I53: =IF(H53="","",H53-F53) -> 0 | J53: =IF(OR(H53="",F53=0),"",H53/F53-1) -> 0 | K53: 44.25 | L53: 111244.94 | M53: =IF(H53="",F53*K53,H53*K53) -> 111244.94 | N53: =M53-L53 -> 0.0025 | O53: =IF(F53=0,"Sem qtd. no contrato",IF(ABS(H53/F53-1)<=0.02,"Confere (±2%)",IF(H53>F53,"Projeto maior","Projeto menor"))) -> Confere (±2%) | P53: Projeto por estaca · aba COBRIM. SAIA (terraplenagem) · memória: Quadro de terraplenagem 1.1.37 | Q53: Contrato usa o número do item 401200 (2.514,01 m³, compactação c/ controle visual); o quadro traz 3.519,61 m³ de material para camada de fechamento (NCT-002). | R53: =HYPERLINK("#'Painel'!B103","→ 103") -> → 103
B54: 57 | C54: 591490 | D54: Corte de pavimento asfáltico / concreto c/serra disco | E54: m | F54: 17 | G54: 17 | H54: =17 -> 17 | I54: =IF(H54="","",H54-F54) -> 0 | J54: =IF(OR(H54="",F54=0),"",H54/F54-1) -> 0 | K54: 9.59 | L54: 163.03 | M54: =IF(H54="",F54*K54,H54*K54) -> 163.03 | N54: =M54-L54 -> 0 | O54: =IF(F54=0,"Sem qtd. no contrato",IF(ABS(H54/F54-1)<=0.02,"Confere (±2%)",IF(H54>F54,"Projeto maior","Projeto menor"))) -> Confere (±2%) | P54: Total da memória (sem localização) · memória de pavimentação 17 m – distribuído pela demolição de pavimento · memória: Tab. 71 item 10 | R54: =HYPERLINK("#'Painel'!B107","→ 107") -> → 107
B55: 58 | C55: 512050 | D55: Demolição mecânica de pavimento | E55: m³ | F55: 689 | G55: 689 | H55: =Painel!$L$106 -> 1028.2023 | I55: =IF(H55="","",H55-F55) -> 339.2023 | J55: =IF(OR(H55="",F55=0),"",H55/F55-1) -> 0.49231104 | K55: 57.28 | L55: 39465.92 | M55: =IF(H55="",F55*K55,H55*K55) -> 58895.428 | N55: =M55-L55 -> 19429.508 | O55: =IF(F55=0,"Sem qtd. no contrato",IF(ABS(H55/F55-1)<=0.02,"Confere (±2%)",IF(H55>F55,"Projeto maior","Projeto menor"))) -> Projeto maior | P55: Projeto por estaca · ≈ 6,50 m × 0,41 m (Parâmetros C10) · memória: Tab. 71 item 9 | Q55: Tab. 71: 689 m³ (remoção mecanizada de camada granular). Estimativa por estaca (T09, 6,50 m × 0,41 m): 1.028,20 m³ – confirmar em campo. | R55: =HYPERLINK("#'Painel'!B106","→ 106") -> → 106
B56: 59 | C56: 505100 | D56: Fresagem descontínua a frio | E56: m³ | F56: 172.5 | G56: 172.5 | H56: =172.5 -> 172.5 | I56: =IF(H56="","",H56-F56) -> 0 | J56: =IF(OR(H56="",F56=0),"",H56/F56-1) -> 0 | K56: 341.15 | L56: 58848.37 | M56: =IF(H56="",F56*K56,H56*K56) -> 58848.375 | N56: =M56-L56 -> 0.005 | O56: =IF(F56=0,"Sem qtd. no contrato",IF(ABS(H56/F56-1)<=0.02,"Confere (±2%)",IF(H56>F56,"Projeto maior","Projeto menor"))) -> Confere (±2%) | P56: Total da memória (sem localização) · memória de pavimentação 172,50 m³ – distribuído pela demolição de pavimento · memória: Tab. 71 item 8 | R56: =HYPERLINK("#'Painel'!B108","→ 108") -> → 108
B57: 60 | C57: 560100 | D57: Imprimação impermeab. exclusive fornec. da emulsão | E57: m² | F57: 161756 | G57: 161734 | H57: =Painel!$L$99 -> 150833.15 | I57: =IF(H57="","",H57-F57) -> -10922.85 | J57: =IF(OR(H57="",F57=0),"",H57/F57-1) -> -0.067526704 | K57: 0.79 | L57: 127787.24 | M57: =IF(H57="",F57*K57,H57*K57) -> 119158.19 | N57: =M57-L57 -> -8629.0512 | O57: =IF(F57=0,"Sem qtd. no contrato",IF(ABS(H57/F57-1)<=0.02,"Confere (±2%)",IF(H57>F57,"Projeto maior","Projeto menor"))) -> Projeto menor | P57: Projeto por estaca · topo da base · memória: Tab. 71 item 3 | Q57: Tab. 71: 161.734 m² (contrato +22 m² a mais que a pintura). Por estaca, topo da base: 150.833,15 m² (−6,8%). | R57: =HYPERLINK("#'Painel'!B99","→ 99") -> → 99
B58: 61 | C58: 561100 | D58: Pintura de ligação exclusive fornec. da emulsão | E58: m² | F58: 161734 | G58: 161734 | H58: =Painel!$L$100 -> 150833.15 | I58: =IF(H58="","",H58-F58) -> -10900.85 | J58: =IF(OR(H58="",F58=0),"",H58/F58-1) -> -0.067399864 | K58: 0.46 | L58: 74397.64 | M58: =IF(H58="",F58*K58,H58*K58) -> 69383.249 | N58: =M58-L58 -> -5014.3908 | O58: =IF(F58=0,"Sem qtd. no contrato",IF(ABS(H58/F58-1)<=0.02,"Confere (±2%)",IF(H58>F58,"Projeto maior","Projeto menor"))) -> Projeto menor | P58: Projeto por estaca · topo da base · memória: Tab. 71 item 2 | Q58: Tab. 71 = contrato. Por estaca, topo da base: −6,7%. | R58: =HYPERLINK("#'Painel'!B100","→ 100") -> → 100
B59: 62 | C59: 516300 | D59: Preenchimento rebaixo c/ aprov. corte 3a. cat. | E59: m³ | F59: 3079.1 | G59: 3079.1 | H59: =Painel!$L$104 -> 3079.1028 | I59: =IF(H59="","",H59-F59) -> 0.00275 | J59: =IF(OR(H59="",F59=0),"",H59/F59-1) -> 8.9311812e-07 | K59: 26.84 | L59: 82643.04 | M59: =IF(H59="",F59*K59,H59*K59) -> 82643.118 | N59: =M59-L59 -> 0.07781 | O59: =IF(F59=0,"Sem qtd. no contrato",IF(ABS(H59/F59-1)<=0.02,"Confere (±2%)",IF(H59>F59,"Projeto maior","Projeto menor"))) -> Confere (±2%) | P59: Projeto por estaca · REV04 por intervalo (terraplenagem) · memória: Quadro de terraplenagem 1.1.39 | R59: =HYPERLINK("#'Painel'!B104","→ 104") -> → 104
B60: 63 | C60: 511200 | D60: Regularização compac.subleito 100% PN (B) | E60: m² | F60: 171057 | G60: 171057 | H60: =Painel!$L$94 -> 172945.16 | I60: =IF(H60="","",H60-F60) -> 1888.1556 | J60: =IF(OR(H60="",F60=0),"",H60/F60-1) -> 0.011038166 | K60: 5.16 | L60: 882654.12 | M60: =IF(H60="",F60*K60,H60*K60) -> 892397 | N60: =M60-L60 -> 9742.8831 | O60: =IF(F60=0,"Sem qtd. no contrato",IF(ABS(H60/F60-1)<=0.02,"Confere (±2%)",IF(H60>F60,"Projeto maior","Projeto menor"))) -> Confere (±2%) | P60: Projeto por estaca · largura medida + Detalhe "A" · áreas médias · memória: Tab. 71 item 7 | R60: =HYPERLINK("#'Painel'!B94","→ 94") -> → 94
D61: Subtotal – Pavimentação | L61: =SUM(L50:L60) -> 27855986 | M61: =SUM(M50:M60) -> 26954862 | N61: =SUM(N50:N60) -> -901123.89
B63: Ligantes Betuminosos
B64: 66 | C64: 589000 | D64: Fornecimento de CAP-50/70 | E64: t | F64: 1068.62 | G64: 1068.64 | H64: =Painel!$L$112 -> 857.69152 | I64: =IF(H64="","",H64-F64) -> -210.92848 | J64: =IF(OR(H64="",F64=0),"",H64/F64-1) -> -0.19738399 | K64: 5547.75 | L64: 5928436.6 | M64: =IF(H64="",F64*K64,H64*K64) -> 4758258.1 | N64: =M64-L64 -> -1170178.5 | O64: =IF(F64=0,"Sem qtd. no contrato",IF(ABS(H64/F64-1)<=0.02,"Confere (±2%)",IF(H64>F64,"Projeto maior","Projeto menor"))) -> Projeto menor | P64: Projeto por estaca · CBUQ (t) × teor executado; contrato ajustado de 5,7% para o teor executado · memória: Tab. 71 item 11.1 (teor 5,7%) | Q64: Contrato a 5,7% de CAP (Tab. 70). Painel usa o teor executado (premissa, 4,8%) sobre o CBUQ apurado por estaca. | R64: =HYPERLINK("#'Painel'!B112","→ 112") -> → 112
B65: 67 | C65: 589190 | D65: Fornecimento de emulsão asfáltica EAI p/ imprimação | E65: t | F65: 194.1 | G65: 194.08 | H65: =Painel!$L$113 -> 180.99978 | I65: =IF(H65="","",H65-F65) -> -13.10022 | J65: =IF(OR(H65="",F65=0),"",H65/F65-1) -> -0.067492115 | K65: 5716.46 | L65: 1109564.9 | M65: =IF(H65="",F65*K65,H65*K65) -> 1034678 | N65: =M65-L65 -> -74886.875 | O65: =IF(F65=0,"Sem qtd. no contrato",IF(ABS(H65/F65-1)<=0.02,"Confere (±2%)",IF(H65>F65,"Projeto maior","Projeto menor"))) -> Projeto menor | P65: Projeto por estaca · área × taxa (premissa) · memória: Tab. 71 item 11.2 | Q65: Tab. 70 indica 1,2 l/m² e a Tab. 71 usa 1,2 kg/m² × 161.734 m². Painel: área por estaca × taxa (premissa). | R65: =HYPERLINK("#'Painel'!B113","→ 113") -> → 113
B66: 68 | C66: 589420 | D66: Fornecimento de emulsão asfáltica RR-1C | E66: t | F66: 80.86 | G66: 80.87 | H66: =Painel!$L$114 -> 75.416575 | I66: =IF(H66="","",H66-F66) -> -5.4434248 | J66: =IF(OR(H66="",F66=0),"",H66/F66-1) -> -0.067319129 | K66: 4476.94 | L66: 362005.36 | M66: =IF(H66="",F66*K66,H66*K66) -> 337635.48 | N66: =M66-L66 -> -24369.878 | O66: =IF(F66=0,"Sem qtd. no contrato",IF(ABS(H66/F66-1)<=0.02,"Confere (±2%)",IF(H66>F66,"Projeto maior","Projeto menor"))) -> Projeto menor | P66: Projeto por estaca · área × taxa (premissa) · memória: Tab. 71 item 11.3 | Q66: Tab. 70 indica 0,00045 t/m² (→ 72,78 t), mas a Tab. 71 e o contrato usam 0,50 kg/m² (80,87 t). Painel: área por estaca × 0,50 kg/m² (premissa). | R66: =HYPERLINK("#'Painel'!B114","→ 114") -> → 114
D67: Subtotal – Ligantes Betuminosos | L67: =SUM(L64:L66) -> 7400006.8 | M67: =SUM(M64:M66) -> 6130571.6 | N67: =SUM(N64:N66) -> -1269435.2
B69: Drenagem E Obras Arte Correntes
B70: 71 | C70: 603600 | D70: Alvenaria pedra de mão argamassada | E70: m³ | F70: 137 | H70: =(Painel!$L$253+Painel!$L$233)*1 -> 118.198 | I70: =IF(H70="","",H70-F70) -> -18.802 | J70: =IF(OR(H70="",F70=0),"",H70/F70-1) -> -0.13724088 | K70: 456.92 | L70: 62598.04 | M70: =IF(H70="",F70*K70,H70*K70) -> 54007.03 | N70: =M70-L70 -> -8591.0098 | O70: =IF(F70=0,"Sem qtd. no contrato",IF(ABS(H70/F70-1)<=0.02,"Confere (±2%)",IF(H70>F70,"Projeto maior","Projeto menor"))) -> Projeto menor | P70: Projeto por estaca – grupo repartido na proporção do contrato · pedra das valas e bacias (DR-9) + dissipadores (DR-4) | R70: =HYPERLINK("#'Painel'!B256","→ 256") -> → 256
B71: 72 | C71: 601100 | D71: Apiloamento manual | E71: m³ | F71: 13601 | H71: =Painel!$L$250 -> 13854.12 | I71: =IF(H71="","",H71-F71) -> 253.12 | J71: =IF(OR(H71="",F71=0),"",H71/F71-1) -> 0.018610396 | K71: 60.31 | L71: 820276.31 | M71: =IF(H71="",F71*K71,H71*K71) -> 835541.98 | N71: =M71-L71 -> 15265.667 | O71: =IF(F71=0,"Sem qtd. no contrato",IF(ABS(H71/F71-1)<=0.02,"Confere (±2%)",IF(H71>F71,"Projeto maior","Projeto menor"))) -> Confere (±2%) | P71: Projeto por estaca · bueiros + rede pluvial + valas + bacias | R71: =HYPERLINK("#'Painel'!B250","→ 250") -> → 250
B72: 73 | C72: 620900 | D72: Boca de BDTC 1,50m | E72: un | F72: 2 | H72: =Painel!$L$159 -> 2 | I72: =IF(H72="","",H72-F72) -> 0 | J72: =IF(OR(H72="",F72=0),"",H72/F72-1) -> 0 | K72: 8161.87 | L72: 16323.74 | M72: =IF(H72="",F72*K72,H72*K72) -> 16323.74 | N72: =M72-L72 -> 0 | O72: =IF(F72=0,"Sem qtd. no contrato",IF(ABS(H72/F72-1)<=0.02,"Confere (±2%)",IF(H72>F72,"Projeto maior","Projeto menor"))) -> Confere (±2%) | P72: Projeto por estaca · projeto: 2 bocas por bueiro | R72: =HYPERLINK("#'Painel'!B159","→ 159") -> → 159
B73: 74 | C73: 620100 | D73: Boca de BSTC 0,60m | E73: un | F73: 2 | H73: =Painel!$L$149 -> 2 | I73: =IF(H73="","",H73-F73) -> 0 | J73: =IF(OR(H73="",F73=0),"",H73/F73-1) -> 0 | K73: 1268.62 | L73: 2537.24 | M73: =IF(H73="",F73*K73,H73*K73) -> 2537.24 | N73: =M73-L73 -> 0 | O73: =IF(F73=0,"Sem qtd. no contrato",IF(ABS(H73/F73-1)<=0.02,"Confere (±2%)",IF(H73>F73,"Projeto maior","Projeto menor"))) -> Confere (±2%) | P73: Projeto por estaca · projeto: 2 bocas por bueiro | R73: =HYPERLINK("#'Painel'!B149","→ 149") -> → 149
B74: 75 | C74: 620200 | D74: Boca de BSTC 0,80m | E74: un | F74: 12 | H74: =Painel!$L$151 -> 14 | I74: =IF(H74="","",H74-F74) -> 2 | J74: =IF(OR(H74="",F74=0),"",H74/F74-1) -> 0.16666667 | K74: 1770.39 | L74: 21244.68 | M74: =IF(H74="",F74*K74,H74*K74) -> 24785.46 | N74: =M74-L74 -> 3540.78 | O74: =IF(F74=0,"Sem qtd. no contrato",IF(ABS(H74/F74-1)<=0.02,"Confere (±2%)",IF(H74>F74,"Projeto maior","Projeto menor"))) -> Projeto maior | P74: Projeto por estaca · projeto: 2 bocas por bueiro | R74: =HYPERLINK("#'Painel'!B151","→ 151") -> → 151
B75: 76 | C75: 620300 | D75: Boca de BSTC 1,00m | E75: un | F75: 17 | H75: =Painel!$L$153 -> 24 | I75: =IF(H75="","",H75-F75) -> 7 | J75: =IF(OR(H75="",F75=0),"",H75/F75-1) -> 0.41176471 | K75: 2543.29 | L75: 43235.93 | M75: =IF(H75="",F75*K75,H75*K75) -> 61038.96 | N75: =M75-L75 -> 17803.03 | O75: =IF(F75=0,"Sem qtd. no contrato",IF(ABS(H75/F75-1)<=0.02,"Confere (±2%)",IF(H75>F75,"Projeto maior","Projeto menor"))) -> Projeto maior | P75: Projeto por estaca · projeto: 2 bocas por bueiro | Q75: Projeto estimado em 2 bocas por bueiro (24); contrato 17. | R75: =HYPERLINK("#'Painel'!B153","→ 153") -> → 153
B76: 77 | C76: 620400 | D76: Boca de BSTC 1,20m | E76: un | F76: 7 | H76: =Painel!$L$155 -> 6 | I76: =IF(H76="","",H76-F76) -> -1 | J76: =IF(OR(H76="",F76=0),"",H76/F76-1) -> -0.14285714 | K76: 3289.4 | L76: 23025.8 | M76: =IF(H76="",F76*K76,H76*K76) -> 19736.4 | N76: =M76-L76 -> -3289.4 | O76: =IF(F76=0,"Sem qtd. no contrato",IF(ABS(H76/F76-1)<=0.02,"Confere (±2%)",IF(H76>F76,"Projeto maior","Projeto menor"))) -> Projeto menor | P76: Projeto por estaca · projeto: 2 bocas por bueiro | R76: =HYPERLINK("#'Painel'!B155","→ 155") -> → 155
B77: 78 | C77: 620500 | D77: Boca de BSTC 1,50m | E77: un | F77: 4 | H77: =Painel!$L$157 -> 4 | I77: =IF(H77="","",H77-F77) -> 0 | J77: =IF(OR(H77="",F77=0),"",H77/F77-1) -> 0 | K77: 6019.67 | L77: 24078.68 | M77: =IF(H77="",F77*K77,H77*K77) -> 24078.68 | N77: =M77-L77 -> 0 | O77: =IF(F77=0,"Sem qtd. no contrato",IF(ABS(H77/F77-1)<=0.02,"Confere (±2%)",IF(H77>F77,"Projeto maior","Projeto menor"))) -> Confere (±2%) | P77: Projeto por estaca · projeto: 2 bocas por bueiro | R77: =HYPERLINK("#'Painel'!B157","→ 157") -> → 157
B78: 79 | C78: 621300 | D78: Boca de BTTC 1,50m | E78: un | F78: 1 | H78: =Painel!$L$161 -> 2 | I78: =IF(H78="","",H78-F78) -> 1 | J78: =IF(OR(H78="",F78=0),"",H78/F78-1) -> 1 | K78: 10307.89 | L78: 10307.89 | M78: =IF(H78="",F78*K78,H78*K78) -> 20615.78 | N78: =M78-L78 -> 10307.89 | O78: =IF(F78=0,"Sem qtd. no contrato",IF(ABS(H78/F78-1)<=0.02,"Confere (±2%)",IF(H78>F78,"Projeto maior","Projeto menor"))) -> Projeto maior | P78: Projeto por estaca · projeto: 2 bocas por bueiro | Q78: Projeto estimado em 2 bocas por bueiro (2); contrato 1. | R78: =HYPERLINK("#'Painel'!B161","→ 161") -> → 161
B79: 80 | C79: 622100 | D79: Boca de saída dreno profundo - tipo 2 | E79: un | F79: 58 | H79: =Painel!$L$201 -> 70 | I79: =IF(H79="","",H79-F79) -> 12 | J79: =IF(OR(H79="",F79=0),"",H79/F79-1) -> 0.20689655 | K79: 384.51 | L79: 22301.58 | M79: =IF(H79="",F79*K79,H79*K79) -> 26915.7 | N79: =M79-L79 -> 4614.12 | O79: =IF(F79=0,"Sem qtd. no contrato",IF(ABS(H79/F79-1)<=0.02,"Confere (±2%)",IF(H79>F79,"Projeto maior","Projeto menor"))) -> Projeto maior | P79: Projeto por estaca · nota de serviço DR-9 | Q79: Notas de serviço DR-9: 70 bocas BSD 02; contrato 58. | R79: =HYPERLINK("#'Painel'!B201","→ 201") -> → 201
B80: 81 | C80: 622200 | D80: Boca de saída dreno sub-superficial | E80: un | F80: 12 | I80: =IF(H80="","",H80-F80) | J80: =IF(OR(H80="",F80=0),"",H80/F80-1) | K80: 211.89 | L80: 2542.68 | M80: =IF(H80="",F80*K80,H80*K80) -> 2542.68 | N80: =M80-L80 -> 0 | O80: Não encontrado | P80: Sem quantidade no projeto – contrato distribuído pelo serviço que o comanda · distribuído pelo DSS 02 | R80: =HYPERLINK("#'Painel'!B203","→ 203") -> → 203
B81: 82 | C81: 612000 | D81: Corpo de BDTC 1,50m com berço | E81: m | F81: 25 | H81: =(Painel!$L$158)*1 -> 24.85 | I81: =IF(H81="","",H81-F81) -> -0.15 | J81: =IF(OR(H81="",F81=0),"",H81/F81-1) -> -0.006 | K81: 5569.35 | L81: 139233.75 | M81: =IF(H81="",F81*K81,H81*K81) -> 138398.35 | N81: =M81-L81 -> -835.4025 | O81: =IF(F81=0,"Sem qtd. no contrato",IF(ABS(H81/F81-1)<=0.02,"Confere (±2%)",IF(H81>F81,"Projeto maior","Projeto menor"))) -> Confere (±2%) | P81: Projeto por estaca – grupo repartido na proporção do contrato · BDTC Ø 1,50 do projeto | R81: =HYPERLINK("#'Painel'!B168","→ 168") -> → 168
B82: 83 | C82: 610500 | D82: Corpo de BSTC 0,40m com berço | E82: m | F82: 435 | H82: =(Painel!$L$137)*1 -> 424.24 | I82: =IF(H82="","",H82-F82) -> -10.76 | J82: =IF(OR(H82="",F82=0),"",H82/F82-1) -> -0.024735632 | K82: 270.12 | L82: 117502.2 | M82: =IF(H82="",F82*K82,H82*K82) -> 114595.71 | N82: =M82-L82 -> -2906.4912 | O82: =IF(F82=0,"Sem qtd. no contrato",IF(ABS(H82/F82-1)<=0.02,"Confere (±2%)",IF(H82>F82,"Projeto maior","Projeto menor"))) -> Projeto menor | P82: Projeto por estaca – grupo repartido na proporção do contrato · rede BSTC Ø 0,40 do projeto | R82: =HYPERLINK("#'Painel'!B162","→ 162") -> → 162
B83: 84 | C83: 610700 | D83: Corpo de BSTC 0,60m com berço | E83: m | F83: 223 | H83: =(Painel!$L$148+Painel!$L$138)*1 -> 229.32 | I83: =IF(H83="","",H83-F83) -> 6.32 | J83: =IF(OR(H83="",F83=0),"",H83/F83-1) -> 0.028340807 | K83: 537.86 | L83: 119942.78 | M83: =IF(H83="",F83*K83,H83*K83) -> 123342.06 | N83: =M83-L83 -> 3399.2752 | O83: =IF(F83=0,"Sem qtd. no contrato",IF(ABS(H83/F83-1)<=0.02,"Confere (±2%)",IF(H83>F83,"Projeto maior","Projeto menor"))) -> Projeto maior | P83: Projeto por estaca – grupo repartido na proporção do contrato · BSTC Ø 0,60 + rede BSTC Ø 0,60 do projeto | R83: =HYPERLINK("#'Painel'!B163","→ 163") -> → 163
B84: 85 | C84: 610900 | D84: Corpo de BSTC 0,80m com berço | E84: m | F84: 300 | H84: =(Painel!$L$150+Painel!$L$139)*1 -> 300.23 | I84: =IF(H84="","",H84-F84) -> 0.23 | J84: =IF(OR(H84="",F84=0),"",H84/F84-1) -> 0.00076666667 | K84: 890.42 | L84: 267126 | M84: =IF(H84="",F84*K84,H84*K84) -> 267330.8 | N84: =M84-L84 -> 204.7966 | O84: =IF(F84=0,"Sem qtd. no contrato",IF(ABS(H84/F84-1)<=0.02,"Confere (±2%)",IF(H84>F84,"Projeto maior","Projeto menor"))) -> Confere (±2%) | P84: Projeto por estaca – grupo repartido na proporção do contrato · BSTC Ø 0,80 + rede BSTC Ø 0,80 do projeto | R84: =HYPERLINK("#'Painel'!B164","→ 164") -> → 164
B85: 86 | C85: 611100 | D85: Corpo de BSTC 1,00m com berço | E85: m | F85: 334 | H85: =(Painel!$L$152+Painel!$L$140)*1 -> 331.53 | I85: =IF(H85="","",H85-F85) -> -2.47 | J85: =IF(OR(H85="",F85=0),"",H85/F85-1) -> -0.0073952096 | K85: 1487.9 | L85: 496958.6 | M85: =IF(H85="",F85*K85,H85*K85) -> 493283.49 | N85: =M85-L85 -> -3675.113 | O85: =IF(F85=0,"Sem qtd. no contrato",IF(ABS(H85/F85-1)<=0.02,"Confere (±2%)",IF(H85>F85,"Projeto maior","Projeto menor"))) -> Confere (±2%) | P85: Projeto por estaca – grupo repartido na proporção do contrato · BSTC Ø 1,00 + rede BSTC Ø 1,00 do projeto | R85: =HYPERLINK("#'Painel'!B165","→ 165") -> → 165
B86: 87 | C86: 611300 | D86: Corpo de BSTC 1,20m com berço | E86: m | F86: 228 | H86: =(Painel!$L$154+Painel!$L$141)*1 -> 183.67 | I86: =IF(H86="","",H86-F86) -> -44.33 | J86: =IF(OR(H86="",F86=0),"",H86/F86-1) -> -0.19442982 | K86: 1819 | L86: 414732 | M86: =IF(H86="",F86*K86,H86*K86) -> 334095.73 | N86: =M86-L86 -> -80636.27 | O86: =IF(F86=0,"Sem qtd. no contrato",IF(ABS(H86/F86-1)<=0.02,"Confere (±2%)",IF(H86>F86,"Projeto maior","Projeto menor"))) -> Projeto menor | P86: Projeto por estaca – grupo repartido na proporção do contrato · BSTC Ø 1,20 + rede BSTC Ø 1,20 do projeto | Q86: Notas de serviço: 183,67 m de BSTC Ø 1,20 (bueiros + rede); contrato 228 m. | R86: =HYPERLINK("#'Painel'!B166","→ 166") -> → 166
B87: 88 | C87: 611500 | D87: Corpo de BSTC 1,50m com berço | E87: m | F87: 37 | H87: =(Painel!$L$156)*1 -> 37.25 | I87: =IF(H87="","",H87-F87) -> 0.25 | J87: =IF(OR(H87="",F87=0),"",H87/F87-1) -> 0.0067567568 | K87: 2831.3 | L87: 104758.1 | M87: =IF(H87="",F87*K87,H87*K87) -> 105465.93 | N87: =M87-L87 -> 707.825 | O87: =IF(F87=0,"Sem qtd. no contrato",IF(ABS(H87/F87-1)<=0.02,"Confere (±2%)",IF(H87>F87,"Projeto maior","Projeto menor"))) -> Confere (±2%) | P87: Projeto por estaca – grupo repartido na proporção do contrato · BSTC Ø 1,50 do projeto | R87: =HYPERLINK("#'Painel'!B167","→ 167") -> → 167
B88: 89 | C88: 612400 | D88: Corpo de BTTC 1,50m com berço | E88: m | F88: 19 | H88: =(Painel!$L$160)*1 -> 18.84 | I88: =IF(H88="","",H88-F88) -> -0.16 | J88: =IF(OR(H88="",F88=0),"",H88/F88-1) -> -0.0084210526 | K88: 8396.93 | L88: 159541.67 | M88: =IF(H88="",F88*K88,H88*K88) -> 158198.16 | N88: =M88-L88 -> -1343.5088 | O88: =IF(F88=0,"Sem qtd. no contrato",IF(ABS(H88/F88-1)<=0.02,"Confere (±2%)",IF(H88>F88,"Projeto maior","Projeto menor"))) -> Confere (±2%) | P88: Projeto por estaca – grupo repartido na proporção do contrato · BTTC Ø 1,50 do projeto | R88: =HYPERLINK("#'Painel'!B169","→ 169") -> → 169
B89: 90 | C89: 606600 | D89: Demolição de concreto armado | E89: m³ | F89: 12.08 | H89: =(Painel!$L$177)*1 -> 12.07 | I89: =IF(H89="","",H89-F89) -> -0.01 | J89: =IF(OR(H89="",F89=0),"",H89/F89-1) -> -0.00082781457 | K89: 343.82 | L89: 4153.34 | M89: =IF(H89="",F89*K89,H89*K89) -> 4149.9074 | N89: =M89-L89 -> -3.4326 | O89: =IF(F89=0,"Sem qtd. no contrato",IF(ABS(H89/F89-1)<=0.02,"Confere (±2%)",IF(H89>F89,"Projeto maior","Projeto menor"))) -> Confere (±2%) | P89: Projeto por estaca – grupo repartido na proporção do contrato · memória – remoção de drenagem existente | R89: =HYPERLINK("#'Painel'!B183","→ 183") -> → 183
B90: 91 | C90: 606700 | D90: Demolição de concreto simples | E90: m³ | F90: 5.95 | H90: =(Painel!$L$178)*1 -> 5.95 | I90: =IF(H90="","",H90-F90) -> 0 | J90: =IF(OR(H90="",F90=0),"",H90/F90-1) -> 0 | K90: 164.4 | L90: 978.18 | M90: =IF(H90="",F90*K90,H90*K90) -> 978.18 | N90: =M90-L90 -> 0 | O90: =IF(F90=0,"Sem qtd. no contrato",IF(ABS(H90/F90-1)<=0.02,"Confere (±2%)",IF(H90>F90,"Projeto maior","Projeto menor"))) -> Confere (±2%) | P90: Projeto por estaca – grupo repartido na proporção do contrato · memória – remoção de drenagem existente | R90: =HYPERLINK("#'Painel'!B184","→ 184") -> → 184
B91: 92 | C91: 692450 | D91: Dreno de Talvegue | E91: m | F91: 1076 | I91: =IF(H91="","",H91-F91) | J91: =IF(OR(H91="",F91=0),"",H91/F91-1) | K91: 367.71 | L91: 395655.96 | M91: =IF(H91="",F91*K91,H91*K91) -> 395655.96 | N91: =M91-L91 -> 0 | O91: Não encontrado | P91: Sem quantidade no projeto – contrato rateado pela extensão · sem localização no projeto – rateio por extensão | Q91: Memória (3.4.6) cita drenos de talvegue nos canais 312+6,30–323+5,00 e 568+14,28, sem comprimento nem detalhe. | R91: =HYPERLINK("#'Painel'!B259","→ 259") -> → 259
B92: 93 | C92: 643100 | D92: Dreno profundo em rocha - tipo 2(GNT) | E92: m | F92: 2870 | H92: =Painel!$L$135 -> 2862.27 | I92: =IF(H92="","",H92-F92) -> -7.73 | J92: =IF(OR(H92="",F92=0),"",H92/F92-1) -> -0.0026933798 | K92: 111.66 | L92: 320464.2 | M92: =IF(H92="",F92*K92,H92*K92) -> 319601.07 | N92: =M92-L92 -> -863.1318 | O92: =IF(F92=0,"Sem qtd. no contrato",IF(ABS(H92/F92-1)<=0.02,"Confere (±2%)",IF(H92>F92,"Projeto maior","Projeto menor"))) -> Confere (±2%) | P92: Projeto por estaca · nota de serviço, proporcional ao trecho | R92: =HYPERLINK("#'Painel'!B135","→ 135") -> → 135
B93: 94 | C93: 641800 | D93: Dreno profundo em solo - tipo 6A(GNT) | E93: m | F93: 10410 | H93: =Painel!$L$134 -> 10366.84 | I93: =IF(H93="","",H93-F93) -> -43.16 | J93: =IF(OR(H93="",F93=0),"",H93/F93-1) -> -0.0041460134 | K93: 251.83 | L93: 2621550.3 | M93: =IF(H93="",F93*K93,H93*K93) -> 2610681.3 | N93: =M93-L93 -> -10868.983 | O93: =IF(F93=0,"Sem qtd. no contrato",IF(ABS(H93/F93-1)<=0.02,"Confere (±2%)",IF(H93>F93,"Projeto maior","Projeto menor"))) -> Confere (±2%) | P93: Projeto por estaca · nota de serviço, proporcional ao trecho | R93: =HYPERLINK("#'Painel'!B134","→ 134") -> → 134
B94: 95 | C94: 644200 | D94: Dreno sub-superficial - tipo 2 | E94: m | F94: 1594 | H94: =Painel!$L$200 -> 1593.85 | I94: =IF(H94="","",H94-F94) -> -0.15 | J94: =IF(OR(H94="",F94=0),"",H94/F94-1) -> -9.4102886e-05 | K94: 25.59 | L94: 40790.46 | M94: =IF(H94="",F94*K94,H94*K94) -> 40786.622 | N94: =M94-L94 -> -3.8385 | O94: =IF(F94=0,"Sem qtd. no contrato",IF(ABS(H94/F94-1)<=0.02,"Confere (±2%)",IF(H94>F94,"Projeto maior","Projeto menor"))) -> Confere (±2%) | P94: Projeto por estaca · nota de serviço DR-9 (L) | R94: =HYPERLINK("#'Painel'!B200","→ 200") -> → 200
B95: 96 | C95: 800000 | D95: Enleivamento | E95: m² | F95: 3412 | H95: =Painel!$L$254 -> 897.90014 | I95: =IF(H95="","",H95-F95) -> -2514.0999 | J95: =IF(OR(H95="",F95=0),"",H95/F95-1) -> -0.73684052 | K95: 13.61 | L95: 46437.32 | M95: =IF(H95="",F95*K95,H95*K95) -> 12220.421 | N95: =M95-L95 -> -34216.899 | O95: =IF(F95=0,"Sem qtd. no contrato",IF(ABS(H95/F95-1)<=0.02,"Confere (±2%)",IF(H95>F95,"Projeto maior","Projeto menor"))) -> Projeto menor | P95: Projeto por estaca · valas e bacias de captação | Q95: Valas e bacias de captação (DR-9): 897,90 m²; contrato 3.412 m². | R95: =HYPERLINK("#'Painel'!B254","→ 254") -> → 254
B96: 97 | C96: 600300 | D96: Escavação de bueiros em 1a. cat. | E96: m³ | F96: 11700 | H96: =Painel!$L$249 -> 12943.554 | I96: =IF(H96="","",H96-F96) -> 1243.5537 | J96: =IF(OR(H96="",F96=0),"",H96/F96-1) -> 0.10628664 | K96: 12.84 | L96: 150228 | M96: =IF(H96="",F96*K96,H96*K96) -> 166195.23 | N96: =M96-L96 -> 15967.23 | O96: =IF(F96=0,"Sem qtd. no contrato",IF(ABS(H96/F96-1)<=0.02,"Confere (±2%)",IF(H96>F96,"Projeto maior","Projeto menor"))) -> Projeto maior | P96: Projeto por estaca · bueiros + rede pluvial + valas + bacias | Q96: Bueiros + redes + valas + bacias: 12.943,55 m³ (+10,6%). | R96: =HYPERLINK("#'Painel'!B249","→ 249") -> → 249
B97: 98 | C97: 600500 | D97: Escavação de bueiros em 3a. cat. | E97: m³ | F97: 220.6 | I97: =IF(H97="","",H97-F97) | J97: =IF(OR(H97="",F97=0),"",H97/F97-1) | K97: 136.1 | L97: 30023.66 | M97: =IF(H97="",F97*K97,H97*K97) -> 30023.66 | N97: =M97-L97 -> 0 | O97: Não encontrado | P97: Sem quantidade no projeto – contrato distribuído pelo serviço que o comanda · distribuído pela escavação de bueiros | Q97: Nenhuma escavação de bueiro em 3ª cat. nas notas de serviço. | R97: =HYPERLINK("#'Painel'!B257","→ 257") -> → 257
B98: 99 | C98: 600600 | D98: Escavação valas de drenagem 1a. cat. | E98: m³ | F98: 3919 | H98: =(Painel!$L$146)*1 -> 4268.908 | I98: =IF(H98="","",H98-F98) -> 349.908 | J98: =IF(OR(H98="",F98=0),"",H98/F98-1) -> 0.089285022 | K98: 20.76 | L98: 81358.44 | M98: =IF(H98="",F98*K98,H98*K98) -> 88622.53 | N98: =M98-L98 -> 7264.0901 | O98: =IF(F98=0,"Sem qtd. no contrato",IF(ABS(H98/F98-1)<=0.02,"Confere (±2%)",IF(H98>F98,"Projeto maior","Projeto menor"))) -> Projeto maior | P98: Projeto por estaca – grupo repartido na proporção do contrato · escavação das valetas VPA/VPC (DR-4-0001/0002) | R98: =HYPERLINK("#'Painel'!B258","→ 258") -> → 258
B99: 100 | C99: 602200 | D99: Escoramento de cavas de fundação | E99: m² | F99: 1808 | H99: =Painel!$L$252 -> 587.77 | I99: =IF(H99="","",H99-F99) -> -1220.23 | J99: =IF(OR(H99="",F99=0),"",H99/F99-1) -> -0.67490597 | K99: 122.5 | L99: 221480 | M99: =IF(H99="",F99*K99,H99*K99) -> 72001.825 | N99: =M99-L99 -> -149478.17 | O99: =IF(F99=0,"Sem qtd. no contrato",IF(ABS(H99/F99-1)<=0.02,"Confere (±2%)",IF(H99>F99,"Projeto maior","Projeto menor"))) -> Projeto menor | P99: Projeto por estaca · bueiros + rede pluvial + valas + bacias | Q99: Escoramento das notas de serviço: 587,77 m²; contrato 1.808 m² (−67,5%). | R99: =HYPERLINK("#'Painel'!B252","→ 252") -> → 252
B100: 101 | C100: 791195 | D100: Fornecimento e colocação de meia cana de concreto 0,30m | E100: m | F100: 125 | I100: =IF(H100="","",H100-F100) | J100: =IF(OR(H100="",F100=0),"",H100/F100-1) | K100: 71.2 | L100: 8900 | M100: =IF(H100="",F100*K100,H100*K100) -> 8900 | N100: =M100-L100 -> 0 | O100: Não encontrado | P100: Sem quantidade no projeto – contrato rateado pela extensão · sem localização no projeto – rateio por extensão | Q100: Memória remete a meia-cana ao projeto de contenções; o CO-2 não a quantifica. | R100: =HYPERLINK("#'Painel'!B260","→ 260") -> → 260
B101: 102 | C101: 860200 | D101: Gabião tipo caixa 2x1x0,50m ZN/AL + PVC (NBR 8964) | E101: m³ | F101: 11 | I101: =IF(H101="","",H101-F101) | J101: =IF(OR(H101="",F101=0),"",H101/F101-1) | K101: 1017.57 | L101: 11193.27 | M101: =IF(H101="",F101*K101,H101*K101) -> 11193.27 | N101: =M101-L101 -> 0 | O101: Não encontrado | P101: Sem quantidade no projeto – contrato rateado pela extensão · sem localização no projeto – rateio por extensão | Q101: Gabião 0,50 m do grupo Drenagem: sem localização nem quantidade no projeto (o dos canais está no grupo Dispositivos). | R101: =HYPERLINK("#'Painel'!B261","→ 261") -> → 261
B102: 103 | C102: 603900 | D102: Lastro de brita | E102: m³ | F102: 385 | H102: =(Painel!$L$170)*1 -> 291.73274 | I102: =IF(H102="","",H102-F102) -> -93.26726 | J102: =IF(OR(H102="",F102=0),"",H102/F102-1) -> -0.24225262 | K102: 195.31 | L102: 75194.35 | M102: =IF(H102="",F102*K102,H102*K102) -> 56978.321 | N102: =M102-L102 -> -18216.029 | O102: =IF(F102=0,"Sem qtd. no contrato",IF(ABS(H102/F102-1)<=0.02,"Confere (±2%)",IF(H102>F102,"Projeto maior","Projeto menor"))) -> Projeto menor | P102: Projeto por estaca – grupo repartido na proporção do contrato · lastro de brita dos detalhes de assentamento DR-4-0036/0037 | Q102: Lastro dos detalhes de assentamento DR-4-0036/0037: 291,73 m³ (−24%). | R102: =HYPERLINK("#'Painel'!B171","→ 171") -> → 171
B103: 104 | C103: 810200 | D103: Meio fio de concreto tipo 2 (executado c/ extrusora) | E103: m | F103: 1860.5 | H103: =Painel!$L$125 -> 1751.5 | I103: =IF(H103="","",H103-F103) -> -109 | J103: =IF(OR(H103="",F103=0),"",H103/F103-1) -> -0.058586402 | K103: 44.4 | L103: 82606.2 | M103: =IF(H103="",F103*K103,H103*K103) -> 77766.6 | N103: =M103-L103 -> -4839.6 | O103: =IF(F103=0,"Sem qtd. no contrato",IF(ABS(H103/F103-1)<=0.02,"Confere (±2%)",IF(H103>F103,"Projeto maior","Projeto menor"))) -> Projeto menor | P103: Projeto por estaca · nota de serviço, proporcional ao trecho | R103: =HYPERLINK("#'Painel'!B125","→ 125") -> → 125
B104: 105 | C104: 810700 | D104: Meio fio de concreto tipo 7 (executado c/ extrusora) | E104: m | F104: 130 | H104: =Painel!$L$126 -> 130 | I104: =IF(H104="","",H104-F104) -> 0 | J104: =IF(OR(H104="",F104=0),"",H104/F104-1) -> 0 | K104: 35.68 | L104: 4638.4 | M104: =IF(H104="",F104*K104,H104*K104) -> 4638.4 | N104: =M104-L104 -> 0 | O104: =IF(F104=0,"Sem qtd. no contrato",IF(ABS(H104/F104-1)<=0.02,"Confere (±2%)",IF(H104>F104,"Projeto maior","Projeto menor"))) -> Confere (±2%) | P104: Projeto por estaca · nota de serviço, proporcional ao trecho | R104: =HYPERLINK("#'Painel'!B126","→ 126") -> → 126
B105: 106 | C105: 601200 | D105: Reaterro e apiloamento mecânico | E105: m³ | F105: 1425 | H105: =Painel!$L$251 -> 1057.03 | I105: =IF(H105="","",H105-F105) -> -367.97 | J105: =IF(OR(H105="",F105=0),"",H105/F105-1) -> -0.25822456 | K105: 38.19 | L105: 54420.75 | M105: =IF(H105="",F105*K105,H105*K105) -> 40367.976 | N105: =M105-L105 -> -14052.774 | O105: =IF(F105=0,"Sem qtd. no contrato",IF(ABS(H105/F105-1)<=0.02,"Confere (±2%)",IF(H105>F105,"Projeto maior","Projeto menor"))) -> Projeto menor | P105: Projeto por estaca · bueiros + rede pluvial + valas + bacias | R105: =HYPERLINK("#'Painel'!B251","→ 251") -> → 251
B106: 107 | C106: 630400 | D106: Remoção de bueiro 0,40m | E106: m | F106: 343 | H106: =(Painel!$L$173)*1 -> 343 | I106: =IF(H106="","",H106-F106) -> 0 | J106: =IF(OR(H106="",F106=0),"",H106/F106-1) -> 0 | K106: 22.17 | L106: 7604.31 | M106: =IF(H106="",F106*K106,H106*K106) -> 7604.31 | N106: =M106-L106 -> 0 | O106: =IF(F106=0,"Sem qtd. no contrato",IF(ABS(H106/F106-1)<=0.02,"Confere (±2%)",IF(H106>F106,"Projeto maior","Projeto menor"))) -> Confere (±2%) | P106: Projeto por estaca – grupo repartido na proporção do contrato · memória – remoção de drenagem existente | R106: =HYPERLINK("#'Painel'!B179","→ 179") -> → 179
...

Sheet Discrepâncias
B2: DISCREPÂNCIAS ENCONTRADAS NA ANÁLISE DA PLANILHA, DO CONTRATO E DOS PROJETOS – PR-990
B3: Valores a preço do contrato, trecho inteiro. Colunas de contrato, memória e projeto em unidades do serviço; impacto (R$) = consumo real − contrato, vindo da aba Contrato × Projeto (atualiza com as premissas).
B5: 1 · CONTRATO × PROJETO – PRINCIPAIS DIVERGÊNCIAS DE QUANTIDADE
B6: # | C6: Disciplina | D6: Código / item | E6: Serviço | F6: Contrato | G6: Memória (quadro) | H6: Consumo real | I6: Impacto (R$) | J6: Descrição da discrepância | K6: Tratamento no painel / ação sugerida
B7: 1 | C7: Ligantes | D7: 589000 | E7: CAP 50/70 (t) | F7: ='Contrato × Projeto'!F64 -> 1068.62 | G7: 1068.64 | H7: ='Contrato × Projeto'!H64 -> 857.69152 | I7: ='Contrato × Projeto'!N64 -> -1170178.5 | J7: Teor de CAP: contrato e memória a 5,7%; o executado é 4,8%. Somado ao CBUQ apurado por estaca (−4,7%), o CAP cai 19,7%. | K7: Painel usa a premissa editável H6 (teor executado). Ajustar o 589000 por apostilamento/aditivo de quantidades.
B8: 2 | C8: Drenagem – dispositivos | D8: 605300 · 602000 · 603000 · 603300 | E8: Concreto, formas e aço dos dispositivos | F8: vários | H8: vários | I8: ='Contrato × Projeto'!N127+'Contrato × Projeto'!N133+'Contrato × Projeto'!N123+'Contrato × Projeto'!N124+'Contrato × Projeto'!N126+'Contrato × Projeto'!N129 -> -841134.96 | J8: Pelos consumos unitários dos detalhes DR-4 × quantidades das notas de serviço, o concreto fck 15 é 15% do contrato (139,48 × 920,67 m³), as formas 40% e o CA-60 25%; o CA-50 é 2,3×. A proporção CA-50/CA-60 do contrato é a inversa da dos detalhes. | K8: Painel valora pelos consumos dos detalhes. Pedir à projetista a memória dos insumos dos dispositivos.
B9: 3 | C9: Obras complementares | D9: 831000 | E9: Cerca de 4 fios | F9: ='Contrato × Projeto'!F231 -> 15906.82 | G9: 27243.64 | H9: ='Contrato × Projeto'!H231 -> 27243.64 | I9: ='Contrato × Projeto'!N231 -> 488730.31 | J9: A Tab. 78 e a tabela por estaca da memória somam 27.243,64 m; o contrato tem 15.906,82 m (+11.336,82 m). | K9: Painel usa a memória por estaca. Rever o quantitativo contratual (provável omissão de um lado ou de trechos).
B10: 4 | C10: Drenagem | D10: 653400 | E10: Sarjeta trapezoidal tipo 3 + STB 01 | F10: ='Contrato × Projeto'!F110 -> 109 | H10: ='Contrato × Projeto'!H110 -> 1767 | I10: ='Contrato × Projeto'!N110 -> 204199.28 | J10: Contrato 109 m (só SZC 03). A sarjeta de borda de aterro STB 01 (1.659 m nas notas de serviço) não tem item próprio e é medida no 653400. | K10: Painel soma SZC 03 + STB 01 no 653400. Criar item para a STB 01 ou formalizar a equivalência de preço.
B11: 5 | C11: Pavimentação | D11: 530200 · 531100 · 570400 | E11: Bica corrida, BGS e CBUQ | F11: vários | H11: vários | I11: ='Contrato × Projeto'!N50+'Contrato × Projeto'!N51+'Contrato × Projeto'!N52 -> -916652.93 | J11: O contrato segue a Tab. 71 da memória; o cálculo por estaca (larguras medidas × espessuras PV-2) dá −2,2% (bica), −5,5% (BGS) e −4,7% (CBUQ). | K11: Painel usa o cálculo por estaca. Conferir as larguras dos trechos de interseção e acessos.
B12: 6 | C12: Terraplenagem | D12: 430610 · 401100 · 403000 | E12: Parcela de 1.412,35 m³ repetida | F12: vários | H12: vários | I12: ='Contrato × Projeto'!N38+'Contrato × Projeto'!N16+'Contrato × Projeto'!N17 -> -7212.6747 | J12: 1.412,35 m³ (preenchimento de rebaixo com material de 3ª, quadro 1.1.33) aparecem no contrato três vezes: como transporte 3ª cat. 400–600 m (faixa que não existe no quadro), somados à compactação 100% PN (102.477,69 × 101.065,34) e à compactação em 3ª cat. (18.294,23 × 16.881,88). | K12: Painel usa o corte por estaca e o quadro. Excluir a duplicidade no contrato.
B13: 7 | C13: Terraplenagem | D13: 430410 a 434010 | E13: Transporte de 3ª categoria | F13: ='Contrato × Projeto'!F37+'Contrato × Projeto'!F38+'Contrato × Projeto'!F39+'Contrato × Projeto'!F40+'Contrato × Projeto'!F41+'Contrato × Projeto'!F42 -> 14398.41 | H13: =N('Contrato × Projeto'!H37)+N('Contrato × Projeto'!H38)+N('Contrato × Projeto'!H39)+N('Contrato × Projeto'!H40)+N('Contrato × Projeto'!H41)+N('Contrato × Projeto'!H42) -> 17477.512 | I13: ='Contrato × Projeto'!N37+'Contrato × Projeto'!N38+'Contrato × Projeto'!N39+'Contrato × Projeto'!N40+'Contrato × Projeto'!N41+'Contrato × Projeto'!N42 -> 176493.05 | J13: Corte em 3ª cat. por estaca (REV04): 17.477,51 m³; faixas do contrato: 14.398,41 m³ (+21,4%). O quadro soma 12.986,06 m³. | K13: Painel reparte o corte de 3ª por estaca na proporção das faixas do contrato.
B14: 8 | C14: Terraplenagem | D14: 495161 | E14: Fundação de aterro com rachão | F14: ='Contrato × Projeto'!F46 -> 28703.95 | G14: 27235.29 | H14: ='Contrato × Projeto'!H46 -> 27235.294 | I14: ='Contrato × Projeto'!N46 -> -249319.04 | J14: Quadro: 25.822,95 + 1.412,35 = 27.235,29 m³ (igual ao apurado por estaca); contrato 28.703,95 (+1.468,66). | K14: Painel usa a REV04.
B15: 9 | C15: Paisagismo | D15: 800000 · 800100 | E15: Enleivamento e hidrossemeadura | F15: vários | H15: vários | I15: ='Contrato × Projeto'!N266+'Contrato × Projeto'!N268 -> -321625.9 | J15: Tab. 76: enleivamento 111.056,76 m² (com canteiro e DME) e hidrossemeadura 39.601,86 m²; contrato 128.450 e 47.522 m². A Tab. 76 tem adubação de cobertura (38.927,59 m²) sem item no contrato. | K15: Painel usa a memória por estaca.
B16: 10 | C16: Drenagem – canais | D16: 860200 · 860023 · 860150 | E16: Gabiões e colchão dos canais | F16: vários | H16: vários | I16: ='Contrato × Projeto'!N138+'Contrato × Projeto'!N139+'Contrato × Projeto'!N140 -> -403879.97 | J16: Canais DR-5 (seção tipo × extensão): gabião h 0,50 166,5 m³ (contrato 360,5), colchão 6.266 m² (6.854), gabião h 1,00 863 m³ (902). | K16: Painel usa as pranchas DR-5.
B17: 11 | C17: Drenagem | D17: 602200 · 800000 · 696420 | E17: Escoramento, enleivamento de valas e PEAD | F17: vários | H17: vários | I17: ='Contrato × Projeto'!N99+'Contrato × Projeto'!N95+'Contrato × Projeto'!N135 -> -202338.63 | J17: Notas de serviço: escoramento 587,77 m² (contrato 1.808), enleivamento das valas 897,90 m² (3.412), PEAD das bacias 57 m (1.539). | K17: Painel usa as notas de serviço.
B18: 12 | C18: Drenagem | D18: 607000 · 690051 | E18: Manta e brita dos drenos sub-superficiais | F18: vários | H18: vários | I18: ='Contrato × Projeto'!N136+'Contrato × Projeto'!N137 -> 95829.446 | J18: DSS 02/04 × detalhe DR-4-0016 (2,15 m²/m e 0,16 m³/m): 6.545,29 m² e 487,09 m³ – o dobro do contrato. O DSS 04 (1.450,47 m) não tem item próprio. | K18: Painel valora pelo detalhe. Confirmar se o contrato considerou só o DSS 02.
B19: 13 | C19: Galerias | D19: 730000 · 792140 · 711000 | E19: Insumos das galerias celulares | F19: vários | H19: vários | I19: ='Contrato × Projeto'!N196+'Contrato × Projeto'!N197+'Contrato × Projeto'!N202+'Contrato × Projeto'!N199+'Contrato × Projeto'!N200+'Contrato × Projeto'!N201 -> -190780.66 | J19: Tabelas DNIT/DER-PR (DR-4-0039 a 0056) dão aço −8,1%, concreto −14,2%, formas −10,1%; o escoramento (só a seção 3,00 × 4,00 traz) é +17,8%. | K19: Painel usa as tabelas das galerias.
B20: 14 | C20: Drenagem | D20: 691104 · 622100 · 611300 | E20: PV, bocas de dreno e BSTC Ø 1,20 | F20: vários | H20: vários | I20: ='Contrato × Projeto'!N134+'Contrato × Projeto'!N79+'Contrato × Projeto'!N86 -> -92915.91 | J20: Notas de serviço: 5 PV 2 (contrato 36), 70 bocas BSD 02 (58), 183,67 m de BSTC Ø 1,20 (228). | K20: Painel usa as notas de serviço DR-9.
B21: 15 | C21: Interferências | D21: 308 a 312 | E21: Remanejamento da rede de água (DN 75) | F21: vários | H21: vários | I21: ='Contrato × Projeto'!N348+'Contrato × Projeto'!N349+'Contrato × Projeto'!N350+'Contrato × Projeto'!N351+'Contrato × Projeto'!N352 -> 1665474.6 | J21: O projeto de interferências (IT-2-0001) tem 4.808 m de tubulação Ø 85 mm (PVC DN 75) a remanejar, de 229+1 a 465+14 LE; o contrato prevê 1.150 m. Enleivamento, escavação, lastro e reaterro foram levados na mesma proporção (consumo por metro do contrato). | K21: Painel usa a extensão do projeto. Confirmar com a SANEPAR a extensão real e a seção de vala – os consumos do contrato (6 m³/m de escavação) parecem altos para DN 75.
B22: 16 | C22: Sinalização | D22: 823000 | E22: Defensa metálica | F22: ='Contrato × Projeto'!F272 -> 5039 | G22: 5039 | H22: ='Contrato × Projeto'!H272 -> 4947 | I22: ='Contrato × Projeto'!N272 -> -49774.76 | J22: Tab. 74: 4.735 + 304 (terminal abatido) = 5.039 m = contrato. A tabela por estaca da memória soma 4.947 m, com linhas incoerentes (370 m em 52 m de estaca; 92 m em 315 m). | K22: Painel usa a tabela por estaca (4.947 m). Pedir a correção da tabela.
B23: 17 | C23: Contenções | D23: 607000 | E23: Geotêxtil dos muros (CO-2) | F23: ='Contrato × Projeto'!F190 -> 1380 | G23: 1215 | H23: ='Contrato × Projeto'!H190 -> 1215 | I23: ='Contrato × Projeto'!N190 -> -1671.45 | J23: O quadro de materiais do CO-2 imprime 1.380 m², mas as parcelas somam 475 + 740 = 1.215 m² (erro de soma levado ao contrato). | K23: Painel usa 1.215 m².
H24: Soma | I24: =SUM(I7:I23) -> -1816758.7 | J24: ="Diferença total real − contrato (todos os itens): R$ "&FIXED('Contrato × Projeto'!N359,2) -> Diferença total real − contrato (todos os itens): R$ -1,986,016.05
B26: 2 · SERVIÇOS QUANTIFICADOS NO PROJETO SEM ITEM NA PLANILHA CONTRATUAL
B27: # | C27: Disciplina | D27: Fonte | E27: Serviço | F27: Un | G27: — | H27: Qtd. projeto | I27: Estimativa (R$) | J27: Observação | K27: Preço de referência usado na estimativa
B28: 1 | C28: Drenagem | D28: DR-9 (notas de serviço) | E28: Sarjeta triangular de concreto STC 05 | F28: m | H28: =Painel!$L$120 -> 1928 | I28: =H28*176.99 -> 341236.72 | J28: 1.928 m nas notas de serviço; nenhum item de sarjeta STC 05 no contrato. | K28: 650000 – sarjeta triangular tipo 1 (similar) · R$ 176,99
B29: 2 | C29: Drenagem | D29: DR-9 (notas de serviço) | E29: Sarjeta triangular de concreto STC 11 | F29: m | H29: =Painel!$L$121 -> 1273 | I29: =H29*176.99 -> 225308.27 | J29: 1.273 m nas notas de serviço; nenhum item de sarjeta STC 11 no contrato. | K29: 650000 – sarjeta triangular tipo 1 (similar) · R$ 176,99
B30: 3 | C30: Drenagem | D30: DR-9 / DR-4-0016 | E30: Dreno sub-superficial DSS 04 | F30: m | H30: =Painel!$L$136 -> 1450.47 | I30: =H30*25.59 -> 37117.527 | J30: O contrato tem só o 644200 (DSS 02, 1.594 m); o DSS 04 não tem item. | K30: 644200 – dreno sub-superficial tipo 2 (similar) · R$ 25,59
B31: 4 | C31: Drenagem – canais | D31: DR-5-0002 a 0011 | E31: Lastro de rachão e = 0,40 m dos canais | F31: m³ | H31: =Painel!$L$190 -> 2752.8 | I31: =H31*169.76 -> 467315.33 | J31: Sem item de rachão no grupo Dispositivos. | K31: 495161 – fundação de aterro com rachão (similar) · R$ 169,76
B32: 5 | C32: Drenagem – canais | D32: DR-5-0002 a 0011 | E32: Geotêxtil MacTex dos canais | F32: m² | H32: =Painel!$L$191 -> 7654 | I32: =H32*10.13 -> 77535.02 | J32: Se o 607000 do grupo Dispositivos for só dos drenos (6.545 m² no projeto), o geotêxtil dos canais fica sem item. | K32: 607000 – geotêxtil não tecido · R$ 10,13
B33: 6 | C33: Sinalização | D33: Tab. 74 / SI-1-0016 | E33: Barreira New Jersey simples (813000) | F33: m | H33: 64 | I33: – | J33: Quantificada na memória; o contrato só tem os refletivos de barreira (801926). | K33: sem preço no contrato
B34: 7 | C34: Paisagismo | D34: Tab. 76 | E34: Adubação de cobertura (hidrossemeadura + enleivamento) | F34: m² | H34: 38927.59 | I34: – | J34: 11.880,56 m² (hidrossemeadura) + 27.047,03 m² (enleivamento). | K34: sem preço no contrato
B35: 8 | C35: Obras complementares | D35: Tab. 78 item 22 | E35: Travessia elevada para pedestres | F35: un | H35: 1 | I35: – | J35: Contrato só tem o piso tátil das travessias (834907, 10 m²). | K35: sem preço no contrato
B36: 9 | C36: Contenções | D36: CO-2 (revisão Terramesh) | E36: Rachão para preparação da base dos muros | F36: m³ | H36: =Painel!$L$344 -> 430.5 | I36: =H36*169.76 -> 73081.68 | J36: Quadro de materiais do CO-2: 430,50 m³. | K36: 495161 – fundação de aterro com rachão (similar) · R$ 169,76
H37: Soma | I37: =SUM(I28:I36) -> 1221594.5 | J37: Estimativa só para dimensionar o impacto (preço de item similar do contrato); não entra no total do painel.
B39: 3 · INCONSISTÊNCIAS INTERNAS DAS MEMÓRIAS E PRANCHAS
B40: # | C40: Disciplina | D40: Documento | E40: Assunto | F40: — | G40: — | H40: — | I40: — | J40: Descrição | K40: Efeito no painel
B41: 1 | C41: Terraplenagem | D41: Tomo II – quadro 1.2.2 | E41: Tela de proteção de talude | J41: Linha geral 2.409,47 kg e coluna total 2.928,56 kg no mesmo item; a planilha de distribuição usa 2.928,555 kg. O contrato adotou 2.409,47. | K41: Painel usa 2.409,47 (= contrato).
B42: 2 | C42: Pavimentação | D42: Tomo II – Tab. 70 × Tab. 71 | E42: Taxas de ligantes | J42: Tab. 70 indica RR-1C 0,00045 t/m² (→ 72,78 t), mas a Tab. 71 usa 0,50 kg/m² (80,87 t). A EAI vem em l/m² na Tab. 70 e em kg/m² na Tab. 71. | K42: Taxas são premissas editáveis (H7, H8).
B43: 3 | C43: Pavimentação | D43: Tomo II – Tab. 71 × contrato | E43: Imprimação | J43: Imprimação 161.734 m² na memória e 161.756 m² no contrato (+22 m²); a pintura de ligação, de mesma área, ficou 161.734. | K43: —
B44: 4 | C44: Contenções | D44: CO-2 – quadro resumo | E44: Geotêxtil | J44: Total impresso 1.380 m²; parcelas 740 + 475 = 1.215 m². | K44: Painel usa 1.215 m².
B45: 5 | C45: Sinalização | D45: Tomo III – defensas por estaca | E45: Defensa metálica | J45: Soma das linhas 4.947 m × total 5.039 m da Tab. 74; linhas com extensão incompatível com as estacas (268+14,70 a 271+6,70: 370 m em 52 m; 309+15 a 325+10: 92 m em 315 m; 168+8 a 169+18: 8 m em 30 m). | K45: Painel distribui pela tabela por estaca.
B46: 6 | C46: Sinalização | D46: Tomo III – sinalização horizontal | E46: Legendas repetidas | J46: Linhas idênticas de PINTURA DE LEGENDA (7,5 m²) nas estacas 323 e 324 (LD) e 329+6 (LE) – possível duplicidade (22,5 m²). | K46: Entram como estão (diferença de 0,6% no 822330).
B47: 7 | C47: Sinalização | D47: Tomo III – placas | E47: Placas repetidas | J47: R-2 e R-33 lançadas duas vezes na estaca 326 LD (rotatória) – podem ser aproximações diferentes. | K47: Entram como estão.
B48: 8 | C48: Sinalização | D48: Tab. 74 × contrato | E48: Unidades | J48: Remoção de placas em un na memória e em m² no contrato; remoção de pórtico 2,68 un no contrato (memória: 1 pórtico + 1 semi-pórtico). | K48: —
B49: 9 | C49: Obras complementares | D49: Tomo III – cercas | E49: Remoção de cerca repetida | J49: Linha REMOÇÃO DE CERCA 599+8,90 a 599+8,90 LD (9,39 m) aparece duas vezes. | K49: Diferença de 9,39 m.
B50: 10 | C50: Obras complementares | D50: Tab. 78 × contrato | E50: Piso podotátil | J50: Memória em metros (83 m); contrato em m² (13,28 + 15,68 + 10). | K50: Painel distribui o contrato pelo piso da memória.
B51: 11 | C51: Drenagem | D51: DR-9 – notas de serviço | E51: Extensão L × estacas | J51: 66 dispositivos lineares com L da nota de serviço diferente (> 10%) da distância entre as estacas de início e fim – a maioria na interseção (Est. 316 a 340) e em sarjetas de concordância. Ex.: STC 01 LD 1+7,43 a 3+10,12 com L = 220 m em 42,7 m de estaca. | K51: Painel usa o L da nota de serviço, distribuído entre as estacas de início e fim.
B52: 12 | C52: Terraplenagem | D52: Quadro × contrato | E52: Camada de fechamento | J52: O contrato (575000) usa 2.514,01 m³, que no quadro é a compactação c/ controle visual (401200); o material para camada de fechamento (NCT-002) é 3.519,61 m³. | K52: Painel usa 2.514,01 (aba COBRIM. SAIA).
B54: 4 · VERIFICAÇÕES DA PLANILHA (CONSISTÊNCIA INTERNA)
B55: # | C55: Verificação | D55: — | E55: — | F55: — | G55: — | H55: Resultado | I55: Status | J55: Como foi verificado | K55: —
B56: 1 | C56: Erros de fórmula no Painel | H56: =SUMPRODUCT(--ISERROR(Painel!B1:R497)) -> 0 | I56: =IF(H56=0,"OK","ERRO") -> OK | J56: Contagem de células com erro (fórmula viva).
B57: 2 | C57: Erros de fórmula na aba Contrato × Projeto | H57: =SUMPRODUCT(--ISERROR('Contrato × Projeto'!F12:N358)) -> 0 | I57: =IF(H57=0,"OK","ERRO") -> OK | J57: Contagem de células com erro (fórmula viva).
B58: 3 | C58: Soma da planilha contratual (269 itens) | H58: ='Contrato × Projeto'!L359 -> 87300000 | I58: =IF(ABS(H58-87300000.04)<0.05,"OK","ERRO") -> OK | J58: Deve ser R$ 87.300.000,04 (medição ago/2026).
B59: 4 | C59: Itens do contrato sem linha no Painel | H59: 0 | I59: =IF(H59=0,"OK","ERRO") -> OK | J59: Verificado na geração (todas as 269 linhas da medição têm linha no Painel).
B60: 5 | C60: Consumo real (aba) = Painel no trecho inteiro | H60: ='Contrato × Projeto'!M359 -> 85313984 | I60: ="OK – conferido na geração" -> OK – conferido na geração | J60: Com o Painel em 0+0 a 642+15,817, o total do Painel (coluna J) é igual a este valor.
B61: 6 | C61: Aditividade dos trechos | H61: 0–300 + 300–642 = total | I61: ="OK" -> OK | J61: Verificado na geração: a soma de dois trechos consecutivos é igual ao trecho inteiro (exceto melhorias ambientais, que só entram com o trecho completo, e mobilização, que entra com a estaca final).
B62: 7 | C62: Linhas de origem fora do trecho / extensão zero / estaca vazia | H62: 0 | I62: ="OK" -> OK | J62: Varredura das 12 abas por intervalo e 6 abas pontuais: nenhum intervalo invertido, vazio ou fora de 0 a 642+15,817.
B63: 8 | C63: Linhas repetidas nas abas de origem | H63: 7 linhas | I63: ="ATENÇÃO" -> ATENÇÃO | J63: Legendas (3), placas na rotatória (2), remoção de cerca (1) – ver seção 3. Na OAE, códigos repetidos são itens distintos (infra × superestrutura).

Sheet Leia-me
A1: Base de volumes de pavimentação – PR-990, Est. 0+0,00 a 642+15,817
A2: Fontes: plantas de pavimentação PV-1-0001 a 0009 (larguras medidas por estaca) e seções tipo PV-2-0001 e 0002 (camadas, espessuras, alargamentos e segmentos).
A4: Como a base funciona
A5: 1) Aba "Estacas": largura W do CBUQ acabado em cada estaca (20 m) e nos limites de segmento. Em zona urbana o passeio foi separado de W. As áreas de cada camada são calculadas por fórmula a partir de W e dos parâmetros.
A6: 2) Aba "Parâmetros": espessura, alargamento do topo e talude de cada camada, tirados do Detalhe "A" das seções tipo. Cada camada fica mais larga que a de cima: CBUQ com borda a 45°, BGS começando 10 cm além do bordo do CBUQ, sub-base 10 cm além do pé da BGS, reforço 10 cm além do pé da sub-base.
A7: Larguras resultantes para W = 11,00 m: CBUQ 11,00 (topo) / 11,10 (base); BGS 11,20 / 11,52; sub-base 11,72 / 12,12; reforço 12,32 / 12,92.
A8: 3) Aba "Volumes por intervalo": volume entre cada par de estacas consecutivas pelo método das áreas médias. Cada intervalo recebe o segmento/seção tipo do seu ponto médio.
A9: 4) Aba "Resumo por segmento": soma por segmento de seção tipo (SUMIFS) e total geral.
A11: Ajustes feitos na largura medida
A12: • Bocas de acesso: linhas do pavimento do acesso captadas na seção foram descartadas (o acesso tem estrutura própria – 15 cm de BGS + EAI, nota 1 das pranchas – e não entra nesta base).
A13: • Estacas onde a borda de um acesso corta a seção junto ao eixo, ou com pico isolado na boca do acesso: largura interpolada entre as estacas vizinhas (coluna "Origem da largura").
A14: • Interseção 01 (Barra dos Andrades): largura limitada a 18,40 m (seção tipo 02); o pavimento da via transversal fica fora.
... A72: • Linhas em itálico cinza são quantidades de projeto rateadas (o projeto só dá o total). Bocas de bueiro do projeto estimadas em 2 por bueiro. Linhas com quantidade zero ficam esmaecidas.

Sheet Parâmetros
A1: PARÂMETROS DAS CAMADAS – Seções tipo DE-E-PR-990-000-012-2-PV-2-0001/0002 (Detalhe "A")
A3: Item | B3: Camada / serviço | C3: Espessura (m) | D3: Alargamento do topo da camada, por lado, além do bordo do CBUQ acabado (m) | E3: Talude da borda (H:V) | F3: Unidade de medição | G3: Especificação | H3: Fonte / observação
A4: C1 | B4: CBUQ Faixa C – asfalto convencional | C4: 0.05 | D4: 0 | E4: 1 | F4: m³ | G4: DER-ES-TE-21-23 | H4: Topo = largura acabada medida na planta; borda a 45° (Detalhe A: 5 cm)
A5: C2 | B5: Base – BGS 100% PM | C5: 0.16 | D5: 0.1 | E5: 1 | F5: m³ | G5: DER-ES-TE-05-23 | H5: Detalhe A: 5+5 cm além do bordo do CBUQ no topo; borda 1:1 (16 cm)
A6: C3 | B6: Sub-base – bica corrida | C6: 0.2 | D6: 0.36 | E6: 1 | F6: m³ | G6: DER-ES-TE-06-23 | H6: Detalhe A: topo 10 cm além do pé da BGS (0,10+0,16+0,10); borda 1:1 (20 cm)
A7: C4 | B7: Reforço do subleito – bica corrida (2 x 15 cm) | C7: 0.3 | D7: 0.66 | E7: 1 | F7: m³ | G7: DER-ES-TE-06-23 | H7: Detalhe A: topo 10 cm além do pé da sub-base (0,36+0,20+0,10); borda 1:1 (30 cm)
A8: C5 | B8: Imprimação asfáltica – EAI | D8: 0.1 | F8: m² | G8: DER-ES-TE-17-23 | H8: Aplicada no topo da BGS (largura = CBUQ + 2 x 0,10)
A9: C6 | B9: Pintura de ligação – RR-1C | D9: 0.1 | F9: m² | G9: DER-ES-TE-17-23 | H9: Representada na seção sobre a imprimação, mesma largura (CBUQ + 2 x 0,10)
A10: C7 | B10: Regularização e compactação do subleito 100% PN | D10: 0.96 | F10: m² | G10: DER-ES-TE-01-23 | H10: Largura do pé do reforço (0,66 + 0,30 por lado)
A11: C8 | B11: Bloco de concreto (paver) – passeio | C11: 0.06 | D11: 0 | F11: m³ | G11: ABNT NBR 9050/2023 | H11: Só seções urbanas (T07, T08, T09); largura do passeio medida na planta
A12: C9 | B12: Colchão de pó de pedra – passeio | C12: 0.05 | D12: 0 | F12: m³ | G12: ABNT NBR 9050/2023 | H12: Idem
A13: C10 | B13: Remoção mecanizada de pavimento existente (T09) | C13: 0.41 | D13: 6.5 | F13: m³ | G13: DER-ES-TE-27-23 | H13: ESTIMATIVA: largura total (coluna D) e profundidade (coluna C) medidas na hachura da seção tipo 09 (≈6,5 m x 0,41 m). Ajustar com levantamento do pavimento existente.
A14: C11 | B14: Densidade do CBUQ (para tonelagem) | C14: 2.4 | F14: t/m³ | H14: Valor de referência – substituir pela densidade do projeto de mistura
A16: Células amarelas (azul) são entradas editáveis; todas as áreas e volumes das outras abas se recalculam.
A17: Área de cada camada (m²) = e × (W + 2a + e × t), onde W = largura do CBUQ acabado, e = espessura, a = alargamento do topo, t = talude.
A18: Volume entre duas estacas = extensão × média das áreas (método das áreas médias).
A21: TERRAPLENAGEM
B22: Espessura média de limpeza (área = volume / espessura) | C22: 0.2 | H22: Planilha VOLUMES DE TERRAPLENAGEM REV04 – Resumo: área 232.329,70 m² x 0,20 = 46.465,94 m³

Sheet Resumo por segmento
A1: Segmento | B1: Seção tipo | C1: Descrição | D1: Estaca inicial | E1: Estaca final | F1: Extensão (m) | G1: CBUQ (m³) | H1: CBUQ (t) | I1: BGS (m³) | J1: Sub-base (m³) | K1: Reforço (m³) | L1: Imprimação EAI (m²) | M1: Pintura RR-1C (m²) | N1: Regularização subleito (m²) | O1: Paver (m³) | P1: Pó de pedra (m³) | Q1: Paver / passeio (m²) | R1: Remoção pav. existente (m³)
A2: S01 | B2: T01 | C2: Linha geral c/ acostamento LE e LD | D2: 0+0,00 | E2: 319+0,00 | F2: =SUMIFS('Volumes por intervalo'!$C$2:$C$649,'Volumes por intervalo'!$D$2:$D$649,A2) -> 6380 | G2: =SUMIFS('Volumes por intervalo'!$H$2:$H$649,'Volumes por intervalo'!$D$2:$D$649,A2) -> 3607.6 | H2: =SUMIFS('Volumes por intervalo'!$I$2:$I$649,'Volumes por intervalo'!$D$2:$D$649,A2) -> 8658.24 | I2: =SUMIFS('Volumes por intervalo'!$J$2:$J$649,'Volumes por intervalo'!$D$2:$D$649,A2) -> 11860.768 | J2: =SUMIFS('Volumes por intervalo'!$K$2:$K$649,'Volumes por intervalo'!$D$2:$D$649,A2) -> 15540.52 | K2: =SUMIFS('Volumes por intervalo'!$L$2:$L$649,'Volumes por intervalo'!$D$2:$D$649,A2) -> 24650.58 | L2: =SUMIFS('Volumes por intervalo'!$M$2:$M$649,'Volumes por intervalo'!$D$2:$D$649,A2) -> 73109 | M2: =SUMIFS('Volumes por intervalo'!$N$2:$N$649,'Volumes por intervalo'!$D$2:$D$649,A2) -> 73109 | N2: =SUMIFS('Volumes por intervalo'!$O$2:$O$649,'Volumes por intervalo'!$D$2:$D$649,A2) -> 84082.6 | O2: =SUMIFS('Volumes por intervalo'!$P$2:$P$649,'Volumes por intervalo'!$D$2:$D$649,A2) -> 0 | P2: =SUMIFS('Volumes por intervalo'!$Q$2:$Q$649,'Volumes por intervalo'!$D$2:$D$649,A2) -> 0 | Q2: =SUMIFS('Volumes por intervalo'!$R$2:$R$649,'Volumes por intervalo'!$D$2:$D$649,A2) -> 0 | R2: =SUMIFS('Volumes por intervalo'!$S$2:$S$649,'Volumes por intervalo'!$D$2:$D$649,A2) -> 0
A3: S02 | B3: T02 | C3: IN 01 – LG c/ 2 faixas LE e LD (interseção Barra dos Andrades) | D3: 319+0,00 | E3: 332+0,00 | F3: =SUMIFS('Volumes por intervalo'!$C$2:$C$649,'Volumes por intervalo'!$D$2:$D$649,A3) -> 260 | G3: =SUMIFS('Volumes por intervalo'!$H$2:$H$649,'Volumes por intervalo'!$D$2:$D$649,A3) -> 230 | H3: =SUMIFS('Volumes por intervalo'!$I$2:$I$649,'Volumes por intervalo'!$D$2:$D$649,A3) -> 552 | I3: =SUMIFS('Volumes por intervalo'!$J$2:$J$649,'Volumes por intervalo'!$D$2:$D$649,A3) -> 748.896 | J3: =SUMIFS('Volumes por intervalo'!$K$2:$K$649,'Volumes por intervalo'!$D$2:$D$649,A3) -> 965.24 | K3: =SUMIFS('Volumes por intervalo'!$L$2:$L$649,'Volumes por intervalo'!$D$2:$D$649,A3) -> 1502.46 | L3: =SUMIFS('Volumes por intervalo'!$M$2:$M$649,'Volumes por intervalo'!$D$2:$D$649,A3) -> 4639 | M3: =SUMIFS('Volumes por intervalo'!$N$2:$N$649,'Volumes por intervalo'!$D$2:$D$649,A3) -> 4639 | N3: =SUMIFS('Volumes por intervalo'!$O$2:$O$649,'Volumes por intervalo'!$D$2:$D$649,A3) -> 5086.2 | O3: =SUMIFS('Volumes por intervalo'!$P$2:$P$649,'Volumes por intervalo'!$D$2:$D$649,A3) -> 0 | P3: =SUMIFS('Volumes por intervalo'!$Q$2:$Q$649,'Volumes por intervalo'!$D$2:$D$649,A3) -> 0 | Q3: =SUMIFS('Volumes por intervalo'!$R$2:$R$649,'Volumes por intervalo'!$D$2:$D$649,A3) -> 0 | R3: =SUMIFS('Volumes por intervalo'!$S$2:$S$649,'Volumes por intervalo'!$D$2:$D$649,A3) -> 0
A4: S03 | B4: T01 | C4: Linha geral c/ acostamento LE e LD | D4: 332+0,00 | E4: 392+10,00 | F4: =SUMIFS('Volumes por intervalo'!$C$2:$C$649,'Volumes por intervalo'!$D$2:$D$649,A4) -> 1210 | G4: =SUMIFS('Volumes por intervalo'!$H$2:$H$649,'Volumes por intervalo'!$D$2:$D$649,A4) -> 701.375 | H4: =SUMIFS('Volumes por intervalo'!$I$2:$I$649,'Volumes por intervalo'!$D$2:$D$649,A4) -> 1683.3 | I4: =SUMIFS('Volumes por intervalo'!$J$2:$J$649,'Volumes por intervalo'!$D$2:$D$649,A4) -> 2304.416 | J4: =SUMIFS('Volumes por intervalo'!$K$2:$K$649,'Volumes por intervalo'!$D$2:$D$649,A4) -> 3016.04 | K4: =SUMIFS('Volumes por intervalo'!$L$2:$L$649,'Volumes por intervalo'!$D$2:$D$649,A4) -> 4778.16 | L4: =SUMIFS('Volumes por intervalo'!$M$2:$M$649,'Volumes por intervalo'!$D$2:$D$649,A4) -> 14209 | M4: =SUMIFS('Volumes por intervalo'!$N$2:$N$649,'Volumes por intervalo'!$D$2:$D$649,A4) -> 14209 | N4: =SUMIFS('Volumes por intervalo'!$O$2:$O$649,'Volumes por intervalo'!$D$2:$D$649,A4) -> 16290.2 | O4: =SUMIFS('Volumes por intervalo'!$P$2:$P$649,'Volumes por intervalo'!$D$2:$D$649,A4) -> 0 | P4: =SUMIFS('Volumes por intervalo'!$Q$2:$Q$649,'Volumes por intervalo'!$D$2:$D$649,A4) -> 0 | Q4: =SUMIFS('Volumes por intervalo'!$R$2:$R$649,'Volumes por intervalo'!$D$2:$D$649,A4) -> 0 | R4: =SUMIFS('Volumes por intervalo'!$S$2:$S$649,'Volumes por intervalo'!$D$2:$D$649,A4) -> 0
A5: S04 | B5: T01* | C5: Sem seção tipo na prancha (faixas de acel./desacel. – Estrada Rodeio); adotada estrutura da T01 | D5: 392+10,00 | E5: 402+0,00 | F5: =SUMIFS('Volumes por intervalo'!$C$2:$C$649,'Volumes por intervalo'!$D$2:$D$649,A5) -> 190 | G5: =SUMIFS('Volumes por intervalo'!$H$2:$H$649,'Volumes por intervalo'!$D$2:$D$649,A5) -> 124.6 | H5: =SUMIFS('Volumes por intervalo'!$I$2:$I$649,'Volumes por intervalo'!$D$2:$D$649,A5) -> 299.04 | I5: =SUMIFS('Volumes por intervalo'!$J$2:$J$649,'Volumes por intervalo'!$D$2:$D$649,A5) -> 408.144 | J5: =SUMIFS('Volumes por intervalo'!$K$2:$K$649,'Volumes por intervalo'!$D$2:$D$649,A5) -> 531.46 | K5: =SUMIFS('Volumes por intervalo'!$L$2:$L$649,'Volumes por intervalo'!$D$2:$D$649,A5) -> 837.09 | L5: =SUMIFS('Volumes por intervalo'!$M$2:$M$649,'Volumes por intervalo'!$D$2:$D$649,A5) -> 2520.5 | M5: =SUMIFS('Volumes por intervalo'!$N$2:$N$649,'Volumes por intervalo'!$D$2:$D$649,A5) -> 2520.5 | N5: =SUMIFS('Volumes por intervalo'!$O$2:$O$649,'Volumes por intervalo'!$D$2:$D$649,A5) -> 2847.3 | O5: =SUMIFS('Volumes por intervalo'!$P$2:$P$649,'Volumes por intervalo'!$D$2:$D$649,A5) -> 0 | P5: =SUMIFS('Volumes por intervalo'!$Q$2:$Q$649,'Volumes por intervalo'!$D$2:$D$649,A5) -> 0 | Q5: =SUMIFS('Volumes por intervalo'!$R$2:$R$649,'Volumes por intervalo'!$D$2:$D$649,A5) -> 0 | R5: =SUMIFS('Volumes por intervalo'!$S$2:$S$649,'Volumes por intervalo'!$D$2:$D$649,A5) -> 0
A6: S05 | B6: T01 | C6: Linha geral c/ acostamento LE e LD | D6: 402+0,00 | E6: 487+10,00 | F6: =SUMIFS('Volumes por intervalo'!$C$2:$C$649,'Volumes por intervalo'!$D$2:$D$649,A6) -> 1710 | G6: =SUMIFS('Volumes por intervalo'!$H$2:$H$649,'Volumes por intervalo'!$D$2:$D$649,A6) -> 1000.125 | H6: =SUMIFS('Volumes por intervalo'!$I$2:$I$649,'Volumes por intervalo'!$D$2:$D$649,A6) -> 2400.3 | I6: =SUMIFS('Volumes por intervalo'!$J$2:$J$649,'Volumes por intervalo'!$D$2:$D$649,A6) -> 3285.216 | J6: =SUMIFS('Volumes por intervalo'!$K$2:$K$649,'Volumes por intervalo'!$D$2:$D$649,A6) -> 4298.04 | K6: =SUMIFS('Volumes por intervalo'!$L$2:$L$649,'Volumes por intervalo'!$D$2:$D$649,A6) -> 6806.16 | L6: =SUMIFS('Volumes por intervalo'!$M$2:$M$649,'Volumes por intervalo'!$D$2:$D$649,A6) -> 20259 | M6: =SUMIFS('Volumes por intervalo'!$N$2:$N$649,'Volumes por intervalo'!$D$2:$D$649,A6) -> 20259 | N6: =SUMIFS('Volumes por intervalo'!$O$2:$O$649,'Volumes por intervalo'!$D$2:$D$649,A6) -> 23200.2 | O6: =SUMIFS('Volumes por intervalo'!$P$2:$P$649,'Volumes por intervalo'!$D$2:$D$649,A6) -> 0 | P6: =SUMIFS('Volumes por intervalo'!$Q$2:$Q$649,'Volumes por intervalo'!$D$2:$D$649,A6) -> 0 | Q6: =SUMIFS('Volumes por intervalo'!$R$2:$R$649,'Volumes por intervalo'!$D$2:$D$649,A6) -> 0 | R6: =SUMIFS('Volumes por intervalo'!$S$2:$S$649,'Volumes por intervalo'!$D$2:$D$649,A6) -> 0
A7: S06 | B7: T03 | C7: LG c/ 2 faixas LD e acostamento LE e LD | D7: 487+10,00 | E7: 492+0,00 | F7: =SUMIFS('Volumes por intervalo'!$C$2:$C$649,'Volumes por intervalo'!$D$2:$D$649,A7) -> 90 | G7: =SUMIFS('Volumes por intervalo'!$H$2:$H$649,'Volumes por intervalo'!$D$2:$D$649,A7) -> 64.225 | H7: =SUMIFS('Volumes por intervalo'!$I$2:$I$649,'Volumes por intervalo'!$D$2:$D$649,A7) -> 154.14 | I7: =SUMIFS('Volumes por intervalo'!$J$2:$J$649,'Volumes por intervalo'!$D$2:$D$649,A7) -> 209.984 | J7: =SUMIFS('Volumes por intervalo'!$K$2:$K$649,'Volumes por intervalo'!$D$2:$D$649,A7) -> 272.56 | K7: =SUMIFS('Volumes por intervalo'!$L$2:$L$649,'Volumes por intervalo'!$D$2:$D$649,A7) -> 427.74 | L7: =SUMIFS('Volumes por intervalo'!$M$2:$M$649,'Volumes por intervalo'!$D$2:$D$649,A7) -> 1298 | M7: =SUMIFS('Volumes por intervalo'!$N$2:$N$649,'Volumes por intervalo'!$D$2:$D$649,A7) -> 1298 | N7: =SUMIFS('Volumes por intervalo'!$O$2:$O$649,'Volumes por intervalo'!$D$2:$D$649,A7) -> 1452.8 | O7: =SUMIFS('Volumes por intervalo'!$P$2:$P$649,'Volumes por intervalo'!$D$2:$D$649,A7) -> 0 | P7: =SUMIFS('Volumes por intervalo'!$Q$2:$Q$649,'Volumes por intervalo'!$D$2:$D$649,A7) -> 0 | Q7: =SUMIFS('Volumes por intervalo'!$R$2:$R$649,'Volumes por intervalo'!$D$2:$D$649,A7) -> 0 | R7: =SUMIFS('Volumes por intervalo'!$S$2:$S$649,'Volumes por intervalo'!$D$2:$D$649,A7) -> 0
A8: S07 | B8: T04 | C8: LG c/ 2 faixas LE e LD e acostamento LD | D8: 492+0,00 | E8: 496+0,00 | F8: =SUMIFS('Volumes por intervalo'!$C$2:$C$649,'Volumes por intervalo'!$D$2:$D$649,A8) -> 80 | G8: =SUMIFS('Volumes por intervalo'!$H$2:$H$649,'Volumes por intervalo'!$D$2:$D$649,A8) -> 64.9 | H8: =SUMIFS('Volumes por intervalo'!$I$2:$I$649,'Volumes por intervalo'!$D$2:$D$649,A8) -> 155.76 | I8: =SUMIFS('Volumes por intervalo'!$J$2:$J$649,'Volumes por intervalo'!$D$2:$D$649,A8) -> 211.648 | J8: =SUMIFS('Volumes por intervalo'!$K$2:$K$649,'Volumes por intervalo'!$D$2:$D$649,A8) -> 273.52 | K8: =SUMIFS('Volumes por intervalo'!$L$2:$L$649,'Volumes por intervalo'!$D$2:$D$649,A8) -> 427.08 | L8: =SUMIFS('Volumes por intervalo'!$M$2:$M$649,'Volumes por intervalo'!$D$2:$D$649,A8) -> 1310 | M8: =SUMIFS('Volumes por intervalo'!$N$2:$N$649,'Volumes por intervalo'!$D$2:$D$649,A8) -> 1310 | N8: =SUMIFS('Volumes por intervalo'!$O$2:$O$649,'Volumes por intervalo'!$D$2:$D$649,A8) -> 1447.6 | O8: =SUMIFS('Volumes por intervalo'!$P$2:$P$649,'Volumes por intervalo'!$D$2:$D$649,A8) -> 0 | P8: =SUMIFS('Volumes por intervalo'!$Q$2:$Q$649,'Volumes por intervalo'!$D$2:$D$649,A8) -> 0 | Q8: =SUMIFS('Volumes por intervalo'!$R$2:$R$649,'Volumes por intervalo'!$D$2:$D$649,A8) -> 0 | R8: =SUMIFS('Volumes por intervalo'!$S$2:$S$649,'Volumes por intervalo'!$D$2:$D$649,A8) -> 0
A9: S08 | B9: T06 | C9: LG c/ 2 faixas LE e acostamento LD | D9: 496+0,00 | E9: 516+10,00 | F9: =SUMIFS('Volumes por intervalo'!$C$2:$C$649,'Volumes por intervalo'!$D$2:$D$649,A9) -> 410 | G9: =SUMIFS('Volumes por intervalo'!$H$2:$H$649,'Volumes por intervalo'!$D$2:$D$649,A9) -> 282.175 | H9: =SUMIFS('Volumes por intervalo'!$I$2:$I$649,'Volumes por intervalo'!$D$2:$D$649,A9) -> 677.22 | I9: =SUMIFS('Volumes por intervalo'!$J$2:$J$649,'Volumes por intervalo'!$D$2:$D$649,A9) -> 923.296 | J9: =SUMIFS('Volumes por intervalo'!$K$2:$K$649,'Volumes por intervalo'!$D$2:$D$649,A9) -> 1200.04 | K9: =SUMIFS('Volumes por intervalo'!$L$2:$L$649,'Volumes por intervalo'!$D$2:$D$649,A9) -> 1886.16 | L9: =SUMIFS('Volumes por intervalo'!$M$2:$M$649,'Volumes por intervalo'!$D$2:$D$649,A9) -> 5705 | M9: =SUMIFS('Volumes por intervalo'!$N$2:$N$649,'Volumes por intervalo'!$D$2:$D$649,A9) -> 5705 | N9: =SUMIFS('Volumes por intervalo'!$O$2:$O$649,'Volumes por intervalo'!$D$2:$D$649,A9) -> 6410.2 | O9: =SUMIFS('Volumes por intervalo'!$P$2:$P$649,'Volumes por intervalo'!$D$2:$D$649,A9) -> 0 | P9: =SUMIFS('Volumes por intervalo'!$Q$2:$Q$649,'Volumes por intervalo'!$D$2:$D$649,A9) -> 0 | Q9: =SUMIFS('Volumes por intervalo'!$R$2:$R$649,'Volumes por intervalo'!$D$2:$D$649,A9) -> 0 | R9: =SUMIFS('Volumes por intervalo'!$S$2:$S$649,'Volumes por intervalo'!$D$2:$D$649,A9) -> 0
A10: S09 | B10: T01 | C10: Linha geral c/ acostamento LE e LD | D10: 516+10,00 | E10: 598+0,00 | F10: =SUMIFS('Volumes por intervalo'!$C$2:$C$649,'Volumes por intervalo'!$D$2:$D$649,A10) -> 1630 | G10: =SUMIFS('Volumes por intervalo'!$H$2:$H$649,'Volumes por intervalo'!$D$2:$D$649,A10) -> 909.875 | H10: =SUMIFS('Volumes por intervalo'!$I$2:$I$649,'Volumes por intervalo'!$D$2:$D$649,A10) -> 2183.7 | I10: =SUMIFS('Volumes por intervalo'!$J$2:$J$649,'Volumes por intervalo'!$D$2:$D$649,A10) -> 2992.448 | J10: =SUMIFS('Volumes por intervalo'!$K$2:$K$649,'Volumes por intervalo'!$D$2:$D$649,A10) -> 3923.12 | K10: =SUMIFS('Volumes por intervalo'!$L$2:$L$649,'Volumes por intervalo'!$D$2:$D$649,A10) -> 6226.98 | L10: =SUMIFS('Volumes por intervalo'!$M$2:$M$649,'Volumes por intervalo'!$D$2:$D$649,A10) -> 18442 | M10: =SUMIFS('Volumes por intervalo'!$N$2:$N$649,'Volumes por intervalo'!$D$2:$D$649,A10) -> 18442 | N10: =SUMIFS('Volumes por intervalo'!$O$2:$O$649,'Volumes por intervalo'!$D$2:$D$649,A10) -> 21245.6 | O10: =SUMIFS('Volumes por intervalo'!$P$2:$P$649,'Volumes por intervalo'!$D$2:$D$649,A10) -> 0 | P10: =SUMIFS('Volumes por intervalo'!$Q$2:$Q$649,'Volumes por intervalo'!$D$2:$D$649,A10) -> 0 | Q10: =SUMIFS('Volumes por intervalo'!$R$2:$R$649,'Volumes por intervalo'!$D$2:$D$649,A10) -> 0 | R10: =SUMIFS('Volumes por intervalo'!$S$2:$S$649,'Volumes por intervalo'!$D$2:$D$649,A10) -> 0
A11: S10 | B11: T07 | C11: Início área urbana Rebouças c/ passeio LD | D11: 598+0,00 | E11: 602+0,00 | F11: =SUMIFS('Volumes por intervalo'!$C$2:$C$649,'Volumes por intervalo'!$D$2:$D$649,A11) -> 80 | G11: =SUMIFS('Volumes por intervalo'!$H$2:$H$649,'Volumes por intervalo'!$D$2:$D$649,A11) -> 44.2 | H11: =SUMIFS('Volumes por intervalo'!$I$2:$I$649,'Volumes por intervalo'!$D$2:$D$649,A11) -> 106.08 | I11: =SUMIFS('Volumes por intervalo'!$J$2:$J$649,'Volumes por intervalo'!$D$2:$D$649,A11) -> 145.408 | J11: =SUMIFS('Volumes por intervalo'!$K$2:$K$649,'Volumes por intervalo'!$D$2:$D$649,A11) -> 190.72 | K11: =SUMIFS('Volumes por intervalo'!$L$2:$L$649,'Volumes por intervalo'!$D$2:$D$649,A11) -> 302.88 | L11: =SUMIFS('Volumes por intervalo'!$M$2:$M$649,'Volumes por intervalo'!$D$2:$D$649,A11) -> 896 | M11: =SUMIFS('Volumes por intervalo'!$N$2:$N$649,'Volumes por intervalo'!$D$2:$D$649,A11) -> 896 | N11: =SUMIFS('Volumes por intervalo'!$O$2:$O$649,'Volumes por intervalo'!$D$2:$D$649,A11) -> 1033.6 | O11: =SUMIFS('Volumes por intervalo'!$P$2:$P$649,'Volumes por intervalo'!$D$2:$D$649,A11) -> 13.5 | P11: =SUMIFS('Volumes por intervalo'!$Q$2:$Q$649,'Volumes por intervalo'!$D$2:$D$649,A11) -> 11.25 | Q11: =SUMIFS('Volumes por intervalo'!$R$2:$R$649,'Volumes por intervalo'!$D$2:$D$649,A11) -> 225 | R11: =SUMIFS('Volumes por intervalo'!$S$2:$S$649,'Volumes por intervalo'!$D$2:$D$649,A11) -> 0
A12: S11 | B12: T08 | C12: Área urbana Rebouças c/ passeio LE e LD | D12: 602+0,00 | E12: 623+10,00 | F12: =SUMIFS('Volumes por intervalo'!$C$2:$C$649,'Volumes por intervalo'!$D$2:$D$649,A12) -> 430 | G12: =SUMIFS('Volumes por intervalo'!$H$2:$H$649,'Volumes por intervalo'!$D$2:$D$649,A12) -> 218.075 | H12: =SUMIFS('Volumes por intervalo'!$I$2:$I$649,'Volumes por intervalo'!$D$2:$D$649,A12) -> 523.38 | I12: =SUMIFS('Volumes por intervalo'!$J$2:$J$649,'Volumes por intervalo'!$D$2:$D$649,A12) -> 719.168 | J12: =SUMIFS('Volumes por intervalo'!$K$2:$K$649,'Volumes por intervalo'!$D$2:$D$649,A12) -> 947.12 | K12: =SUMIFS('Volumes por intervalo'!$L$2:$L$649,'Volumes por intervalo'!$D$2:$D$649,A12) -> 1510.98 | L12: =SUMIFS('Volumes por intervalo'!$M$2:$M$649,'Volumes por intervalo'!$D$2:$D$649,A12) -> 4426 | M12: =SUMIFS('Volumes por intervalo'!$N$2:$N$649,'Volumes por intervalo'!$D$2:$D$649,A12) -> 4426 | N12: =SUMIFS('Volumes por intervalo'!$O$2:$O$649,'Volumes por intervalo'!$D$2:$D$649,A12) -> 5165.6 | O12: =SUMIFS('Volumes por intervalo'!$P$2:$P$649,'Volumes por intervalo'!$D$2:$D$649,A12) -> 135.78 | P12: =SUMIFS('Volumes por intervalo'!$Q$2:$Q$649,'Volumes por intervalo'!$D$2:$D$649,A12) -> 113.15 | Q12: =SUMIFS('Volumes por intervalo'!$R$2:$R$649,'Volumes por intervalo'!$D$2:$D$649,A12) -> 2263 | R12: =SUMIFS('Volumes por intervalo'!$S$2:$S$649,'Volumes por intervalo'!$D$2:$D$649,A12) -> 0
A13: S12 | B13: T09 | C13: Área urbana c/ passeio LE e LD e remoção de pavimento existente | D13: 623+10,00 | E13: 642+0,00 | F13: =SUMIFS('Volumes por intervalo'!$C$2:$C$649,'Volumes por intervalo'!$D$2:$D$649,A13) -> 370 | G13: =SUMIFS('Volumes por intervalo'!$H$2:$H$649,'Volumes por intervalo'!$D$2:$D$649,A13) -> 189.35 | H13: =SUMIFS('Volumes por intervalo'!$I$2:$I$649,'Volumes por intervalo'!$D$2:$D$649,A13) -> 454.44 | I13: =SUMIFS('Volumes por intervalo'!$J$2:$J$649,'Volumes por intervalo'!$D$2:$D$649,A13) -> 624.272 | J13: =SUMIFS('Volumes por intervalo'!$K$2:$K$649,'Volumes por intervalo'!$D$2:$D$649,A13) -> 821.78 | K13: =SUMIFS('Volumes por intervalo'!$L$2:$L$649,'Volumes por intervalo'!$D$2:$D$649,A13) -> 1310.37 | L13: =SUMIFS('Volumes por intervalo'!$M$2:$M$649,'Volumes por intervalo'!$D$2:$D$649,A13) -> 3842.5 | M13: =SUMIFS('Volumes por intervalo'!$N$2:$N$649,'Volumes por intervalo'!$D$2:$D$649,A13) -> 3842.5 | N13: =SUMIFS('Volumes por intervalo'!$O$2:$O$649,'Volumes por intervalo'!$D$2:$D$649,A13) -> 4478.9 | O13: =SUMIFS('Volumes por intervalo'!$P$2:$P$649,'Volumes por intervalo'!$D$2:$D$649,A13) -> 114 | P13: =SUMIFS('Volumes por intervalo'!$Q$2:$Q$649,'Volumes por intervalo'!$D$2:$D$649,A13) -> 95 | Q13: =SUMIFS('Volumes por intervalo'!$R$2:$R$649,'Volumes por intervalo'!$D$2:$D$649,A13) -> 1900 | R13: =SUMIFS('Volumes por intervalo'!$S$2:$S$649,'Volumes por intervalo'!$D$2:$D$649,A13) -> 986.05
A14: S13 | B14: T09* | C14: Após 642+0,00 (fim do trecho) – sem seção tipo; adotada T09 | D14: 642+0,00 | E14: 642+15,817 | F14: =SUMIFS('Volumes por intervalo'!$C$2:$C$649,'Volumes por intervalo'!$D$2:$D$649,A14) -> 15.817 | G14: =SUMIFS('Volumes por intervalo'!$H$2:$H$649,'Volumes por intervalo'!$D$2:$D$649,A14) -> 8.7388925 | H14: =SUMIFS('Volumes por intervalo'!$I$2:$I$649,'Volumes por intervalo'!$D$2:$D$649,A14) -> 20.973342 | I14: =SUMIFS('Volumes por intervalo'!$J$2:$J$649,'Volumes por intervalo'!$D$2:$D$649,A14) -> 28.748979 | J14: =SUMIFS('Volumes por intervalo'!$K$2:$K$649,'Volumes por intervalo'!$D$2:$D$649,A14) -> 37.707728 | K14: =SUMIFS('Volumes por intervalo'!$L$2:$L$649,'Volumes por intervalo'!$D$2:$D$649,A14) -> 59.883162 | L14: =SUMIFS('Volumes por intervalo'!$M$2:$M$649,'Volumes por intervalo'!$D$2:$D$649,A14) -> 177.1504 | M14: =SUMIFS('Volumes por intervalo'!$N$2:$N$649,'Volumes por intervalo'!$D$2:$D$649,A14) -> 177.1504 | N14: =SUMIFS('Volumes por intervalo'!$O$2:$O$649,'Volumes por intervalo'!$D$2:$D$649,A14) -> 204.35564 | O14: =SUMIFS('Volumes por intervalo'!$P$2:$P$649,'Volumes por intervalo'!$D$2:$D$649,A14) -> 5.69412 | P14: =SUMIFS('Volumes por intervalo'!$Q$2:$Q$649,'Volumes por intervalo'!$D$2:$D$649,A14) -> 4.7451 | Q14: =SUMIFS('Volumes por intervalo'!$R$2:$R$649,'Volumes por intervalo'!$D$2:$D$649,A14) -> 94.902 | R14: =SUMIFS('Volumes por intervalo'!$S$2:$S$649,'Volumes por intervalo'!$D$2:$D$649,A14) -> 42.152305
A15: TOTAL | F15: =SUM(F2:F14) -> 12855.817 | G15: =SUM(G2:G14) -> 7445.2389 | H15: =SUM(H2:H14) -> 17868.573 | I15: =SUM(I2:I14) -> 24462.413 | J15: =SUM(J2:J14) -> 32017.868 | K15: =SUM(K2:K14) -> 50726.523 | L15: =SUM(L2:L14) -> 150833.15 | M15: =SUM(M2:M14) -> 150833.15 | ... R15: =SUM(R2:R14) -> 1028.2023
A17: Encaixes pavimento novo/existente (início Est. 0 e fim Est. 642+15,817): remoção mecanizada de revestimento 0,50 m x 0,05 m na largura da pista (detalhe da folha 02/02):
C18: Remoção de revestimento nos encaixes (m³) | G18: =0.5*0.05*(Estacas!F2+Estacas!F650) -> 0.55
C19: Corte com serra nos encaixes (m) | G19: =2*(Estacas!F2+Estacas!F650) -> 44

Sheet Estacas
A1: Estaca | B1: Estaca (decimal) | C1: Distância (m) | D1: Segmento | E1: Seção tipo | F1: Largura CBUQ acabado W (m) | G1: Passeio LE (m) | H1: Passeio LD (m) | I1: Origem da largura | J1: Observações | K1: Área CBUQ (m²) | L1: Área BGS (m²) | M1: Área sub-base (m²) | N1: Área reforço (m²) | O1: Largura imprimação / pintura (m) | P1: Largura regularização subleito (m) | Q1: Largura total de passeio (m) | S1: Acum. W·m (m²) | T1: Acum. CBUQ (m³) | U1: Acum. BGS (m³) | V1: Acum. sub-base (m³) | W1: Acum. reforço (m³) | X1: Acum. imprimação (m²) | Y1: Acum. pintura (m²) | Z1: Acum. regularização (m²) | AA1: Acum. paver (m³) | AB1: Acum. pó de pedra (m³) | AC1: Acum. passeio (m²) | AD1: Acum. remoção (m³)
A2: 0+0,00 | B2: 0 | C2: 0 | D2: S01 | E2: T01 | F2: 11 | G2: 0 | H2: 0 | I2: Medida | K2: =Parâmetros!$C$4*(F2+2*Parâmetros!$D$4+Parâmetros!$C$4*Parâmetros!$E$4) -> 0.5525 | L2: =Parâmetros!$C$5*(F2+2*Parâmetros!$D$5+Parâmetros!$C$5*Parâmetros!$E$5) -> 1.8176 | M2: =Parâmetros!$C$6*(F2+2*Parâmetros!$D$6+Parâmetros!$C$6*Parâmetros!$E$6) -> 2.384 | N2: =Parâmetros!$C$7*(F2+2*Parâmetros!$D$7+Parâmetros!$C$7*Parâmetros!$E$7) -> 3.786 | O2: =F2+2*Parâmetros!$D$8 -> 11.2 | P2: =F2+2*Parâmetros!$D$10 -> 12.92 | Q2: =G2+H2 -> 0 | S2: 0 | T2: 0 | U2: 0 | V2: 0 | W2: 0 | X2: 0 | Y2: 0 | Z2: 0 | AA2: 0 | AB2: 0 | AC2: 0 | AD2: 0
A3: 1+0,00 | B3: 1 | C3: 20 | D3: S01 | E3: T01 | F3: 11 | G3: 0 | H3: 0 | I3: Medida | K3: =Parâmetros!$C$4*(F3+2*Parâmetros!$D$4+Parâmetros!$C$4*Parâmetros!$E$4) -> 0.5525 | L3: =Parâmetros!$C$5*(F3+2*Parâmetros!$D$5+Parâmetros!$C$5*Parâmetros!$E$5) -> 1.8176 | M3: =Parâmetros!$C$6*(F3+2*Parâmetros!$D$6+Parâmetros!$C$6*Parâmetros!$E$6) -> 2.384 | N3: =Parâmetros!$C$7*(F3+2*Parâmetros!$D$7+Parâmetros!$C$7*Parâmetros!$E$7) -> 3.786 | O3: =F3+2*Parâmetros!$D$8 -> 11.2 | P3: =F3+2*Parâmetros!$D$10 -> 12.92 | Q3: =G3+H3 -> 0 | S3: =S2+'Volumes por intervalo'!C2*(F2+F3)/2 -> 220 | T3: =T2+'Volumes por intervalo'!H2 -> 11.05 | U3: =U2+'Volumes por intervalo'!J2 -> 36.352 | V3: =V2+'Volumes por intervalo'!K2 -> 47.68 | W3: =W2+'Volumes por intervalo'!L2 -> 75.72 | X3: =X2+'Volumes por intervalo'!M2 -> 224 | Y3: =Y2+'Volumes por intervalo'!N2 -> 224 | Z3: =Z2+'Volumes por intervalo'!O2 -> 258.4 | AA3: =AA2+'Volumes por intervalo'!P2 -> 0 | AB3: =AB2+'Volumes por intervalo'!Q2 -> 0 | ... AD3: =AD2+'Volumes por intervalo'!S2 -> 0
A4: 2+0,00 | B4: 2 | C4: 40 | D4: S01 | E4: T01 | F4: 11 | G4: 0 | H4: 0 | I4: Medida | K4: =Parâmetros!$C$4*(F4+2*Parâmetros!$D$4+Parâmetros!$C$4*Parâmetros!$E$4) -> 0.5525 | L4: =Parâmetros!$C$5*(F4+2*Parâmetros!$D$5+Parâmetros!$C$5*Parâmetros!$E$5) -> 1.8176 | M4: =Parâmetros!$C$6*(F4+2*Parâmetros!$D$6+Parâmetros!$C$6*Parâmetros!$E$6) -> 2.384 | N4: =Parâmetros!$C$7*(F4+2*Parâmetros!$D$7+Parâmetros!$C$7*Parâmetros!$E$7) -> 3.786 | O4: =F4+2*Parâmetros!$D$8 -> 11.2 | P4: =F4+2*Parâmetros!$D$10 -> 12.92 | Q4: =G4+H4 -> 0 | S4: =S3+'Volumes por intervalo'!C3*(F3+F4)/2 -> 440 | T4: =T3+'Volumes por intervalo'!H3 -> 22.1 | U4: =U3+'Volumes por intervalo'!J3 -> 72.704 | V4: =V3+'Volumes por intervalo'!K3 -> 95.36 | W4: =W3+'Volumes por intervalo'!L3 -> 151.44 | X4: =X3+'Volumes por intervalo'!M3 -> 448 | Y4: =Y3+'Volumes por intervalo'!N3 -> 448 | Z4: =Z3+'Volumes por intervalo'!O3 -> 516.8 | AA4: =AA3+'Volumes por intervalo'!P3 -> 0 | AB4: =AB3+'Volumes por intervalo'!Q3 -> 0 | ... AD4: =AD3+'Volumes por intervalo'!S3 -> 0
A5: 3+0,00 | B5: 3 | C5: 60 | D5: S01 | E5: T01 | F5: 11 | G5: 0 | H5: 0 | I5: Medida | K5: =Parâmetros!$C$4*(F5+2*Parâmetros!$D$4+Parâmetros!$C$4*Parâmetros!$E$4) -> 0.5525 | L5: =Parâmetros!$C$5*(F5+2*Parâmetros!$D$5+Parâmetros!$C$5*Parâmetros!$E$5) -> 1.8176 | M5: =Parâmetros!$C$6*(F5+2*Parâmetros!$D$6+Parâmetros!$C$6*Parâmetros!$E$6) -> 2.384 | N5: =Parâmetros!$C$7*(F5+2*Parâmetros!$D$7+Parâmetros!$C$7*Parâmetros!$E$7) -> 3.786 | O5: =F5+2*Parâmetros!$D$8 -> 11.2 | P5: =F5+2*Parâmetros!$D$10 -> 12.92 | Q5: =G5+H5 -> 0 | S5: =S4+'Volumes por intervalo'!C4*(F4+F5)/2 -> 660 | T5: =T4+'Volumes por intervalo'!H4 -> 33.15 | U5: =U4+'Volumes por intervalo'!J4 -> 109.056 | V5: =V4+'Volumes por intervalo'!K4 -> 143.04 | W5: =W4+'Volumes por intervalo'!L4 -> 227.16 | X5: =X4+'Volumes por intervalo'!M4 -> 672 | Y5: =Y4+'Volumes por intervalo'!N4 -> 672 | Z5: =Z4+'Volumes por intervalo'!O4 -> 775.2 | AA5: =AA4+'Volumes por intervalo'!P4 -> 0 | AB5: =AB4+'Volumes por intervalo'!Q4 -> 0 | ... AD5: =AD4+'Volumes por intervalo'!S4 -> 0
A6: 4+0,00 | B6: 4 | C6: 80 | D6: S01 | E6: T01 | F6: 11 | G6: 0 | H6: 0 | I6: Medida | K6: =Parâmetros!$C$4*(F6+2*Parâmetros!$D$4+Parâmetros!$C$4*Parâmetros!$E$4) -> 0.5525 | L6: =Parâmetros!$C$5*(F6+2*Parâmetros!$D$5+Parâmetros!$C$5*Parâmetros!$E$5) -> 1.8176 | M6: =Parâmetros!$C$6*(F6+2*Parâmetros!$D$6+Parâmetros!$C$6*Parâmetros!$E$6) -> 2.384 | N6: =Parâmetros!$C$7*(F6+2*Parâmetros!$D$7+Parâmetros!$C$7*Parâmetros!$E$7) -> 3.786 | O6: =F6+2*Parâmetros!$D$8 -> 11.2 | P6: =F6+2*Parâmetros!$D$10 -> 12.92 | Q6: =G6+H6 -> 0 | S6: =S5+'Volumes por intervalo'!C5*(F5+F6)/2 -> 880 | T6: =T5+'Volumes por intervalo'!H5 -> 44.2 | U6: =U5+'Volumes por intervalo'!J5 -> 145.408 | V6: =V5+'Volumes por intervalo'!K5 -> 190.72 | W6: =W5+'Volumes por intervalo'!L5 -> 302.88 | X6: =X5+'Volumes por intervalo'!M5 -> 896 | Y6: =Y5+'Volumes por intervalo'!N5 -> 896 | Z6: =Z5+'Volumes por intervalo'!O5 -> 1033.6 | AA6: =AA5+'Volumes por intervalo'!P5 -> 0 | AB6: =AB5+'Volumes por intervalo'!Q5 -> 0 | ... AD6: =AD5+'Volumes por intervalo'!S5 -> 0
A7: 5+0,00 | B7: 5 | C7: 100 | D7: S01 | E7: T01 | F7: 11 | G7: 0 | H7: 0 | I7: Medida | K7: =Parâmetros!$C$4*(F7+2*Parâmetros!$D$4+Parâmetros!$C$4*Parâmetros!$E$4) -> 0.5525 | L7: =Parâmetros!$C$5*(F7+2*Parâmetros!$D$5+Parâmetros!$C$5*Parâmetros!$E$5) -> 1.8176 | M7: =Parâmetros!$C$6*(F7+2*Parâmetros!$D$6+Parâmetros!$C$6*Parâmetros!$E$6) -> 2.384 | N7: =Parâmetros!$C$7*(F7+2*Parâmetros!$D$7+Parâmetros!$C$7*Parâmetros!$E$7) -> 3.786 | O7: =F7+2*Parâmetros!$D$8 -> 11.2 | P7: =F7+2*Parâmetros!$D$10 -> 12.92 | Q7: =G7+H7 -> 0 | S7: =S6+'Volumes por intervalo'!C6*(F6+F7)/2 -> 1100 | T7: =T6+'Volumes por intervalo'!H6 -> 55.25 | U7: =U6+'Volumes por intervalo'!J6 -> 181.76 | V7: =V6+'Volumes por intervalo'!K6 -> 238.4 | W7: =W6+'Volumes por intervalo'!L6 -> 378.6 | X7: =X6+'Volumes por intervalo'!M6 -> 1120 | Y7: =Y6+'Volumes por intervalo'!N6 -> 1120 | Z7: =Z6+'Volumes por intervalo'!O6 -> 1292 | AA7: =AA6+'Volumes por intervalo'!P6 -> 0 | AB7: =AB6+'Volumes por intervalo'!Q6 -> 0 | ... AD7: =AD6+'Volumes por intervalo'!S6 -> 0
A8: 6+0,00 | B8: 6 | C8: 120 | D8: S01 | E8: T01 | F8: 11 | G8: 0 | H8: 0 | I8: Medida | K8: =Parâmetros!$C$4*(F8+2*Parâmetros!$D$4+Parâmetros!$C$4*Parâmetros!$E$4) -> 0.5525 | L8: =Parâmetros!$C$5*(F8+2*Parâmetros!$D$5+Parâmetros!$C$5*Parâmetros!$E$5) -> 1.8176 | M8: =Parâmetros!$C$6*(F8+2*Parâmetros!$D$6+Parâmetros!$C$6*Parâmetros!$E$6) -> 2.384 | N8: =Parâmetros!$C$7*(F8+2*Parâmetros!$D$7+Parâmetros!$C$7*Parâmetros!$E$7) -> 3.786 | O8: =F8+2*Parâmetros!$D$8 -> 11.2 | P8: =F8+2*Parâmetros!$D$10 -> 12.92 | Q8: =G8+H8 -> 0 | S8: =S7+'Volumes por intervalo'!C7*(F7+F8)/2 -> 1320 | T8: =T7+'Volumes por intervalo'!H7 -> 66.3 | U8: =U7+'Volumes por intervalo'!J7 -> 218.112 | V8: =V7+'Volumes por intervalo'!K7 -> 286.08 | W8: =W7+'Volumes por intervalo'!L7 -> 454.32 | X8: =X7+'Volumes por intervalo'!M7 -> 1344 | Y8: =Y7+'Volumes por intervalo'!N7 -> 1344 | Z8: =Z7+'Volumes por intervalo'!O7 -> 1550.4 | AA8: =AA7+'Volumes por intervalo'!P7 -> 0 | AB8: =AB7+'Volumes por intervalo'!Q7 -> 0 | ... AD8: =AD7+'Volumes por intervalo'!S7 -> 0
A9: 7+0,00 | B9: 7 | C9: 140 | D9: S01 | E9: T01 | F9: 11 | G9: 0 | H9: 0 | I9: Medida | K9: =Parâmetros!$C$4*(F9+2*Parâmetros!$D$4+Parâmetros!$C$4*Parâmetros!$E$4) -> 0.5525 | L9: =Parâmetros!$C$5*(F9+2*Parâmetros!$D$5+Parâmetros!$C$5*Parâmetros!$E$5) -> 1.8176 | M9: =Parâmetros!$C$6*(F9+2*Parâmetros!$D$6+Parâmetros!$C$6*Parâmetros!$E$6) -> 2.384 | N9: =Parâmetros!$C$7*(F9+2*Parâmetros!$D$7+Parâmetros!$C$7*Parâmetros!$E$7) -> 3.786 | O9: =F9+2*Parâmetros!$D$8 -> 11.2 | P9: =F9+2*Parâmetros!$D$10 -> 12.92 | Q9: =G9+H9 -> 0 | S9: =S8+'Volumes por intervalo'!C8*(F8+F9)/2 -> 1540 | T9: =T8+'Volumes por intervalo'!H8 -> 77.35 | U9: =U8+'Volumes por intervalo'!J8 -> 254.464 | V9: =V8+'Volumes por intervalo'!K8 -> 333.76 | W9: =W8+'Volumes por intervalo'!L8 -> 530.04 | X9: =X8+'Volumes por intervalo'!M8 -> 1568 | Y9: =Y8+'Volumes por intervalo'!N8 -> 1568 | Z9: =Z8+'Volumes por intervalo'!O8 -> 1808.8 | AA9: =AA8+'Volumes por intervalo'!P8 -> 0 | AB9: =AB8+'Volumes por intervalo'!Q8 -> 0 | ... AD9: =AD8+'Volumes por intervalo'!S8 -> 0
A10: 8+0,00 | B10: 8 | C10: 160 | D10: S01 | E10: T01 | F10: 11 | G10: 0 | H10: 0 | I10: Medida | K10: =Parâmetros!$C$4*(F10+2*Parâmetros!$D$4+Parâmetros!$C$4*Parâmetros!$E$4) -> 0.5525 | L10: =Parâmetros!$C$5*(F10+2*Parâmetros!$D$5+Parâmetros!$C$5*Parâmetros!$E$5) -> 1.8176 | M10: =Parâmetros!$C$6*(F10+2*Parâmetros!$D$6+Parâmetros!$C$6*Parâmetros!$E$6) -> 2.384 | N10: =Parâmetros!$C$7*(F10+2*Parâmetros!$D$7+Parâmetros!$C$7*Parâmetros!$E$7) -> 3.786 | O10: =F10+2*Parâmetros!$D$8 -> 11.2 | P10: =F10+2*Parâmetros!$D$10 -> 12.92 | Q10: =G10+H10 -> 0 | S10: =S9+'Volumes por intervalo'!C9*(F9+F10)/2 -> 1760 | T10: =T9+'Volumes por intervalo'!H9 -> 88.4 | U10: =U9+'Volumes por intervalo'!J9 -> 290.816 | V10: =V9+'Volumes por intervalo'!K9 -> 381.44 | W10: =W9+'Volumes por intervalo'!L9 -> 605.76 | X10: =X9+'Volumes por intervalo'!M9 -> 1792 | Y10: =Y9+'Volumes por intervalo'!N9 -> 1792 | Z10: =Z9+'Volumes por intervalo'!O9 -> 2067.2 | AA10: =AA9+'Volumes por intervalo'!P9 -> 0 | AB10: =AB9+'Volumes por intervalo'!Q9 -> 0 | ... AD10: =AD9+'Volumes por intervalo'!S9 -> 0
A11: 9+0,00 | B11: 9 | C11: 180 | D11: S01 | E11: T01 | F11: 11 | G11: 0 | H11: 0 | I11: Medida | K11: =Parâmetros!$C$4*(F11+2*Parâmetros!$D$4+Parâmetros!$C$4*Parâmetros!$E$4) -> 0.5525 | L11: =Parâmetros!$C$5*(F11+2*Parâmetros!$D$5+Parâmetros!$C$5*Parâmetros!$E$5) -> 1.8176 | M11: =Parâmetros!$C$6*(F11+2*Parâmetros!$D$6+Parâmetros!$C$6*Parâmetros!$E$6) -> 2.384 | N11: =Parâmetros!$C$7*(F11+2*Parâmetros!$D$7+Parâmetros!$C$7*Parâmetros!$E$7) -> 3.786 | O11: =F11+2*Parâmetros!$D$8 -> 11.2 | P11: =F11+2*Parâmetros!$D$10 -> 12.92 | Q11: =G11+H11 -> 0 | S11: =S10+'Volumes por intervalo'!C10*(F10+F11)/2 -> 1980 | T11: =T10+'Volumes por intervalo'!H10 -> 99.45 | U11: =U10+'Volumes por intervalo'!J10 -> 327.168 | V11: =V10+'Volumes por intervalo'!K10 -> 429.12 | W11: =W10+'Volumes por intervalo'!L10 -> 681.48 | X11: =X10+'Volumes por intervalo'!M10 -> 2016 | Y11: =Y10+'Volumes por intervalo'!N10 -> 2016 | Z11: =Z10+'Volumes por intervalo'!O10 -> 2325.6 | AA11: =AA10+'Volumes por intervalo'!P10 -> 0 | AB11: =AB10+'Volumes por intervalo'!Q10 -> 0 | ... AD11: =AD10+'Volumes por intervalo'!S10 -> 0
A12: 10+0,00 | B12: 10 | C12: 200 | D12: S01 | E12: T01 | F12: 11 | G12: 0 | H12: 0 | I12: Medida | K12: =Parâmetros!$C$4*(F12+2*Parâmetros!$D$4+Parâmetros!$C$4*Parâmetros!$E$4) -> 0.5525 | L12: =Parâmetros!$C$5*(F12+2*Parâmetros!$D$5+Parâmetros!$C$5*Parâmetros!$E$5) -> 1.8176 | M12: =Parâmetros!$C$6*(F12+2*Parâmetros!$D$6+Parâmetros!$C$6*Parâmetros!$E$6) -> 2.384 | N12: =Parâmetros!$C$7*(F12+2*Parâmetros!$D$7+Parâmetros!$C$7*Parâmetros!$E$7) -> 3.786 | O12: =F12+2*Parâmetros!$D$8 -> 11.2 | P12: =F12+2*Parâmetros!$D$10 -> 12.92 | Q12: =G12+H12 -> 0 | S12: =S11+'Volumes por intervalo'!C11*(F11+F12)/2 -> 2200 | T12: =T11+'Volumes por intervalo'!H11 -> 110.5 | U12: =U11+'Volumes por intervalo'!J11 -> 363.52 | V12: =V11+'Volumes por intervalo'!K11 -> 476.8 | W12: =W11+'Volumes por intervalo'!L11 -> 757.2 | X12: =X11+'Volumes por intervalo'!M11 -> 2240 | Y12: =Y11+'Volumes por intervalo'!N11 -> 2240 | Z12: =Z11+'Volumes por intervalo'!O11 -> 2584 | AA12: =AA11+'Volumes por intervalo'!P11 -> 0 | AB12: =AB11+'Volumes por intervalo'!Q11 -> 0 | ... AD12: =AD11+'Volumes por intervalo'!S11 -> 0
A13: 11+0,00 | B13: 11 | C13: 220 | D13: S01 | E13: T01 | F13: 11 | G13: 0 | H13: 0 | I13: Medida | K13: =Parâmetros!$C$4*(F13+2*Parâmetros!$D$4+Parâmetros!$C$4*Parâmetros!$E$4) -> 0.5525 | L13: =Parâmetros!$C$5*(F13+2*Parâmetros!$D$5+Parâmetros!$C$5*Parâmetros!$E$5) -> 1.8176 | M13: =Parâmetros!$C$6*(F13+2*Parâmetros!$D$6+Parâmetros!$C$6*Parâmetros!$E$6) -> 2.384 | N13: =Parâmetros!$C$7*(F13+2*Parâmetros!$D$7+Parâmetros!$C$7*Parâmetros!$E$7) -> 3.786 | O13: =F13+2*Parâmetros!$D$8 -> 11.2 | P13: =F13+2*Parâmetros!$D$10 -> 12.92 | Q13: =G13+H13 -> 0 | S13: =S12+'Volumes por intervalo'!C12*(F12+F13)/2 -> 2420 | T13: =T12+'Volumes por intervalo'!H12 -> 121.55 | U13: =U12+'Volumes por intervalo'!J12 -> 399.872 | V13: =V12+'Volumes por intervalo'!K12 -> 524.48 | W13: =W12+'Volumes por intervalo'!L12 -> 832.92 | X13: =X12+'Volumes por intervalo'!M12 -> 2464 | Y13: =Y12+'Volumes por intervalo'!N12 -> 2464 | Z13: =Z12+'Volumes por intervalo'!O12 -> 2842.4 | AA13: =AA12+'Volumes por intervalo'!P12 -> 0 | AB13: =AB12+'Volumes por intervalo'!Q12 -> 0 | ... AD13: =AD12+'Volumes por intervalo'!S12 -> 0
A14: 12+0,00 | B14: 12 | C14: 240 | D14: S01 | E14: T01 | F14: 11 | G14: 0 | H14: 0 | I14: Medida | K14: =Parâmetros!$C$4*(F14+2*Parâmetros!$D$4+Parâmetros!$C$4*Parâmetros!$E$4) -> 0.5525 | L14: =Parâmetros!$C$5*(F14+2*Parâmetros!$D$5+Parâmetros!$C$5*Parâmetros!$E$5) -> 1.8176 | M14: =Parâmetros!$C$6*(F14+2*Parâmetros!$D$6+Parâmetros!$C$6*Parâmetros!$E$6) -> 2.384 | N14: =Parâmetros!$C$7*(F14+2*Parâmetros!$D$7+Parâmetros!$C$7*Parâmetros!$E$7) -> 3.786 | O14: =F14+2*Parâmetros!$D$8 -> 11.2 | P14: =F14+2*Parâmetros!$D$10 -> 12.92 | Q14: =G14+H14 -> 0 | S14: =S13+'Volumes por intervalo'!C13*(F13+F14)/2 -> 2640 | T14: =T13+'Volumes por intervalo'!H13 -> 132.6 | U14: =U13+'Volumes por intervalo'!J13 -> 436.224 | V14: =V13+'Volumes por intervalo'!K13 -> 572.16 | W14: =W13+'Volumes por intervalo'!L13 -> 908.64 | X14: =X13+'Volumes por intervalo'!M13 -> 2688 | Y14: =Y13+'Volumes por intervalo'!N13 -> 2688 | Z14: =Z13+'Volumes por intervalo'!O13 -> 3100.8 | AA14: =AA13+'Volumes por intervalo'!P13 -> 0 | AB14: =AB13+'Volumes por intervalo'!Q13 -> 0 | ... AD14: =AD13+'Volumes por intervalo'!S13 -> 0
... A43: 41+0,00 | B43: 41 | C43: 820 | D43: S01 | E43: T01 | F43: 11 | G43: 0 | H43: 0 | I43: Medida | K43: =Parâmetros!$C$4*(F43+2*Parâmetros!$D$4+Parâmetros!$C$4*Parâmetros!$E$4) -> 0.5525 | L43: =Parâmetros!$C$5*(F43+2*Parâmetros!$D$5+Parâmetros!$C$5*Parâmetros!$E$5) -> 1.8176 | M43: =Parâmetros!$C$6*(F43+2*Parâmetros!$D$6+Parâmetros!$C$6*Parâmetros!$E$6) -> 2.384 | N43: =Parâmetros!$C$7*(F43+2*Parâmetros!$D$7+Parâmetros!$C$7*Parâmetros!$E$7) -> 3.786 | O43: =F43+2*Parâmetros!$D$8 -> 11.2 | P43: =F43+2*Parâmetros!$D$10 -> 12.92 | Q43: =G43+H43 -> 0 | S43: =S42+'Volumes por intervalo'!C42*(F42+F43)/2 -> 9020 | T43: =T42+'Volumes por intervalo'!H42 -> 453.05 | U43: =U42+'Volumes por intervalo'!J42 -> 1490.432 | V43: =V42+'Volumes por intervalo'!K42 -> 1954.88 | W43: =W42+'Volumes por intervalo'!L42 -> 3104.52 | X43: =X42+'Volumes por intervalo'!M42 -> 9184 | Y43: =Y42+'Volumes por intervalo'!N42 -> 9184 | Z43: =Z42+'Volumes por intervalo'!O42 -> 10594.4 | AA43: =AA42+'Volumes por intervalo'!P42 -> 0 | AB43: =AB42+'Volumes por intervalo'!Q42 -> 0 | ... AD43: =AD42+'Volumes por intervalo'!S42 -> 0
A44: 42+0,00 | B44: 42 | C44: 840 | D44: S01 | E44: T01 | F44: 11 | G44: 0 | H44: 0 | I44: Medida | J44: LD: elemento de 7.40 m (acesso/ilha) descartado | K44: =Parâmetros!$C$4*(F44+2*Parâmetros!$D$4+Parâmetros!$C$4*Parâmetros!$E$4) -> 0.5525 | L44: =Parâmetros!$C$5*(F44+2*Parâmetros!$D$5+Parâmetros!$C$5*Parâmetros!$E$5) -> 1.8176 | M44: =Parâmetros!$C$6*(F44+2*Parâmetros!$D$6+Parâmetros!$C$6*Parâmetros!$E$6) -> 2.384 | N44: =Parâmetros!$C$7*(F44+2*Parâmetros!$D$7+Parâmetros!$C$7*Parâmetros!$E$7) -> 3.786 | O44: =F44+2*Parâmetros!$D$8 -> 11.2 | P44: =F44+2*Parâmetros!$D$10 -> 12.92 | Q44: =G44+H44 -> 0 | S44: =S43+'Volumes por intervalo'!C43*(F43+F44)/2 -> 9240 | T44: =T43+'Volumes por intervalo'!H43 -> 464.1 | U44: =U43+'Volumes por intervalo'!J43 -> 1526.784 | V44: =V43+'Volumes por intervalo'!K43 -> 2002.56 | W44: =W43+'Volumes por intervalo'!L43 -> 3180.24 | X44: =X43+'Volumes por intervalo'!M43 -> 9408 | Y44: =Y43+'Volumes por intervalo'!N43 -> 9408 | Z44: =Z43+'Volumes por intervalo'!O43 -> 10852.8 | AA44: =AA43+'Volumes por intervalo'!P43 -> 0 | AB44: =AB43+'Volumes por intervalo'!Q43 -> 0 | ... AD44: =AD43+'Volumes por intervalo'!S43 -> 0
A45: 43+0,00 | B45: 43 | C45: 860 | D45: S01 | E45: T01 | F45: 11 | G45: 0 | H45: 0 | I45: Medida | K45: =Parâmetros!$C$4*(F45+2*Parâmetros!$D$4+Parâmetros!$C$4*Parâmetros!$E$4) -> 0.5525 | L45: =Parâmetros!$C$5*(F45+2*Parâmetros!$D$5+Parâmetros!$C$5*Parâmetros!$E$5) -> 1.8176 | M45: =Parâmetros!$C$6*(F45+2*Parâmetros!$D$6+Parâmetros!$C$6*Parâmetros!$E$6) -> 2.384 | N45: =Parâmetros!$C$7*(F45+2*Parâmetros!$D$7+Parâmetros!$C$7*Parâmetros!$E$7) -> 3.786 | O45: =F45+2*Parâmetros!$D$8 -> 11.2 | P45: =F45+2*Parâmetros!$D$10 -> 12.92 | Q45: =G45+H45 -> 0 | S45: =S44+'Volumes por intervalo'!C44*(F44+F45)/2 -> 9460 | T45: =T44+'Volumes por intervalo'!H44 -> 475.15 | U45: =U44+'Volumes por intervalo'!J44 -> 1563.136 | V45: =V44+'Volumes por intervalo'!K44 -> 2050.24 | W45: =W44+'Volumes por intervalo'!L44 -> 3255.96 | X45: =X44+'Volumes por intervalo'!M44 -> 9632 | Y45: =Y44+'Volumes por intervalo'!N44 -> 9632 | Z45: =Z44+'Volumes por intervalo'!O44 -> 11111.2 | AA45: =AA44+'Volumes por intervalo'!P44 -> 0 | AB45: =AB44+'Volumes por intervalo'!Q44 -> 0 | ... AD45: =AD44+'Volumes por intervalo'!S44 -> 0
A46: 44+0,00 | B46: 44 | C46: 880 | D46: S01 | E46: T01 | F46: 11 | G46: 0 | H46: 0 | I46: Medida | K46: =Parâmetros!$C$4*(F46+2*Parâmetros!$D$4+Parâmetros!$C$4*Parâmetros!$E$4) -> 0.5525 | L46: =Parâmetros!$C$5*(F46+2*Parâmetros!$D$5+Parâmetros!$C$5*Parâmetros!$E$5) -> 1.8176 | M46: =Parâmetros!$C$6*(F46+2*Parâmetros!$D$6+Parâmetros!$C$6*Parâmetros!$E$6) -> 2.384 | N46: =Parâmetros!$C$7*(F46+2*Parâmetros!$D$7+Parâmetros!$C$7*Parâmetros!$E$7) -> 3.786 | O46: =F46+2*Parâmetros!$D$8 -> 11.2 | P46: =F46+2*Parâmetros!$D$10 -> 12.92 | Q46: =G46+H46 -> 0 | S46: =S45+'Volumes por intervalo'!C45*(F45+F46)/2 -> 9680 | T46: =T45+'Volumes por intervalo'!H45 -> 486.2 | U46: =U45+'Volumes por intervalo'!J45 -> 1599.488 | V46: =V45+'Volumes por intervalo'!K45 -> 2097.92 | W46: =W45+'Volumes por intervalo'!L45 -> 3331.68 | X46: =X45+'Volumes por intervalo'!M45 -> 9856 | Y46: =Y45+'Volumes por intervalo'!N45 -> 9856 | Z46: =Z45+'Volumes por intervalo'!O45 -> 11369.6 | AA46: =AA45+'Volumes por intervalo'!P45 -> 0 | AB46: =AB45+'Volumes por intervalo'!Q45 -> 0 | ... AD46: =AD45+'Volumes por intervalo'!S45 -> 0
A47: 45+0,00 | B47: 45 | C47: 900 | D47: S01 | E47: T01 | F47: 11 | G47: 0 | H47: 0 | I47: Medida | K47: =Parâmetros!$C$4*(F47+2*Parâmetros!$D$4+Parâmetros!$C$4*Parâmetros!$E$4) -> 0.5525 | L47: =Parâmetros!$C$5*(F47+2*Parâmetros!$D$5+Parâmetros!$C$5*Parâmetros!$E$5) -> 1.8176 | M47: =Parâmetros!$C$6*(F47+2*Parâmetros!$D$6+Parâmetros!$C$6*Parâmetros!$E$6) -> 2.384 | N47: =Parâmetros!$C$7*(F47+2*Parâmetros!$D$7+Parâmetros!$C$7*Parâmetros!$E$7) -> 3.786 | O47: =F47+2*Parâmetros!$D$8 -> 11.2 | P47: =F47+2*Parâmetros!$D$10 -> 12.92 | Q47: =G47+H47 -> 0 | S47: =S46+'Volumes por intervalo'!C46*(F46+F47)/2 -> 9900 | T47: =T46+'Volumes por intervalo'!H46 -> 497.25 | U47: =U46+'Volumes por intervalo'!J46 -> 1635.84 | V47: =V46+'Volumes por intervalo'!K46 -> 2145.6 | W47: =W46+'Volumes por intervalo'!L46 -> 3407.4 | X47: =X46+'Volumes por intervalo'!M46 -> 10080 | Y47: =Y46+'Volumes por intervalo'!N46 -> 10080 | Z47: =Z46+'Volumes por intervalo'!O46 -> 11628 | AA47: =AA46+'Volumes por intervalo'!P46 -> 0 | AB47: =AB46+'Volumes por intervalo'!Q46 -> 0 | ... AD47: =AD46+'Volumes por intervalo'!S46 -> 0
A48: 46+0,00 | B48: 46 | C48: 920 | D48: S01 | E48: T01 | F48: 11 | G48: 0 | H48: 0 | I48: Medida | K48: =Parâmetros!$C$4*(F48+2*Parâmetros!$D$4+Parâmetros!$C$4*Parâmetros!$E$4) -> 0.5525 | L48: =Parâmetros!$C$5*(F48+2*Parâmetros!$D$5+Parâmetros!$C$5*Parâmetros!$E$5) -> 1.8176 | M48: =Parâmetros!$C$6*(F48+2*Parâmetros!$D$6+Parâmetros!$C$6*Parâmetros!$E$6) -> 2.384 | N48: =Parâmetros!$C$7*(F48+2*Parâmetros!$D$7+Parâmetros!$C$7*Parâmetros!$E$7) -> 3.786 | O48: =F48+2*Parâmetros!$D$8 -> 11.2 | P48: =F48+2*Parâmetros!$D$10 -> 12.92 | Q48: =G48+H48 -> 0 | S48: =S47+'Volumes por intervalo'!C47*(F47+F48)/2 -> 10120 | T48: =T47+'Volumes por intervalo'!H47 -> 508.3 | U48: =U47+'Volumes por intervalo'!J47 -> 1672.192 | V48: =V47+'Volumes por intervalo'!K47 -> 2193.28 | W48: =W47+'Volumes por intervalo'!L47 -> 3483.12 | X48: =X47+'Volumes por intervalo'!M47 -> 10304 | Y48: =Y47+'Volumes por intervalo'!N47 -> 10304 | Z48: =Z47+'Volumes por intervalo'!O47 -> 11886.4 | AA48: =AA47+'Volumes por intervalo'!P47 -> 0 | AB48: =AB47+'Volumes por intervalo'!Q47 -> 0 | ... AD48: =AD47+'Volumes por intervalo'!S47 -> 0
A49: 47+0,00 | B49: 47 | C49: 940 | D49: S01 | E49: T01 | F49: 11 | G49: 0 | H49: 0 | I49: Medida | K49: =Parâmetros!$C$4*(F49+2*Parâmetros!$D$4+Parâmetros!$C$4*Parâmetros!$E$4) -> 0.5525 | L49: =Parâmetros!$C$5*(F49+2*Parâmetros!$D$5+Parâmetros!$C$5*Parâmetros!$E$5) -> 1.8176 | M49: =Parâmetros!$C$6*(F49+2*Parâmetros!$D$6+Parâmetros!$C$6*Parâmetros!$E$6) -> 2.384 | N49: =Parâmetros!$C$7*(F49+2*Parâmetros!$D$7+Parâmetros!$C$7*Parâmetros!$E$7) -> 3.786 | O49: =F49+2*Parâmetros!$D$8 -> 11.2 | P49: =F49+2*Parâmetros!$D$10 -> 12.92 | Q49: =G49+H49 -> 0 | S49: =S48+'Volumes por intervalo'!C48*(F48+F49)/2 -> 10340 | T49: =T48+'Volumes por intervalo'!H48 -> 519.35 | U49: =U48+'Volumes por intervalo'!J48 -> 1708.544 | V49: =V48+'Volumes por intervalo'!K48 -> 2240.96 | W49: =W48+'Volumes por intervalo'!L48 -> 3558.84 | X49: =X48+'Volumes por intervalo'!M48 -> 10528 | Y49: =Y48+'Volumes por intervalo'!N48 -> 10528 | Z49: =Z48+'Volumes por intervalo'!O48 -> 12144.8 | AA49: =AA48+'Volumes por intervalo'!P48 -> 0 | AB49: =AB48+'Volumes por intervalo'!Q48 -> 0 | ... AD49: =AD48+'Volumes por intervalo'!S48 -> 0
A50: 48+0,00 | B50: 48 | C50: 960 | D50: S01 | E50: T01 | F50: 11 | G50: 0 | H50: 0 | I50: Medida | K50: =Parâmetros!$C$4*(F50+2*Parâmetros!$D$4+Parâmetros!$C$4*Parâmetros!$E$4) -> 0.5525 | L50: =Parâmetros!$C$5*(F50+2*Parâmetros!$D$5+Parâmetros!$C$5*Parâmetros!$E$5) -> 1.8176 | M50: =Parâmetros!$C$6*(F50+2*Parâmetros!$D$6+Parâmetros!$C$6*Parâmetros!$E$6) -> 2.384 | N50: =Parâmetros!$C$7*(F50+2*Parâmetros!$D$7+Parâmetros!$C$7*Parâmetros!$E$7) -> 3.786 | O50: =F50+2*Parâmetros!$D$8 -> 11.2 | P50: =F50+2*Parâmetros!$D$10 -> 12.92 | Q50: =G50+H50 -> 0 | S50: =S49+'Volumes por intervalo'!C49*(F49+F50)/2 -> 10560 | T50: =T49+'Volumes por intervalo'!H49 -> 530.4 | U50: =U49+'Volumes por intervalo'!J49 -> 1744.896 | V50: =V49+'Volumes por intervalo'!K49 -> 2288.64 | W50: =W49+'Volumes por intervalo'!L49 -> 3634.56 | X50: =X49+'Volumes por intervalo'!M49 -> 10752 | Y50: =Y49+'Volumes por intervalo'!N49 -> 10752 | Z50: =Z49+'Volumes por intervalo'!O49 -> 12403.2 | AA50: =AA49+'Volumes por intervalo'!P49 -> 0 | AB50: =AB49+'Volumes por intervalo'!Q49 -> 0 | ... AD50: =AD49+'Volumes por intervalo'!S49 -> 0
A51: 49+0,00 | B51: 49 | C51: 980 | D51: S01 | E51: T01 | F51: 11 | G51: 0 | H51: 0 | I51: Medida | K51: =Parâmetros!$C$4*(F51+2*Parâmetros!$D$4+Parâmetros!$C$4*Parâmetros!$E$4) -> 0.5525 | L51: =Parâmetros!$C$5*(F51+2*Parâmetros!$D$5+Parâmetros!$C$5*Parâmetros!$E$5) -> 1.8176 | M51: =Parâmetros!$C$6*(F51+2*Parâmetros!$D$6+Parâmetros!$C$6*Parâmetros!$E$6) -> 2.384 | N51: =Parâmetros!$C$7*(F51+2*Parâmetros!$D$7+Parâmetros!$C$7*Parâmetros!$E$7) -> 3.786 | O51: =F51+2*Parâmetros!$D$8 -> 11.2 | P51: =F51+2*Parâmetros!$D$10 -> 12.92 | Q51: =G51+H51 -> 0 | S51: =S50+'Volumes por intervalo'!C50*(F50+F51)/2 -> 10780 | T51: =T50+'Volumes por intervalo'!H50 -> 541.45 | U51: =U50+'Volumes por intervalo'!J50 -> 1781.248 | V51: =V50+'Volumes por intervalo'!K50 -> 2336.32 | W51: =W50+'Volumes por intervalo'!L50 -> 3710.28 | X51: =X50+'Volumes por intervalo'!M50 -> 10976 | Y51: =Y50+'Volumes por intervalo'!N50 -> 10976 | Z51: =Z50+'Volumes por intervalo'!O50 -> 12661.6 | AA51: =AA50+'Volumes por intervalo'!P50 -> 0 | AB51: =AB50+'Volumes por intervalo'!Q50 -> 0 | ... AD51: =AD50+'Volumes por intervalo'!S50 -> 0
A52: 50+0,00 | B52: 50 | C52: 1000 | D52: S01 | E52: T01 | F52: 12.9 | G52: 0 | H52: 0 | I52: Medida | K52: =Parâmetros!$C$4*(F52+2*Parâmetros!$D$4+Parâmetros!$C$4*Parâmetros!$E$4) -> 0.6475 | L52: =Parâmetros!$C$5*(F52+2*Parâmetros!$D$5+Parâmetros!$C$5*Parâmetros!$E$5) -> 2.1216 | M52: =Parâmetros!$C$6*(F52+2*Parâmetros!$D$6+Parâmetros!$C$6*Parâmetros!$E$6) -> 2.764 | N52: =Parâmetros!$C$7*(F52+2*Parâmetros!$D$7+Parâmetros!$C$7*Parâmetros!$E$7) -> 4.356 | O52: =F52+2*Parâmetros!$D$8 -> 13.1 | P52: =F52+2*Parâmetros!$D$10 -> 14.82 | Q52: =G52+H52 -> 0 | S52: =S51+'Volumes por intervalo'!C51*(F51+F52)/2 -> 11019 | T52: =T51+'Volumes por intervalo'!H51 -> 553.45 | U52: =U51+'Volumes por intervalo'!J51 -> 1820.64 | V52: =V51+'Volumes por intervalo'!K51 -> 2387.8 | W52: =W51+'Volumes por intervalo'!L51 -> 3791.7 | X52: =X51+'Volumes por intervalo'!M51 -> 11219 | Y52: =Y51+'Volumes por intervalo'!N51 -> 11219 | Z52: =Z51+'Volumes por intervalo'!O51 -> 12939 | AA52: =AA51+'Volumes por intervalo'!P51 -> 0 | AB52: =AB51+'Volumes por intervalo'!Q51 -> 0 | ... AD52: =AD51+'Volumes por intervalo'!S51 -> 0
A53: 51+0,00 | B53: 51 | C53: 1020 | D53: S01 | E53: T01 | F53: 11 | G53: 0 | H53: 0 | I53: Medida | K53: =Parâmetros!$C$4*(F53+2*Parâmetros!$D$4+Parâmetros!$C$4*Parâmetros!$E$4) -> 0.5525 | L53: =Parâmetros!$C$5*(F53+2*Parâmetros!$D$5+Parâmetros!$C$5*Parâmetros!$E$5) -> 1.8176 | M53: =Parâmetros!$C$6*(F53+2*Parâmetros!$D$6+Parâmetros!$C$6*Parâmetros!$E$6) -> 2.384 | N53: =Parâmetros!$C$7*(F53+2*Parâmetros!$D$7+Parâmetros!$C$7*Parâmetros!$E$7) -> 3.786 | O53: =F53+2*Parâmetros!$D$8 -> 11.2 | P53: =F53+2*Parâmetros!$D$10 -> 12.92 | Q53: =G53+H53 -> 0 | S53: =S52+'Volumes por intervalo'!C52*(F52+F53)/2 -> 11258 | T53: =T52+'Volumes por intervalo'!H52 -> 565.45 | U53: =U52+'Volumes por intervalo'!J52 -> 1860.032 | V53: =V52+'Volumes por intervalo'!K52 -> 2439.28 | W53: =W52+'Volumes por intervalo'!L52 -> 3873.12 | X53: =X52+'Volumes por intervalo'!M52 -> 11462 | Y53: =Y52+'Volumes por intervalo'!N52 -> 11462 | Z53: =Z52+'Volumes por intervalo'!O52 -> 13216.4 | AA53: =AA52+'Volumes por intervalo'!P52 -> 0 | AB53: =AB52+'Volumes por intervalo'!Q52 -> 0 | ... AD53: =AD52+'Volumes por intervalo'!S52 -> 0
A54: 52+0,00 | B54: 52 | C54: 1040 | D54: S01 | E54: T01 | F54: 11 | G54: 0 | H54: 0 | I54: Medida | K54: =Parâmetros!$C$4*(F54+2*Parâmetros!$D$4+Parâmetros!$C$4*Parâmetros!$E$4) -> 0.5525 | L54: =Parâmetros!$C$5*(F54+2*Parâmetros!$D$5+Parâmetros!$C$5*Parâmetros!$E$5) -> 1.8176 | M54: =Parâmetros!$C$6*(F54+2*Parâmetros!$D$6+Parâmetros!$C$6*Parâmetros!$E$6) -> 2.384 | N54: =Parâmetros!$C$7*(F54+2*Parâmetros!$D$7+Parâmetros!$C$7*Parâmetros!$E$7) -> 3.786 | O54: =F54+2*Parâmetros!$D$8 -> 11.2 | P54: =F54+2*Parâmetros!$D$10 -> 12.92 | Q54: =G54+H54 -> 0 | S54: =S53+'Volumes por intervalo'!C53*(F53+F54)/2 -> 11478 | T54: =T53+'Volumes por intervalo'!H53 -> 576.5 | U54: =U53+'Volumes por intervalo'!J53 -> 1896.384 | V54: =V53+'Volumes por intervalo'!K53 -> 2486.96 | W54: =W53+'Volumes por intervalo'!L53 -> 3948.84 | X54: =X53+'Volumes por intervalo'!M53 -> 11686 | Y54: =Y53+'Volumes por intervalo'!N53 -> 11686 | Z54: =Z53+'Volumes por intervalo'!O53 -> 13474.8 | AA54: =AA53+'Volumes por intervalo'!P53 -> 0 | AB54: =AB53+'Volumes por intervalo'!Q53 -> 0 | ... AD54: =AD53+'Volumes por intervalo'!S53 -> 0
A55: 53+0,00 | B55: 53 | C55: 1060 | D55: S01 | E55: T01 | F55: 11 | G55: 0 | H55: 0 | I55: Medida | K55: =Parâmetros!$C$4*(F55+2*Parâmetros!$D$4+Parâmetros!$C$4*Parâmetros!$E$4) -> 0.5525 | L55: =Parâmetros!$C$5*(F55+2*Parâmetros!$D$5+Parâmetros!$C$5*Parâmetros!$E$5) -> 1.8176 | M55: =Parâmetros!$C$6*(F55+2*Parâmetros!$D$6+Parâmetros!$C$6*Parâmetros!$E$6) -> 2.384 | N55: =Parâmetros!$C$7*(F55+2*Parâmetros!$D$7+Parâmetros!$C$7*Parâmetros!$E$7) -> 3.786 | O55: =F55+2*Parâmetros!$D$8 -> 11.2 | P55: =F55+2*Parâmetros!$D$10 -> 12.92 | Q55: =G55+H55 -> 0 | S55: =S54+'Volumes por intervalo'!C54*(F54+F55)/2 -> 11698 | T55: =T54+'Volumes por intervalo'!H54 -> 587.55 | U55: =U54+'Volumes por intervalo'!J54 -> 1932.736 | V55: =V54+'Volumes por intervalo'!K54 -> 2534.64 | W55: =W54+'Volumes por intervalo'!L54 -> 4024.56 | X55: =X54+'Volumes por intervalo'!M54 -> 11910 | Y55: =Y54+'Volumes por intervalo'!N54 -> 11910 | Z55: =Z54+'Volumes por intervalo'!O54 -> 13733.2 | AA55: =AA54+'Volumes por intervalo'!P54 -> 0 | AB55: =AB54+'Volumes por intervalo'!Q54 -> 0 | ... AD55: =AD54+'Volumes por intervalo'!S54 -> 0
A56: 54+0,00 | B56: 54 | C56: 1080 | D56: S01 | E56: T01 | F56: 11 | G56: 0 | H56: 0 | I56: Medida | K56: =Parâmetros!$C$4*(F56+2*Parâmetros!$D$4+Parâmetros!$C$4*Parâmetros!$E$4) -> 0.5525 | L56: =Parâmetros!$C$5*(F56+2*Parâmetros!$D$5+Parâmetros!$C$5*Parâmetros!$E$5) -> 1.8176 | M56: =Parâmetros!$C$6*(F56+2*Parâmetros!$D$6+Parâmetros!$C$6*Parâmetros!$E$6) -> 2.384 | N56: =Parâmetros!$C$7*(F56+2*Parâmetros!$D$7+Parâmetros!$C$7*Parâmetros!$E$7) -> 3.786 | O56: =F56+2*Parâmetros!$D$8 -> 11.2 | P56: =F56+2*Parâmetros!$D$10 -> 12.92 | Q56: =G56+H56 -> 0 | S56: =S55+'Volumes por intervalo'!C55*(F55+F56)/2 -> 11918 | T56: =T55+'Volumes por intervalo'!H55 -> 598.6 | U56: =U55+'Volumes por intervalo'!J55 -> 1969.088 | V56: =V55+'Volumes por intervalo'!K55 -> 2582.32 | W56: =W55+'Volumes por intervalo'!L55 -> 4100.28 | X56: =X55+'Volumes por intervalo'!M55 -> 12134 | Y56: =Y55+'Volumes por intervalo'!N55 -> 12134 | Z56: =Z55+'Volumes por intervalo'!O55 -> 13991.6 | AA56: =AA55+'Volumes por intervalo'!P55 -> 0 | AB56: =AB55+'Volumes por intervalo'!Q55 -> 0 | ... AD56: =AD55+'Volumes por intervalo'!S55 -> 0
... A96: 94+0,00 | B96: 94 | C96: 1880 | D96: S01 | E96: T01 | F96: 11 | G96: 0 | H96: 0 | I96: Medida | K96: =Parâmetros!$C$4*(F96+2*Parâmetros!$D$4+Parâmetros!$C$4*Parâmetros!$E$4) -> 0.5525 | L96: =Parâmetros!$C$5*(F96+2*Parâmetros!$D$5+Parâmetros!$C$5*Parâmetros!$E$5) -> 1.8176 | M96: =Parâmetros!$C$6*(F96+2*Parâmetros!$D$6+Parâmetros!$C$6*Parâmetros!$E$6) -> 2.384 | N96: =Parâmetros!$C$7*(F96+2*Parâmetros!$D$7+Parâmetros!$C$7*Parâmetros!$E$7) -> 3.786 | O96: =F96+2*Parâmetros!$D$8 -> 11.2 | P96: =F96+2*Parâmetros!$D$10 -> 12.92 | Q96: =G96+H96 -> 0 | S96: =S95+'Volumes por intervalo'!C95*(F95+F96)/2 -> 20718 | T96: =T95+'Volumes por intervalo'!H95 -> 1040.6 | U96: =U95+'Volumes por intervalo'!J95 -> 3423.168 | V96: =V95+'Volumes por intervalo'!K95 -> 4489.52 | W96: =W95+'Volumes por intervalo'!L95 -> 7129.08 | X96: =X95+'Volumes por intervalo'!M95 -> 21094 | Y96: =Y95+'Volumes por intervalo'!N95 -> 21094 | Z96: =Z95+'Volumes por intervalo'!O95 -> 24327.6 | AA96: =AA95+'Volumes por intervalo'!P95 -> 0 | AB96: =AB95+'Volumes por intervalo'!Q95 -> 0 | ... AD96: =AD95+'Volumes por intervalo'!S95 -> 0
A97: 95+0,00 | B97: 95 | C97: 1900 | D97: S01 | E97: T01 | F97: 11 | G97: 0 | H97: 0 | I97: Medida | J97: LD: elemento de 0.20 m (linha de acesso) descartado | K97: =Parâmetros!$C$4*(F97+2*Parâmetros!$D$4+Parâmetros!$C$4*Parâmetros!$E$4) -> 0.5525 | L97: =Parâmetros!$C$5*(F97+2*Parâmetros!$D$5+Parâmetros!$C$5*Parâmetros!$E$5) -> 1.8176 | M97: =Parâmetros!$C$6*(F97+2*Parâmetros!$D$6+Parâmetros!$C$6*Parâmetros!$E$6) -> 2.384 | N97: =Parâmetros!$C$7*(F97+2*Parâmetros!$D$7+Parâmetros!$C$7*Parâmetros!$E$7) -> 3.786 | O97: =F97+2*Parâmetros!$D$8 -> 11.2 | P97: =F97+2*Parâmetros!$D$10 -> 12.92 | Q97: =G97+H97 -> 0 | S97: =S96+'Volumes por intervalo'!C96*(F96+F97)/2 -> 20938 | T97: =T96+'Volumes por intervalo'!H96 -> 1051.65 | U97: =U96+'Volumes por intervalo'!J96 -> 3459.52 | V97: =V96+'Volumes por intervalo'!K96 -> 4537.2 | W97: =W96+'Volumes por intervalo'!L96 -> 7204.8 | X97: =X96+'Volumes por intervalo'!M96 -> 21318 | Y97: =Y96+'Volumes por intervalo'!N96 -> 21318 | Z97: =Z96+'Volumes por intervalo'!O96 -> 24586 | AA97: =AA96+'Volumes por intervalo'!P96 -> 0 | AB97: =AB96+'Volumes por intervalo'!Q96 -> 0 | ... AD97: =AD96+'Volumes por intervalo'!S96 -> 0
A98: 96+0,00 | B98: 96 | C98: 1920 | D98: S01 | E98: T01 | F98: 11 | G98: 0 | H98: 0 | I98: Medida | K98: =Parâmetros!$C$4*(F98+2*Parâmetros!$D$4+Parâmetros!$C$4*Parâmetros!$E$4) -> 0.5525 | L98: =Parâmetros!$C$5*(F98+2*Parâmetros!$D$5+Parâmetros!$C$5*Parâmetros!$E$5) -> 1.8176 | M98: =Parâmetros!$C$6*(F98+2*Parâmetros!$D$6+Parâmetros!$C$6*Parâmetros!$E$6) -> 2.384 | N98: =Parâmetros!$C$7*(F98+2*Parâmetros!$D$7+Parâmetros!$C$7*Parâmetros!$E$7) -> 3.786 | O98: =F98+2*Parâmetros!$D$8 -> 11.2 | P98: =F98+2*Parâmetros!$D$10 -> 12.92 | Q98: =G98+H98 -> 0 | S98: =S97+'Volumes por intervalo'!C97*(F97+F98)/2 -> 21158 | T98: =T97+'Volumes por intervalo'!H97 -> 1062.7 | U98: =U97+'Volumes por intervalo'!J97 -> 3495.872 | V98: =V97+'Volumes por intervalo'!K97 -> 4584.88 | W98: =W97+'Volumes por intervalo'!L97 -> 7280.52 | X98: =X97+'Volumes por intervalo'!M97 -> 21542 | Y98: =Y97+'Volumes por intervalo'!N97 -> 21542 | Z98: =Z97+'Volumes por intervalo'!O97 -> 24844.4 | AA98: =AA97+'Volumes por intervalo'!P97 -> 0 | AB98: =AB97+'Volumes por intervalo'!Q97 -> 0 | ... AD98: =AD97+'Volumes por intervalo'!S97 -> 0
A99: 97+0,00 | B99: 97 | C99: 1940 | D99: S01 | E99: T01 | F99: 11 | G99: 0 | H99: 0 | I99: Medida | K99: =Parâmetros!$C$4*(F99+2*Parâmetros!$D$4+Parâmetros!$C$4*Parâmetros!$E$4) -> 0.5525 | L99: =Parâmetros!$C$5*(F99+2*Parâmetros!$D$5+Parâmetros!$C$5*Parâmetros!$E$5) -> 1.8176 | M99: =Parâmetros!$C$6*(F99+2*Parâmetros!$D$6+Parâmetros!$C$6*Parâmetros!$E$6) -> 2.384 | N99: =Parâmetros!$C$7*(F99+2*Parâmetros!$D$7+Parâmetros!$C$7*Parâmetros!$E$7) -> 3.786 | O99: =F99+2*Parâmetros!$D$8 -> 11.2 | P99: =F99+2*Parâmetros!$D$10 -> 12.92 | Q99: =G99+H99 -> 0 | S99: =S98+'Volumes por intervalo'!C98*(F98+F99)/2 -> 21378 | T99: =T98+'Volumes por intervalo'!H98 -> 1073.75 | U99: =U98+'Volumes por intervalo'!J98 -> 3532.224 | V99: =V98+'Volumes por intervalo'!K98 -> 4632.56 | W99: =W98+'Volumes por intervalo'!L98 -> 7356.24 | X99: =X98+'Volumes por intervalo'!M98 -> 21766 | Y99: =Y98+'Volumes por intervalo'!N98 -> 21766 | Z99: =Z98+'Volumes por intervalo'!O98 -> 25102.8 | AA99: =AA98+'Volumes por intervalo'!P98 -> 0 | AB99: =AB98+'Volumes por intervalo'!Q98 -> 0 | ... AD99: =AD98+'Volumes por intervalo'!S98 -> 0
A100: 98+0,00 | B100: 98 | C100: 1960 | D100: S01 | E100: T01 | F100: 11 | G100: 0 | H100: 0 | I100: Medida | K100: =Parâmetros!$C$4*(F100+2*Parâmetros!$D$4+Parâmetros!$C$4*Parâmetros!$E$4) -> 0.5525 | L100: =Parâmetros!$C$5*(F100+2*Parâmetros!$D$5+Parâmetros!$C$5*Parâmetros!$E$5) -> 1.8176 | M100: =Parâmetros!$C$6*(F100+2*Parâmetros!$D$6+Parâmetros!$C$6*Parâmetros!$E$6) -> 2.384 | N100: =Parâmetros!$C$7*(F100+2*Parâmetros!$D$7+Parâmetros!$C$7*Parâmetros!$E$7) -> 3.786 | O100: =F100+2*Parâmetros!$D$8 -> 11.2 | P100: =F100+2*Parâmetros!$D$10 -> 12.92 | Q100: =G100+H100 -> 0 | S100: =S99+'Volumes por intervalo'!C99*(F99+F100)/2 -> 21598 | T100: =T99+'Volumes por intervalo'!H99 -> 1084.8 | U100: =U99+'Volumes por intervalo'!J99 -> 3568.576 | V100: =V99+'Volumes por intervalo'!K99 -> 4680.24 | W100: =W99+'Volumes por intervalo'!L99 -> 7431.96 | X100: =X99+'Volumes por intervalo'!M99 -> 21990 | Y100: =Y99+'Volumes por intervalo'!N99 -> 21990 | Z100: =Z99+'Volumes por intervalo'!O99 -> 25361.2 | AA100: =AA99+'Volumes por intervalo'!P99 -> 0 | AB100: =AB99+'Volumes por intervalo'!Q99 -> 0 | ... AD100: =AD99+'Volumes por intervalo'!S99 -> 0
A101: 99+0,00 | B101: 99 | C101: 1980 | D101: S01 | E101: T01 | F101: 11 | G101: 0 | H101: 0 | I101: Medida | K101: =Parâmetros!$C$4*(F101+2*Parâmetros!$D$4+Parâmetros!$C$4*Parâmetros!$E$4) -> 0.5525 | L101: =Parâmetros!$C$5*(F101+2*Parâmetros!$D$5+Parâmetros!$C$5*Parâmetros!$E$5) -> 1.8176 | M101: =Parâmetros!$C$6*(F101+2*Parâmetros!$D$6+Parâmetros!$C$6*Parâmetros!$E$6) -> 2.384 | N101: =Parâmetros!$C$7*(F101+2*Parâmetros!$D$7+Parâmetros!$C$7*Parâmetros!$E$7) -> 3.786 | O101: =F101+2*Parâmetros!$D$8 -> 11.2 | P101: =F101+2*Parâmetros!$D$10 -> 12.92 | Q101: =G101+H101 -> 0 | S101: =S100+'Volumes por intervalo'!C100*(F100+F101)/2 -> 21818 | T101: =T100+'Volumes por intervalo'!H100 -> 1095.85 | U101: =U100+'Volumes por intervalo'!J100 -> 3604.928 | V101: =V100+'Volumes por intervalo'!K100 -> 4727.92 | W101: =W100+'Volumes por intervalo'!L100 -> 7507.68 | X101: =X100+'Volumes por intervalo'!M100 -> 22214 | Y101: =Y100+'Volumes por intervalo'!N100 -> 22214 | Z101: =Z100+'Volumes por intervalo'!O100 -> 25619.6 | AA101: =AA100+'Volumes por intervalo'!P100 -> 0 | AB101: =AB100+'Volumes por intervalo'!Q100 -> 0 | ... AD101: =AD100+'Volumes por intervalo'!S100 -> 0
A102: 100+0,00 | B102: 100 | C102: 2000 | D102: S01 | E102: T01 | F102: 11 | G102: 0 | H102: 0 | I102: Medida | K102: =Parâmetros!$C$4*(F102+2*Parâmetros!$D$4+Parâmetros!$C$4*Parâmetros!$E$4) -> 0.5525 | L102: =Parâmetros!$C$5*(F102+2*Parâmetros!$D$5+Parâmetros!$C$5*Parâmetros!$E$5) -> 1.8176 | M102: =Parâmetros!$C$6*(F102+2*Parâmetros!$D$6+Parâmetros!$C$6*Parâmetros!$E$6) -> 2.384 | N102: =Parâmetros!$C$7*(F102+2*Parâmetros!$D$7+Parâmetros!$C$7*Parâmetros!$E$7) -> 3.786 | O102: =F102+2*Parâmetros!$D$8 -> 11.2 | P102: =F102+2*Parâmetros!$D$10 -> 12.92 | Q102: =G102+H102 -> 0 | S102: =S101+'Volumes por intervalo'!C101*(F101+F102)/2 -> 22038 | T102: =T101+'Volumes por intervalo'!H101 -> 1106.9 | U102: =U101+'Volumes por intervalo'!J101 -> 3641.28 | V102: =V101+'Volumes por intervalo'!K101 -> 4775.6 | W102: =W101+'Volumes por intervalo'!L101 -> 7583.4 | X102: =X101+'Volumes por intervalo'!M101 -> 22438 | Y102: =Y101+'Volumes por intervalo'!N101 -> 22438 | Z102: =Z101+'Volumes por intervalo'!O101 -> 25878 | AA102: =AA101+'Volumes por intervalo'!P101 -> 0 | AB102: =AB101+'Volumes por intervalo'!Q101 -> 0 | ... AD102: =AD101+'Volumes por intervalo'!S101 -> 0
